Workbook

Sheet Summary
A1: The EverBloom Center for Women: three-case summary
A2: Green = linked from the monthly sheets. Change inputs on the Assumptions and Capital tabs; everything here updates.
A3: Where women heal, rebuild and become.
A4: Metric ($) | B4: Conservative | C4: Base | D4: Upside
A5: Year 1 revenue | B5: =SUMIF('Conservative Monthly'!$F$5:$AO$5,1,'Conservative Monthly'!$F$22:$AO$22) -> 1701913.4 | C5: =SUMIF('Base Monthly'!$F$5:$AO$5,1,'Base Monthly'!$F$22:$AO$22) -> 2693492.4 | D5: =SUMIF('Upside Monthly'!$F$5:$AO$5,1,'Upside Monthly'!$F$22:$AO$22) -> 3804714.4
A6: Year 1 EBITDA | B6: =SUMIF('Conservative Monthly'!$F$5:$AO$5,1,'Conservative Monthly'!$F$46:$AO$46) -> -1483353.4 | C6: =SUMIF('Base Monthly'!$F$5:$AO$5,1,'Base Monthly'!$F$46:$AO$46) -> -523933.21 | D6: =SUMIF('Upside Monthly'!$F$5:$AO$5,1,'Upside Monthly'!$F$46:$AO$46) -> 559307.36
A7: Year 1 EBITDA margin | B7: =IF(B5=0,0,B6/B5) -> -0.87157984 | C7: =IF(C5=0,0,C6/C5) -> -0.19451817 | D7: =IF(D5=0,0,D6/D5) -> 0.14700377
A8: Year 1 net cash flow | B8: =SUMIF('Conservative Monthly'!$F$5:$AO$5,1,'Conservative Monthly'!$F$51:$AO$51) -> -3494342.5 | C8: =SUMIF('Base Monthly'!$F$5:$AO$5,1,'Base Monthly'!$F$51:$AO$51) -> -2907300.1 | D8: =SUMIF('Upside Monthly'!$F$5:$AO$5,1,'Upside Monthly'!$F$51:$AO$51) -> -2244087.5
A9: Year 2 revenue | B9: =SUMIF('Conservative Monthly'!$F$5:$AO$5,2,'Conservative Monthly'!$F$22:$AO$22) -> 5991113.8 | C9: =SUMIF('Base Monthly'!$F$5:$AO$5,2,'Base Monthly'!$F$22:$AO$22) -> 8512508.7 | D9: =SUMIF('Upside Monthly'!$F$5:$AO$5,2,'Upside Monthly'!$F$22:$AO$22) -> 11066665
A10: Year 2 EBITDA | B10: =SUMIF('Conservative Monthly'!$F$5:$AO$5,2,'Conservative Monthly'!$F$46:$AO$46) -> 1227960.5 | C10: =SUMIF('Base Monthly'!$F$5:$AO$5,2,'Base Monthly'!$F$46:$AO$46) -> 3713563 | D10: =SUMIF('Upside Monthly'!$F$5:$AO$5,2,'Upside Monthly'!$F$46:$AO$46) -> 6248932.8
A11: Year 2 EBITDA margin | B11: =IF(B9=0,0,B10/B9) -> 0.20496364 | C11: =IF(C9=0,0,C10/C9) -> 0.43624778 | D11: =IF(D9=0,0,D10/D9) -> 0.56466271
A12: Year 2 net cash flow | B12: =SUMIF('Conservative Monthly'!$F$5:$AO$5,2,'Conservative Monthly'!$F$51:$AO$51) -> 911840.67 | C12: =SUMIF('Base Monthly'!$F$5:$AO$5,2,'Base Monthly'!$F$51:$AO$51) -> 3326334.8 | D12: =SUMIF('Upside Monthly'!$F$5:$AO$5,2,'Upside Monthly'!$F$51:$AO$51) -> 5845050
A13: Year 3 revenue | B13: =SUMIF('Conservative Monthly'!$F$5:$AO$5,3,'Conservative Monthly'!$F$22:$AO$22) -> 6540486.8 | C13: =SUMIF('Base Monthly'!$F$5:$AO$5,3,'Base Monthly'!$F$22:$AO$22) -> 9245496.3 | D13: =SUMIF('Upside Monthly'!$F$5:$AO$5,3,'Upside Monthly'!$F$22:$AO$22) -> 11919855
A14: Year 3 EBITDA | B14: =SUMIF('Conservative Monthly'!$F$5:$AO$5,3,'Conservative Monthly'!$F$46:$AO$46) -> 1638062.1 | C14: =SUMIF('Base Monthly'!$F$5:$AO$5,3,'Base Monthly'!$F$46:$AO$46) -> 4308589.3 | D14: =SUMIF('Upside Monthly'!$F$5:$AO$5,3,'Upside Monthly'!$F$46:$AO$46) -> 6968973.9
A15: Year 3 EBITDA margin | B15: =IF(B13=0,0,B14/B13) -> 0.25044957 | C15: =IF(C13=0,0,C14/C13) -> 0.46602033 | D15: =IF(D13=0,0,D14/D13) -> 0.58465258
A16: Year 3 net cash flow | B16: =SUMIF('Conservative Monthly'!$F$5:$AO$5,3,'Conservative Monthly'!$F$51:$AO$51) -> 1572837.8 | C16: =SUMIF('Base Monthly'!$F$5:$AO$5,3,'Base Monthly'!$F$51:$AO$51) -> 4224745.5 | D16: =SUMIF('Upside Monthly'!$F$5:$AO$5,3,'Upside Monthly'!$F$51:$AO$51) -> 6864943.1
A18: Peak capital need | B18: ='Conservative Monthly'!B56 -> 3551434.9 | C18: ='Base Monthly'!B56 -> 2986131.8 | D18: ='Upside Monthly'!B56 -> 2758115.9
A19: Month of peak need | B19: ='Conservative Monthly'!B57 -> 14 | C19: ='Base Monthly'!B57 -> 11 | D19: ='Upside Monthly'!B57 -> 9
A20: EBITDA positive from month | B20: ='Conservative Monthly'!B58 -> 12 | C20: ='Base Monthly'!B58 -> 9 | D20: ='Upside Monthly'!B58 -> 7
A21: Cash flow positive from month | B21: ='Conservative Monthly'!B59 -> 15 | C21: ='Base Monthly'!B59 -> 12 | D21: ='Upside Monthly'!B59 -> 10
A22: Cumulative cash payback month | B22: ='Conservative Monthly'!B60 -> After M36 | C22: ='Base Monthly'!B60 -> 23 | D22: ='Upside Monthly'!B60 -> 18
A23: Cumulative cash at Month 36 | B23: ='Conservative Monthly'!B61 -> -1009664 | C23: ='Base Monthly'!B61 -> 4643780.1 | D23: ='Upside Monthly'!B61 -> 10465906
A25: Year 1 includes the five pre-opening months (Months 1-5); first patients in Month 6. Months count from project start.

Sheet Assumptions
A1: The EverBloom Center for Women: model assumptions
A2: Blue = input you can change. Black = formula. Yellow = key lever. Columns B-D feed the three monthly sheets. All figures are illustrative planning assumptions (source: management estimates), to be validated against payer contracts and the chosen site.
A4: Assumption | B4: Conservative | C4: Base | D4: Upside | E4: Notes
A5: Capacity and calendar
A6: Residential beds | B6: 20 | C6: =$B6 -> 20 | D6: =$B6 -> 20 | E6: Women-only residential
A7: Opening month (first admissions) | B7: 6 | C7: =$B7 -> 6 | D7: =$B7 -> 6 | E7: Months counted from project start / funding. Management has opened comparable Florida sites in 4 to 6 months
A8: Days per month | B8: 30.4 | C8: =$B8 -> 30.4 | D8: =$B8 -> 30.4
A9: PHP program days per month | B9: 21.7 | C9: =$B9 -> 21.7 | D9: =$B9 -> 21.7 | E9: About 5 days a week
A10: IOP program days per month | B10: 17.3 | C10: =$B10 -> 17.3 | D10: =$B10 -> 17.3 | E10: About 4 days a week
A11: Volumes and rates
A12: Residential rate per patient day | B12: 950 | C12: 1100 | D12: 1300 | E12: Blended net rate; upside reflects premium/luxury positioning
A13: Stabilized occupancy through Month 24 | B13: 0.72 | C13: 0.82 | D13: 0.85
A14: Stabilized occupancy from Month 25 | B14: 0.75 | C14: 0.85 | D14: 0.88
A15: PHP target average daily census | B15: 8 | C15: 12 | D15: 15
A16: PHP rate per patient day | B16: 475 | C16: 550 | D16: 625
A17: IOP target average daily census | B17: 10 | C17: 15 | D17: 20
A18: IOP rate per patient day | B18: 240 | C18: 275 | D18: 310
A19: Outpatient visits per month at target | B19: 120 | C19: 200 | D19: 280
A20: Outpatient rate per visit | B20: 150 | C20: =$B20 -> 150 | D20: =$B20 -> 150
A21: PHP starts (months after opening) | B21: 2 | C21: =$B21 -> 2 | D21: =$B21 -> 2
A22: PHP months to reach target | B22: 8 | C22: =$B22 -> 8 | D22: =$B22 -> 8
A23: IOP starts (months after opening) | B23: 3 | C23: =$B23 -> 3 | D23: =$B23 -> 3
A24: IOP months to reach target | B24: 9 | C24: =$B24 -> 9 | D24: =$B24 -> 9
A25: Outpatient starts (months after opening) | B25: 6 | C25: =$B25 -> 6 | D25: =$B25 -> 6
A26: Outpatient months to reach target | B26: 6 | C26: =$B26 -> 6 | D26: =$B26 -> 6
A27: Rate increase from Month 25 | B27: 0.03 | C27: =$B27 -> 0.03 | D27: =$B27 -> 0.03
A28: Cost inflation per year | B28: 0.03 | C28: =$B28 -> 0.03 | D28: =$B28 -> 0.03
A29: Collections (share of a month's billed revenue collected)
A30: Denials and bad debt reserve (% of billed revenue) | B30: 0.08 | C30: =$B30 -> 0.08 | D30: =$B30 -> 0.08 | E30: Claims that are denied, underpaid or never collected
A31: Collected same month | B31: 0 | C31: =$B31 -> 0 | D31: =$B31 -> 0
A32: Collected 1 month later | B32: 0.2 | C32: =$B32 -> 0.2 | D32: =$B32 -> 0.2
A33: Collected 2 months later | B33: 0.55 | C33: =$B33 -> 0.55 | D33: =$B33 -> 0.55 | E33: In-network contracts take 30-180+ days; OON PPO and self-pay from day one
A34: Collected 3 months later | B34: 0.25 | C34: =$B34 -> 0.25 | D34: =$B34 -> 0.25
A35: Payroll (roles, FTEs and rates live on the Staffing tab)
A36: Payroll taxes and benefits (% of wages) | B36: 0.22 | C36: =$B36 -> 0.22 | D36: =$B36 -> 0.22 | E36: FICA, FUTA/SUTA, workers comp, health benefits
A37: PRN, overtime and PTO coverage (% of payroll) | B37: 0.1 | C37: =$B37 -> 0.1 | D37: =$B37 -> 0.1 | E37: Lean 24/7 posts need fill-ins for sick days, PTO and turnover
A38: Operating expenses (monthly unless noted). Everything is in-house: no billing company, no marketing agency
A39: Facility rent once open | B39: 45000 | C39: =$B39 -> 45000 | D39: =$B39 -> 45000 | E39: Leased campus
A40: Pre-opening rent (% of full) | B40: 0.5 | C40: =$B40 -> 0.5 | D40: =$B40 -> 0.5
A41: Pre-opening rent start month | B41: 3 | C41: =$B41 -> 3 | D41: =$B41 -> 3 | E41: Half rent during buildout
A42: Utilities once open | B42: 12000 | C42: =$B42 -> 12000 | D42: =$B42 -> 12000
A43: Utilities before opening | B43: 4000 | C43: =$B43 -> 4000 | D43: =$B43 -> 4000
A44: Pre-opening utilities start month | B44: 4 | C44: =$B44 -> 4 | D44: =$B44 -> 4
A45: Food per residential patient day (ingredients; cooks are on staff) | B45: 20 | C45: =$B45 -> 20 | D45: =$B45 -> 20
A46: Medical supplies per residential patient day | B46: 20 | C46: =$B46 -> 20 | D46: =$B46 -> 20
A47: Supplies per PHP/IOP patient day | B47: 3 | C47: =$B47 -> 3 | D47: =$B47 -> 3
A48: Wellness and activity supplies once open | B48: 3000 | C48: =$B48 -> 3000 | D48: =$B48 -> 3000 | E48: Yoga mats, art supplies, outings
A49: Contracted wellness services once open | B49: 8000 | C49: =$B49 -> 8000 | D49: =$B49 -> 8000 | E49: Acupuncture, massage, sound therapy, guest instructors, equine or nature sessions
A50: Medical director stipend (Dr. Bokhari) | B50: 5000 | C50: =$B50 -> 5000 | D50: =$B50 -> 5000 | E50: Oversight, protocols, NP supervision; not direct patient care
A51: Medical director stipend start month | B51: 3 | C51: =$B51 -> 3 | D51: =$B51 -> 3
A52: Insurance (malpractice, liability, property, D&O) | B52: 12500 | C52: =$B52 -> 12500 | D52: =$B52 -> 12500
A53: Insurance start month | B53: 4 | C53: =$B53 -> 4 | D53: =$B53 -> 4
A54: Technology, EHR and phones | B54: 10000 | C54: =$B54 -> 10000 | D54: =$B54 -> 10000
A55: Technology start month | B55: 3 | C55: =$B55 -> 3 | D55: =$B55 -> 3
A56: Clearinghouse and billing software once open | B56: 2500 | C56: =$B56 -> 2500 | D56: =$B56 -> 2500 | E56: In-house billing team; no % of collections to a vendor
A57: Paid media once open (Google, Meta, directories) | B57: 25000 | C57: =$B57 -> 25000 | D57: =$B57 -> 25000 | E57: Run by in-house digital team; no agency fees
A58: Paid media before opening | B58: 10000 | C58: =$B58 -> 10000 | D58: =$B58 -> 10000 | E58: Pre-launch awareness and search
A59: Pre-launch paid media start month | B59: 4 | C59: =$B59 -> 4 | D59: =$B59 -> 4
A60: Marketing software (SEO tools, call tracking, CRM) | B60: 3000 | C60: =$B60 -> 3000 | D60: =$B60 -> 3000
A61: Marketing software start month | B61: 2 | C61: =$B61 -> 2 | D61: =$B61 -> 2
A62: Accreditation survey fee (one-time) | B62: 25000 | C62: =$B62 -> 25000 | D62: =$B62 -> 25000 | E62: Joint Commission or CARF; survey requires the program to be open and treating patients
A63: Accreditation survey month | B63: 11 | C63: =$B63 -> 11 | D63: =$B63 -> 11 | E63: About 5 months after opening
A64: Annual accreditation fees after survey | B64: 10000 | C64: =$B64 -> 10000 | D64: =$B64 -> 10000
A65: Professional fees before opening | B65: 15000 | C65: =$B65 -> 15000 | D65: =$B65 -> 15000
A66: Professional fees once open (legal, audit) | B66: 8000 | C66: =$B66 -> 8000 | D66: =$B66 -> 8000
A67: Other operating (repairs, IT support, travel, admin) once open | B67: 12000 | C67: =$B67 -> 12000 | D67: =$B67 -> 12000 | E67: No maintenance or IT staff; contracted as needed
A68: Residential occupancy ramp (month after opening)
A69: Open month 1 | B69: 0.15 | C69: 0.25 | D69: 0.3
A70: Open month 2 | B70: 0.25 | C70: 0.4 | D70: 0.5
A71: Open month 3 | B71: 0.35 | C71: 0.5 | D71: 0.62
A72: Open month 4 | B72: 0.45 | C72: 0.6 | D72: 0.72
A73: Open month 5 | B73: 0.5 | C73: 0.65 | D73: 0.78
A74: Open month 6 | B74: 0.55 | C74: 0.7 | D74: 0.82
A75: Open month 7 | B75: 0.6 | C75: 0.75 | D75: 0.85
A76: Open month 8 | B76: 0.65 | C76: 0.78 | D76: 0.85
A77: Open month 9 | B77: 0.68 | C77: 0.78 | D77: 0.85
A78: Open month 10 | B78: 0.7 | C78: 0.8 | D78: 0.85
A79: Open month 11 | B79: 0.72 | C79: 0.8 | D79: 0.85 | E79: After month 11, stabilized occupancy applies

Sheet Capital
A1: Startup capital: one-time costs by month, and uses of funds
A3: One-time cost ($) | B3: M1 | C3: M2 | D3: M3 | E3: M4 | F3: M5 | G3: M6 | H3: M7 | I3: M8 | J3: Total
A4: Security deposit | B4: 90000 | C4: 0 | D4: 0 | E4: 0 | F4: 0 | G4: 0 | H4: 0 | I4: 0 | J4: =SUM(B4:I4) -> 90000
A5: Buildout, life safety, ADA | B5: 0 | C5: 125000 | D5: 150000 | E5: 125000 | F5: 50000 | G5: 0 | H5: 0 | I5: 0 | J5: =SUM(B5:I5) -> 450000
A6: Furniture, fixtures and equipment | B6: 0 | C6: 0 | D6: 0 | E6: 100000 | F6: 175000 | G6: 0 | H6: 0 | I6: 0 | J6: =SUM(B6:I6) -> 275000
A7: Technology and EHR implementation | B7: 0 | C7: 0 | D7: 30000 | E7: 30000 | F7: 25000 | G7: 0 | H7: 0 | I7: 0 | J7: =SUM(B7:I7) -> 85000
A8: Licensing, accreditation and legal | B8: 30000 | C8: 20000 | D8: 20000 | E8: 20000 | F8: 15000 | G8: 15000 | H8: 0 | I8: 0 | J8: =SUM(B8:I8) -> 120000
A9: Credentialing and payer contracting | B9: 10000 | C9: 10000 | D9: 10000 | E9: 10000 | F9: 0 | G9: 0 | H9: 0 | I9: 0 | J9: =SUM(B9:I9) -> 40000
A10: Recruiting and training | B10: 0 | C10: 0 | D10: 15000 | E10: 20000 | F10: 25000 | G10: 0 | H10: 0 | I10: 0 | J10: =SUM(B10:I10) -> 60000
A11: Vehicles (2 transport vans) | B11: 0 | C11: 0 | D11: 0 | E11: 0 | F11: 80000 | G11: 0 | H11: 0 | I11: 0 | J11: =SUM(B11:I11) -> 80000
A12: Brand, website and launch marketing | B12: 15000 | C12: 20000 | D12: 20000 | E12: 20000 | F12: 0 | G12: 0 | H12: 0 | I12: 0 | J12: =SUM(B12:I12) -> 75000
A13: Total one-time costs | B13: =SUM(B4:B12) -> 145000 | C13: =SUM(C4:C12) -> 175000 | D13: =SUM(D4:D12) -> 245000 | E13: =SUM(E4:E12) -> 325000 | F13: =SUM(F4:F12) -> 370000 | G13: =SUM(G4:G12) -> 15000 | H13: =SUM(H4:H12) -> 0 | I13: =SUM(I4:I12) -> 0 | J13: =SUM(J4:J12) -> 1275000
A14: Source: management estimates for a leased 20-bed campus that needs light renovation, not new construction; a 4 to 6 month opening depends on finding that kind of property.
A16: Uses of funds (base case) | B16: $
A17: One-time startup costs (above) | B17: =J13 -> 1275000
A18: Pre-opening payroll and operations | B18: =SUMPRODUCT(('Base Monthly'!$F$6:$AO$6<0)*('Base Monthly'!$F$28:$AO$28+'Base Monthly'!$F$45:$AO$45)) -> 596790.1
A19: Ramp operating support and working capital | B19: ='Base Monthly'!B56-B17-B18 -> 1114341.7
A20: Reserve and contingency | B20: =B22-'Base Monthly'!B56 -> 513868.17
A21: Total uses | B21: =SUM(B17:B20) -> 3500000
A22: Equity raise (input) | B22: 3500000
A23: Recommended credit line (input) | B23: 500000
A24: Conservative case peak need | B24: ='Conservative Monthly'!B56 -> 3551434.9
A25: Raise + credit line covers conservative peak? | B25: =IF(B22+B23>=B24,"Yes","No") -> Yes

Sheet Staffing
A1: EverBloom lean staffing model: every role, FTE, Florida market rate and planned pay
A2: Lean and in-house: the corporate COO covers licensing, payers, HR, brand and content, and an onsite Administrator runs the site day to day; one RN (Director of Nursing) with LPNs on every shift; one psychiatric NP. Medical director stipend and contracted wellness services are operating expenses on the Assumptions tab. Market median = Florida statewide annual median, BLS OEWS 2025 via O*NET OnLine. Planned rate = management input (blue). Census-driven roles scale with patient volume but never drop below the minimum FTE.
A4: Department | B4: Role | C4: Staffing type | D4: FTE at stabilized census | E4: Minimum FTE | F4: Start month | G4: Market reference (BLS occupation) | H4: FL market median | I4: Planned annual rate | J4: Burden applies (1=yes) | K4: Coverage and notes | L4: Stabilized annual cost
A5: Leadership | B5: Chief Operating Officer (Ashlee Bryant), corporate | C5: Fixed | D5: 1 | F5: 1 | G5: Medical and health services managers | H5: 120360 | I5: 200000 | J5: 1 | K5: Everything above the site: licensing, payers, finance, HR, brand, content, compliance, growth | L5: =D5*I5*(1+Assumptions!$B$36*J5) -> 244000
A6: Leadership | B6: Facility Administrator (onsite) | C6: Fixed | D6: 1 | F6: 5 | G6: Medical and health services managers | H6: 120360 | I6: 85000 | J6: 1 | K6: Runs the site day to day: schedules, staff, patient and family issues, facility; starts 30 days before opening | L6: =D6*I6*(1+Assumptions!$B$36*J6) -> 103700
A7: Clinical leadership | B7: Clinical Director (LCSW / LMHC) | C7: Fixed | D7: 1 | F7: 3 | G7: Medical and health services managers | H7: 120360 | I7: 110000 | J7: 1 | K7: Runs the clinical program and the tiered curriculum; carries a small caseload | L7: =D7*I7*(1+Assumptions!$B$36*J7) -> 134200
A8: Clinical leadership | B8: Director of Nursing (RN) | C8: Fixed | D8: 1 | F8: 4 | G8: Registered nurses | H8: 84190 | I8: 105000 | J8: 1 | K8: The one RN: directs LPNs, on call nights and weekends | L8: =D8*I8*(1+Assumptions!$B$36*J8) -> 128100
A9: Clinical leadership | B9: Psychiatric Nurse Practitioner | C9: Fixed | D9: 1 | F9: 5 | G9: Nurse practitioners | H9: 129510 | I9: 135000 | J9: 1 | K9: All levels of care; Dr. Bokhari supervises as medical director | L9: =D9*I9*(1+Assumptions!$B$36*J9) -> 164700
A10: Nursing & floor | B10: Licensed Practical Nurse, 24/7 | C10: Fixed | D10: 4.2 | F10: 5 | G10: Licensed practical and vocational nurses | H10: 61770 | I10: 62000 | J10: 1 | K10: One LPN on site every shift: med pass, vitals, intake nursing, monitoring | L10: =D10*I10*(1+Assumptions!$B$36*J10) -> 317688
A11: Nursing & floor | B11: Behavioral Health Technician | C11: Fixed | D11: 6.3 | F11: 5 | G11: Psychiatric technicians | H11: 43570 | I11: 44000 | J11: 1 | K11: Two on 12-hour days, one awake overnight; trained in ED meal support; drive outings | L11: =D11*I11*(1+Assumptions!$B$36*J11) -> 338184
A12: Therapy & wellness | B12: Primary Therapist, residential (general and OCD) | C12: Residential | D12: 2 | E12: 1 | F12: 5 | G12: Mental health counselors | H12: 56790 | I12: 65000 | J12: 1 | K12: Caseload about 5 to 6; ERP-trained for the OCD track | L12: =D12*I12*(1+Assumptions!$B$36*J12) -> 158600
A13: Therapy & wellness | B13: Eating Disorder Therapist (specialty track) | C13: Fixed | D13: 1 | F13: 5 | G13: Mental health counselors | H13: 56790 | I13: 70000 | J13: 1 | K13: ED specialist (CEDS or working toward it); ED groups and individual therapy from day one | L13: =D13*I13*(1+Assumptions!$B$36*J13) -> 85400
A14: Therapy & wellness | B14: Day Program Therapist (PHP / IOP) | C14: Day program | D14: 2 | E14: 1 | F14: 8 | G14: Mental health counselors | H14: 56790 | I14: 65000 | J14: 1 | K14: Co-leads groups with wellness staff | L14: =D14*I14*(1+Assumptions!$B$36*J14) -> 158600
A15: Therapy & wellness | B15: Wellness & Movement Coordinator | C15: Fixed | D15: 1 | F15: 5 | G15: Recreational therapists | H15: 57980 | I15: 55000 | J15: 1 | K15: Yoga, fitness, recreation, nature outings | L15: =D15*I15*(1+Assumptions!$B$36*J15) -> 67100
A16: Therapy & wellness | B16: Art / Expressive Therapist (part-time) | C16: Fixed | D16: 0.5 | F16: 5 | G16: Recreational therapists | H16: 57980 | I16: 58000 | J16: 1 | K16: Art and expressive groups | L16: =D16*I16*(1+Assumptions!$B$36*J16) -> 35380
A17: Therapy & wellness | B17: Registered Dietitian | C17: Fixed | D17: 1 | F17: 5 | G17: Dietitians and nutritionists | H17: 76050 | I17: 76000 | J17: 1 | K17: ED track from day one: meal plans, nutrition therapy, menus and cooking groups | L17: =D17*I17*(1+Assumptions!$B$36*J17) -> 92720
A18: Admissions & business | B18: Case Manager / Utilization Review (licensed) | C18: Fixed | D18: 1 | F18: 5 | G18: Mental health counselors | H18: 56790 | I18: 60000 | J18: 1 | K18: Authorizations, concurrent review, discharge planning | L18: =D18*I18*(1+Assumptions!$B$36*J18) -> 73200
A19: Admissions & business | B19: Admissions & Verification Coordinator | C19: Fixed | D19: 1.5 | F19: 5 | G19: Customer service representatives | H19: 40440 | I19: 46000 | J19: 1 | K19: Calls 7 days and benefits checks; after-hours calls to an on-call phone | L19: =D19*I19*(1+Assumptions!$B$36*J19) -> 84180
A20: Admissions & business | B20: Billing & Revenue Cycle Specialist | C20: Fixed | D20: 1 | F20: 5 | G20: Billing and posting clerks | H20: 46540 | I20: 55000 | J20: 1 | K20: Claims, posting, denials, A/R; in-house | L20: =D20*I20*(1+Assumptions!$B$36*J20) -> 67100
A21: Admissions & business | B21: Outreach & Digital Marketing Manager | C21: Fixed | D21: 1 | F21: 3 | G21: Sales representatives of services | H21: 60660 | I21: 70000 | J21: 1 | K21: Referral partners plus Google and Meta ads | L21: =D21*I21*(1+Assumptions!$B$36*J21) -> 85400
A22: Support services | B22: Cook | C22: Fixed | D22: 1.5 | F22: 5 | G22: Cooks, institution and cafeteria | H22: 36250 | I22: 38000 | J22: 1 | K22: Meals 7 days; ED meal plans with the dietitian | L22: =D22*I22*(1+Assumptions!$B$36*J22) -> 69540
A23: Support services | B23: Housekeeper | C23: Fixed | D23: 1 | F23: 5 | G23: Maids and housekeeping cleaners | H23: 33860 | I23: 35000 | J23: 1 | K23: Above Florida $15/hr minimum wage (Sept 2026) | L23: =D23*I23*(1+Assumptions!$B$36*J23) -> 42700
A24: Total at stabilized census | D24: =SUM(D5:D23) -> 30 | K24: Includes payroll taxes and benefits | L24: =SUM(L5:L23) -> 2450492
A26: Summary by department
A27: Department | B27: FTEs | C27: Stabilized annual cost incl. burden | D27: Share of payroll
A28: Leadership | B28: =SUMIF($A$5:$A$23,A28,$D$5:$D$23) -> 2 | C28: =SUMIF($A$5:$A$23,A28,$L$5:$L$23) -> 347700 | D28: =IF($L$24=0,0,C28/$L$24) -> 0.14188987
A29: Clinical leadership | B29: =SUMIF($A$5:$A$23,A29,$D$5:$D$23) -> 3 | C29: =SUMIF($A$5:$A$23,A29,$L$5:$L$23) -> 427000 | D29: =IF($L$24=0,0,C29/$L$24) -> 0.17425072
A30: Nursing & floor | B30: =SUMIF($A$5:$A$23,A30,$D$5:$D$23) -> 10.5 | C30: =SUMIF($A$5:$A$23,A30,$L$5:$L$23) -> 655872 | D30: =IF($L$24=0,0,C30/$L$24) -> 0.26764911
A31: Therapy & wellness | B31: =SUMIF($A$5:$A$23,A31,$D$5:$D$23) -> 7.5 | C31: =SUMIF($A$5:$A$23,A31,$L$5:$L$23) -> 597800 | D31: =IF($L$24=0,0,C31/$L$24) -> 0.24395101
A32: Admissions & business | B32: =SUMIF($A$5:$A$23,A32,$D$5:$D$23) -> 4.5 | C32: =SUMIF($A$5:$A$23,A32,$L$5:$L$23) -> 309880 | D32: =IF($L$24=0,0,C32/$L$24) -> 0.12645624
A33: Support services | B33: =SUMIF($A$5:$A$23,A33,$D$5:$D$23) -> 2.5 | C33: =SUMIF($A$5:$A$23,A33,$L$5:$L$23) -> 112240 | D33: =IF($L$24=0,0,C33/$L$24) -> 0.045803047
A34: Total | B34: =SUM(B28:B33) -> 30 | C34: =SUM(C28:C33) -> 2450492
A36: Sources: Florida statewide annual median wages, BLS Occupational Employment and Wage Statistics 2025, via O*NET OnLine (onetonline.org/link/localwages, st=FL). 24/7 posts use 4.2 FTE (8,760 hours / 2,080). Census-driven FTEs = stabilized FTE x (census / target census), never below the minimum.

Sheet Conservative Monthly
A1: EverBloom: monthly model, Conservative case
A2: All values in $ unless noted. Columns C-E are blank padding so collection lags work in the first months.
C3: (pad) | D3: (pad) | E3: (pad)
A4: Month | F4: 1 | G4: 2 | H4: 3 | I4: 4 | J4: 5 | K4: 6 | L4: 7 | M4: 8 | N4: 9 | O4: 10 | P4: 11 | Q4: 12 | R4: 13 | S4: 14 | T4: 15 | U4: 16 | V4: 17 | W4: 18 | X4: 19 | Y4: 20 | Z4: 21 | AA4: 22 | AB4: 23 | AC4: 24 | AD4: 25 | AE4: 26 | AF4: 27 | AG4: 28 | AH4: 29 | AI4: 30 | AJ4: 31 | AK4: 32 | AL4: 33 | AM4: 34 | AN4: 35 | AO4: 36
A5: Year | F5: =ROUNDUP(F4/12,0) -> 1 | G5: =ROUNDUP(G4/12,0) -> 1 | H5: =ROUNDUP(H4/12,0) -> 1 | I5: =ROUNDUP(I4/12,0) -> 1 | J5: =ROUNDUP(J4/12,0) -> 1 | K5: =ROUNDUP(K4/12,0) -> 1 | L5: =ROUNDUP(L4/12,0) -> 1 | M5: =ROUNDUP(M4/12,0) -> 1 | ... AO5: =ROUNDUP(AO4/12,0) -> 3
A6: Months since opening | F6: =F4-Assumptions!$B$7 -> -5 | G6: =G4-Assumptions!$B$7 -> -4 | H6: =H4-Assumptions!$B$7 -> -3 | I6: =I4-Assumptions!$B$7 -> -2 | J6: =J4-Assumptions!$B$7 -> -1 | K6: =K4-Assumptions!$B$7 -> 0 | L6: =L4-Assumptions!$B$7 -> 1 | M6: =M4-Assumptions!$B$7 -> 2 | ... AO6: =AO4-Assumptions!$B$7 -> 30
A7: Cost escalator | F7: =(1+Assumptions!$B$28)^(F5-1) -> 1 | G7: =(1+Assumptions!$B$28)^(G5-1) -> 1 | H7: =(1+Assumptions!$B$28)^(H5-1) -> 1 | I7: =(1+Assumptions!$B$28)^(I5-1) -> 1 | J7: =(1+Assumptions!$B$28)^(J5-1) -> 1 | K7: =(1+Assumptions!$B$28)^(K5-1) -> 1 | L7: =(1+Assumptions!$B$28)^(L5-1) -> 1 | M7: =(1+Assumptions!$B$28)^(M5-1) -> 1 | ... AO7: =(1+Assumptions!$B$28)^(AO5-1) -> 1.0609
A8: Rate escalator | F8: =IF(F4>24,1+Assumptions!$B$27,1) -> 1 | G8: =IF(G4>24,1+Assumptions!$B$27,1) -> 1 | H8: =IF(H4>24,1+Assumptions!$B$27,1) -> 1 | I8: =IF(I4>24,1+Assumptions!$B$27,1) -> 1 | J8: =IF(J4>24,1+Assumptions!$B$27,1) -> 1 | K8: =IF(K4>24,1+Assumptions!$B$27,1) -> 1 | L8: =IF(L4>24,1+Assumptions!$B$27,1) -> 1 | M8: =IF(M4>24,1+Assumptions!$B$27,1) -> 1 | ... AO8: =IF(AO4>24,1+Assumptions!$B$27,1) -> 1.03
A9: VOLUMES
A10: Residential occupancy | F10: =IF(F6<0,0,IF(F6<11,INDEX(Assumptions!$B$69:$B$79,F6+1),IF(F4>24,Assumptions!$B$14,Assumptions!$B$13))) -> 0 | G10: =IF(G6<0,0,IF(G6<11,INDEX(Assumptions!$B$69:$B$79,G6+1),IF(G4>24,Assumptions!$B$14,Assumptions!$B$13))) -> 0 | H10: =IF(H6<0,0,IF(H6<11,INDEX(Assumptions!$B$69:$B$79,H6+1),IF(H4>24,Assumptions!$B$14,Assumptions!$B$13))) -> 0 | I10: =IF(I6<0,0,IF(I6<11,INDEX(Assumptions!$B$69:$B$79,I6+1),IF(I4>24,Assumptions!$B$14,Assumptions!$B$13))) -> 0 | J10: =IF(J6<0,0,IF(J6<11,INDEX(Assumptions!$B$69:$B$79,J6+1),IF(J4>24,Assumptions!$B$14,Assumptions!$B$13))) -> 0 | K10: =IF(K6<0,0,IF(K6<11,INDEX(Assumptions!$B$69:$B$79,K6+1),IF(K4>24,Assumptions!$B$14,Assumptions!$B$13))) -> 0.15 | L10: =IF(L6<0,0,IF(L6<11,INDEX(Assumptions!$B$69:$B$79,L6+1),IF(L4>24,Assumptions!$B$14,Assumptions!$B$13))) -> 0.25 | M10: =IF(M6<0,0,IF(M6<11,INDEX(Assumptions!$B$69:$B$79,M6+1),IF(M4>24,Assumptions!$B$14,Assumptions!$B$13))) -> 0.35 | ... AO10: =IF(AO6<0,0,IF(AO6<11,INDEX(Assumptions!$B$69:$B$79,AO6+1),IF(AO4>24,Assumptions!$B$14,Assumptions!$B$13))) -> 0.75
A11: Residential patient days | F11: =Assumptions!$B$6*F10*Assumptions!$B$8 -> 0 | G11: =Assumptions!$B$6*G10*Assumptions!$B$8 -> 0 | H11: =Assumptions!$B$6*H10*Assumptions!$B$8 -> 0 | I11: =Assumptions!$B$6*I10*Assumptions!$B$8 -> 0 | J11: =Assumptions!$B$6*J10*Assumptions!$B$8 -> 0 | K11: =Assumptions!$B$6*K10*Assumptions!$B$8 -> 91.2 | L11: =Assumptions!$B$6*L10*Assumptions!$B$8 -> 152 | M11: =Assumptions!$B$6*M10*Assumptions!$B$8 -> 212.8 | ... AO11: =Assumptions!$B$6*AO10*Assumptions!$B$8 -> 456
A12: PHP average daily census | F12: =IF(F6-Assumptions!$B$21<0,0,Assumptions!$B$15*MIN(1,(F6-Assumptions!$B$21+1)/Assumptions!$B$22)) -> 0 | G12: =IF(G6-Assumptions!$B$21<0,0,Assumptions!$B$15*MIN(1,(G6-Assumptions!$B$21+1)/Assumptions!$B$22)) -> 0 | H12: =IF(H6-Assumptions!$B$21<0,0,Assumptions!$B$15*MIN(1,(H6-Assumptions!$B$21+1)/Assumptions!$B$22)) -> 0 | I12: =IF(I6-Assumptions!$B$21<0,0,Assumptions!$B$15*MIN(1,(I6-Assumptions!$B$21+1)/Assumptions!$B$22)) -> 0 | J12: =IF(J6-Assumptions!$B$21<0,0,Assumptions!$B$15*MIN(1,(J6-Assumptions!$B$21+1)/Assumptions!$B$22)) -> 0 | K12: =IF(K6-Assumptions!$B$21<0,0,Assumptions!$B$15*MIN(1,(K6-Assumptions!$B$21+1)/Assumptions!$B$22)) -> 0 | L12: =IF(L6-Assumptions!$B$21<0,0,Assumptions!$B$15*MIN(1,(L6-Assumptions!$B$21+1)/Assumptions!$B$22)) -> 0 | M12: =IF(M6-Assumptions!$B$21<0,0,Assumptions!$B$15*MIN(1,(M6-Assumptions!$B$21+1)/Assumptions!$B$22)) -> 1 | ... AO12: =IF(AO6-Assumptions!$B$21<0,0,Assumptions!$B$15*MIN(1,(AO6-Assumptions!$B$21+1)/Assumptions!$B$22)) -> 8
A13: IOP average daily census | F13: =IF(F6-Assumptions!$B$23<0,0,Assumptions!$B$17*MIN(1,(F6-Assumptions!$B$23+1)/Assumptions!$B$24)) -> 0 | G13: =IF(G6-Assumptions!$B$23<0,0,Assumptions!$B$17*MIN(1,(G6-Assumptions!$B$23+1)/Assumptions!$B$24)) -> 0 | H13: =IF(H6-Assumptions!$B$23<0,0,Assumptions!$B$17*MIN(1,(H6-Assumptions!$B$23+1)/Assumptions!$B$24)) -> 0 | I13: =IF(I6-Assumptions!$B$23<0,0,Assumptions!$B$17*MIN(1,(I6-Assumptions!$B$23+1)/Assumptions!$B$24)) -> 0 | J13: =IF(J6-Assumptions!$B$23<0,0,Assumptions!$B$17*MIN(1,(J6-Assumptions!$B$23+1)/Assumptions!$B$24)) -> 0 | K13: =IF(K6-Assumptions!$B$23<0,0,Assumptions!$B$17*MIN(1,(K6-Assumptions!$B$23+1)/Assumptions!$B$24)) -> 0 | L13: =IF(L6-Assumptions!$B$23<0,0,Assumptions!$B$17*MIN(1,(L6-Assumptions!$B$23+1)/Assumptions!$B$24)) -> 0 | M13: =IF(M6-Assumptions!$B$23<0,0,Assumptions!$B$17*MIN(1,(M6-Assumptions!$B$23+1)/Assumptions!$B$24)) -> 0 | ... AO13: =IF(AO6-Assumptions!$B$23<0,0,Assumptions!$B$17*MIN(1,(AO6-Assumptions!$B$23+1)/Assumptions!$B$24)) -> 10
A14: Outpatient visits | F14: =IF(F6-Assumptions!$B$25<0,0,Assumptions!$B$19*MIN(1,(F6-Assumptions!$B$25+1)/Assumptions!$B$26)) -> 0 | G14: =IF(G6-Assumptions!$B$25<0,0,Assumptions!$B$19*MIN(1,(G6-Assumptions!$B$25+1)/Assumptions!$B$26)) -> 0 | H14: =IF(H6-Assumptions!$B$25<0,0,Assumptions!$B$19*MIN(1,(H6-Assumptions!$B$25+1)/Assumptions!$B$26)) -> 0 | I14: =IF(I6-Assumptions!$B$25<0,0,Assumptions!$B$19*MIN(1,(I6-Assumptions!$B$25+1)/Assumptions!$B$26)) -> 0 | J14: =IF(J6-Assumptions!$B$25<0,0,Assumptions!$B$19*MIN(1,(J6-Assumptions!$B$25+1)/Assumptions!$B$26)) -> 0 | K14: =IF(K6-Assumptions!$B$25<0,0,Assumptions!$B$19*MIN(1,(K6-Assumptions!$B$25+1)/Assumptions!$B$26)) -> 0 | L14: =IF(L6-Assumptions!$B$25<0,0,Assumptions!$B$19*MIN(1,(L6-Assumptions!$B$25+1)/Assumptions!$B$26)) -> 0 | M14: =IF(M6-Assumptions!$B$25<0,0,Assumptions!$B$19*MIN(1,(M6-Assumptions!$B$25+1)/Assumptions!$B$26)) -> 0 | ... AO14: =IF(AO6-Assumptions!$B$25<0,0,Assumptions!$B$19*MIN(1,(AO6-Assumptions!$B$25+1)/Assumptions!$B$26)) -> 120
A15: REVENUE (billed, net of contractual adjustments)
A16: Residential | F16: =F11*Assumptions!$B$12*F8 -> 0 | G16: =G11*Assumptions!$B$12*G8 -> 0 | H16: =H11*Assumptions!$B$12*H8 -> 0 | I16: =I11*Assumptions!$B$12*I8 -> 0 | J16: =J11*Assumptions!$B$12*J8 -> 0 | K16: =K11*Assumptions!$B$12*K8 -> 86640 | L16: =L11*Assumptions!$B$12*L8 -> 144400 | M16: =M11*Assumptions!$B$12*M8 -> 202160 | ... AO16: =AO11*Assumptions!$B$12*AO8 -> 446196
A17: PHP | F17: =F12*Assumptions!$B$9*Assumptions!$B$16*F8 -> 0 | G17: =G12*Assumptions!$B$9*Assumptions!$B$16*G8 -> 0 | H17: =H12*Assumptions!$B$9*Assumptions!$B$16*H8 -> 0 | I17: =I12*Assumptions!$B$9*Assumptions!$B$16*I8 -> 0 | J17: =J12*Assumptions!$B$9*Assumptions!$B$16*J8 -> 0 | K17: =K12*Assumptions!$B$9*Assumptions!$B$16*K8 -> 0 | L17: =L12*Assumptions!$B$9*Assumptions!$B$16*L8 -> 0 | M17: =M12*Assumptions!$B$9*Assumptions!$B$16*M8 -> 10307.5 | ... AO17: =AO12*Assumptions!$B$9*Assumptions!$B$16*AO8 -> 84933.8
A18: IOP | F18: =F13*Assumptions!$B$10*Assumptions!$B$18*F8 -> 0 | G18: =G13*Assumptions!$B$10*Assumptions!$B$18*G8 -> 0 | H18: =H13*Assumptions!$B$10*Assumptions!$B$18*H8 -> 0 | I18: =I13*Assumptions!$B$10*Assumptions!$B$18*I8 -> 0 | J18: =J13*Assumptions!$B$10*Assumptions!$B$18*J8 -> 0 | K18: =K13*Assumptions!$B$10*Assumptions!$B$18*K8 -> 0 | L18: =L13*Assumptions!$B$10*Assumptions!$B$18*L8 -> 0 | M18: =M13*Assumptions!$B$10*Assumptions!$B$18*M8 -> 0 | ... AO18: =AO13*Assumptions!$B$10*Assumptions!$B$18*AO8 -> 42765.6
A19: Outpatient | F19: =F14*Assumptions!$B$20*F8 -> 0 | G19: =G14*Assumptions!$B$20*G8 -> 0 | H19: =H14*Assumptions!$B$20*H8 -> 0 | I19: =I14*Assumptions!$B$20*I8 -> 0 | J19: =J14*Assumptions!$B$20*J8 -> 0 | K19: =K14*Assumptions!$B$20*K8 -> 0 | L19: =L14*Assumptions!$B$20*L8 -> 0 | M19: =M14*Assumptions!$B$20*M8 -> 0 | ... AO19: =AO14*Assumptions!$B$20*AO8 -> 18540
A20: Gross billed revenue | F20: =SUM(F16:F19) -> 0 | G20: =SUM(G16:G19) -> 0 | H20: =SUM(H16:H19) -> 0 | I20: =SUM(I16:I19) -> 0 | J20: =SUM(J16:J19) -> 0 | K20: =SUM(K16:K19) -> 86640 | L20: =SUM(L16:L19) -> 144400 | M20: =SUM(M16:M19) -> 212467.5 | ... AO20: =SUM(AO16:AO19) -> 592435.4
A21: Less denials and bad debt | F21: =-F20*Assumptions!$B$30 -> 0 | G21: =-G20*Assumptions!$B$30 -> 0 | H21: =-H20*Assumptions!$B$30 -> 0 | I21: =-I20*Assumptions!$B$30 -> 0 | J21: =-J20*Assumptions!$B$30 -> 0 | K21: =-K20*Assumptions!$B$30 -> -6931.2 | L21: =-L20*Assumptions!$B$30 -> -11552 | M21: =-M20*Assumptions!$B$30 -> -16997.4 | ... AO21: =-AO20*Assumptions!$B$30 -> -47394.832
A22: Net revenue | C22: 0 | D22: 0 | E22: 0 | F22: =F20+F21 -> 0 | G22: =G20+G21 -> 0 | H22: =H20+H21 -> 0 | I22: =I20+I21 -> 0 | J22: =J20+J21 -> 0 | K22: =K20+K21 -> 79708.8 | L22: =L20+L21 -> 132848 | M22: =M20+M21 -> 195470.1 | ... AO22: =AO20+AO21 -> 545040.57
A23: PAYROLL
A24: Fixed roles (leadership, RCM, admissions, marketing, nursing, support) | F24: =SUMPRODUCT((Staffing!$F$5:$F$23<=F4)*(Staffing!$C$5:$C$23="Fixed")*Staffing!$D$5:$D$23*Staffing!$I$5:$I$23*(1+Assumptions!$B$36*Staffing!$J$5:$J$23))/12 -> 20333.333 | G24: =SUMPRODUCT((Staffing!$F$5:$F$23<=G4)*(Staffing!$C$5:$C$23="Fixed")*Staffing!$D$5:$D$23*Staffing!$I$5:$I$23*(1+Assumptions!$B$36*Staffing!$J$5:$J$23))/12 -> 20333.333 | H24: =SUMPRODUCT((Staffing!$F$5:$F$23<=H4)*(Staffing!$C$5:$C$23="Fixed")*Staffing!$D$5:$D$23*Staffing!$I$5:$I$23*(1+Assumptions!$B$36*Staffing!$J$5:$J$23))/12 -> 38633.333 | I24: =SUMPRODUCT((Staffing!$F$5:$F$23<=I4)*(Staffing!$C$5:$C$23="Fixed")*Staffing!$D$5:$D$23*Staffing!$I$5:$I$23*(1+Assumptions!$B$36*Staffing!$J$5:$J$23))/12 -> 49308.333 | J24: =SUMPRODUCT((Staffing!$F$5:$F$23<=J4)*(Staffing!$C$5:$C$23="Fixed")*Staffing!$D$5:$D$23*Staffing!$I$5:$I$23*(1+Assumptions!$B$36*Staffing!$J$5:$J$23))/12 -> 177774.33 | K24: =SUMPRODUCT((Staffing!$F$5:$F$23<=K4)*(Staffing!$C$5:$C$23="Fixed")*Staffing!$D$5:$D$23*Staffing!$I$5:$I$23*(1+Assumptions!$B$36*Staffing!$J$5:$J$23))/12 -> 177774.33 | L24: =SUMPRODUCT((Staffing!$F$5:$F$23<=L4)*(Staffing!$C$5:$C$23="Fixed")*Staffing!$D$5:$D$23*Staffing!$I$5:$I$23*(1+Assumptions!$B$36*Staffing!$J$5:$J$23))/12 -> 177774.33 | M24: =SUMPRODUCT((Staffing!$F$5:$F$23<=M4)*(Staffing!$C$5:$C$23="Fixed")*Staffing!$D$5:$D$23*Staffing!$I$5:$I$23*(1+Assumptions!$B$36*Staffing!$J$5:$J$23))/12 -> 177774.33 | ... AO24: =SUMPRODUCT((Staffing!$F$5:$F$23<=AO4)*(Staffing!$C$5:$C$23="Fixed")*Staffing!$D$5:$D$23*Staffing!$I$5:$I$23*(1+Assumptions!$B$36*Staffing!$J$5:$J$23))/12 -> 177774.33
A25: Residential census-driven roles (techs, therapists) | F25: =SUMPRODUCT((Staffing!$F$5:$F$23<=F4)*(Staffing!$C$5:$C$23="Residential")*((Staffing!$D$5:$D$23*(F10/Assumptions!$B$13)+Staffing!$E$5:$E$23+ABS(Staffing!$D$5:$D$23*(F10/Assumptions!$B$13)-Staffing!$E$5:$E$23))/2)*Staffing!$I$5:$I$23*(1+Assumptions!$B$36*Staffing!$J$5:$J$23))/12 -> 0 | G25: =SUMPRODUCT((Staffing!$F$5:$F$23<=G4)*(Staffing!$C$5:$C$23="Residential")*((Staffing!$D$5:$D$23*(G10/Assumptions!$B$13)+Staffing!$E$5:$E$23+ABS(Staffing!$D$5:$D$23*(G10/Assumptions!$B$13)-Staffing!$E$5:$E$23))/2)*Staffing!$I$5:$I$23*(1+Assumptions!$B$36*Staffing!$J$5:$J$23))/12 -> 0 | H25: =SUMPRODUCT((Staffing!$F$5:$F$23<=H4)*(Staffing!$C$5:$C$23="Residential")*((Staffing!$D$5:$D$23*(H10/Assumptions!$B$13)+Staffing!$E$5:$E$23+ABS(Staffing!$D$5:$D$23*(H10/Assumptions!$B$13)-Staffing!$E$5:$E$23))/2)*Staffing!$I$5:$I$23*(1+Assumptions!$B$36*Staffing!$J$5:$J$23))/12 -> 0 | I25: =SUMPRODUCT((Staffing!$F$5:$F$23<=I4)*(Staffing!$C$5:$C$23="Residential")*((Staffing!$D$5:$D$23*(I10/Assumptions!$B$13)+Staffing!$E$5:$E$23+ABS(Staffing!$D$5:$D$23*(I10/Assumptions!$B$13)-Staffing!$E$5:$E$23))/2)*Staffing!$I$5:$I$23*(1+Assumptions!$B$36*Staffing!$J$5:$J$23))/12 -> 0 | J25: =SUMPRODUCT((Staffing!$F$5:$F$23<=J4)*(Staffing!$C$5:$C$23="Residential")*((Staffing!$D$5:$D$23*(J10/Assumptions!$B$13)+Staffing!$E$5:$E$23+ABS(Staffing!$D$5:$D$23*(J10/Assumptions!$B$13)-Staffing!$E$5:$E$23))/2)*Staffing!$I$5:$I$23*(1+Assumptions!$B$36*Staffing!$J$5:$J$23))/12 -> 6608.3333 | K25: =SUMPRODUCT((Staffing!$F$5:$F$23<=K4)*(Staffing!$C$5:$C$23="Residential")*((Staffing!$D$5:$D$23*(K10/Assumptions!$B$13)+Staffing!$E$5:$E$23+ABS(Staffing!$D$5:$D$23*(K10/Assumptions!$B$13)-Staffing!$E$5:$E$23))/2)*Staffing!$I$5:$I$23*(1+Assumptions!$B$36*Staffing!$J$5:$J$23))/12 -> 6608.3333 | L25: =SUMPRODUCT((Staffing!$F$5:$F$23<=L4)*(Staffing!$C$5:$C$23="Residential")*((Staffing!$D$5:$D$23*(L10/Assumptions!$B$13)+Staffing!$E$5:$E$23+ABS(Staffing!$D$5:$D$23*(L10/Assumptions!$B$13)-Staffing!$E$5:$E$23))/2)*Staffing!$I$5:$I$23*(1+Assumptions!$B$36*Staffing!$J$5:$J$23))/12 -> 6608.3333 | M25: =SUMPRODUCT((Staffing!$F$5:$F$23<=M4)*(Staffing!$C$5:$C$23="Residential")*((Staffing!$D$5:$D$23*(M10/Assumptions!$B$13)+Staffing!$E$5:$E$23+ABS(Staffing!$D$5:$D$23*(M10/Assumptions!$B$13)-Staffing!$E$5:$E$23))/2)*Staffing!$I$5:$I$23*(1+Assumptions!$B$36*Staffing!$J$5:$J$23))/12 -> 6608.3333 | ... AO25: =SUMPRODUCT((Staffing!$F$5:$F$23<=AO4)*(Staffing!$C$5:$C$23="Residential")*((Staffing!$D$5:$D$23*(AO10/Assumptions!$B$13)+Staffing!$E$5:$E$23+ABS(Staffing!$D$5:$D$23*(AO10/Assumptions!$B$13)-Staffing!$E$5:$E$23))/2)*Staffing!$I$5:$I$23*(1+Assumptions!$B$36*Staffing!$J$5:$J$23))/12 -> 13767.361
A26: Day program census-driven roles | F26: =SUMPRODUCT((Staffing!$F$5:$F$23<=F4)*(Staffing!$C$5:$C$23="Day program")*((Staffing!$D$5:$D$23*((F12+F13)/(Assumptions!$B$15+Assumptions!$B$17))+Staffing!$E$5:$E$23+ABS(Staffing!$D$5:$D$23*((F12+F13)/(Assumptions!$B$15+Assumptions!$B$17))-Staffing!$E$5:$E$23))/2)*Staffing!$I$5:$I$23*(1+Assumptions!$B$36*Staffing!$J$5:$J$23))/12 -> 0 | G26: =SUMPRODUCT((Staffing!$F$5:$F$23<=G4)*(Staffing!$C$5:$C$23="Day program")*((Staffing!$D$5:$D$23*((G12+G13)/(Assumptions!$B$15+Assumptions!$B$17))+Staffing!$E$5:$E$23+ABS(Staffing!$D$5:$D$23*((G12+G13)/(Assumptions!$B$15+Assumptions!$B$17))-Staffing!$E$5:$E$23))/2)*Staffing!$I$5:$I$23*(1+Assumptions!$B$36*Staffing!$J$5:$J$23))/12 -> 0 | H26: =SUMPRODUCT((Staffing!$F$5:$F$23<=H4)*(Staffing!$C$5:$C$23="Day program")*((Staffing!$D$5:$D$23*((H12+H13)/(Assumptions!$B$15+Assumptions!$B$17))+Staffing!$E$5:$E$23+ABS(Staffing!$D$5:$D$23*((H12+H13)/(Assumptions!$B$15+Assumptions!$B$17))-Staffing!$E$5:$E$23))/2)*Staffing!$I$5:$I$23*(1+Assumptions!$B$36*Staffing!$J$5:$J$23))/12 -> 0 | I26: =SUMPRODUCT((Staffing!$F$5:$F$23<=I4)*(Staffing!$C$5:$C$23="Day program")*((Staffing!$D$5:$D$23*((I12+I13)/(Assumptions!$B$15+Assumptions!$B$17))+Staffing!$E$5:$E$23+ABS(Staffing!$D$5:$D$23*((I12+I13)/(Assumptions!$B$15+Assumptions!$B$17))-Staffing!$E$5:$E$23))/2)*Staffing!$I$5:$I$23*(1+Assumptions!$B$36*Staffing!$J$5:$J$23))/12 -> 0 | J26: =SUMPRODUCT((Staffing!$F$5:$F$23<=J4)*(Staffing!$C$5:$C$23="Day program")*((Staffing!$D$5:$D$23*((J12+J13)/(Assumptions!$B$15+Assumptions!$B$17))+Staffing!$E$5:$E$23+ABS(Staffing!$D$5:$D$23*((J12+J13)/(Assumptions!$B$15+Assumptions!$B$17))-Staffing!$E$5:$E$23))/2)*Staffing!$I$5:$I$23*(1+Assumptions!$B$36*Staffing!$J$5:$J$23))/12 -> 0 | K26: =SUMPRODUCT((Staffing!$F$5:$F$23<=K4)*(Staffing!$C$5:$C$23="Day program")*((Staffing!$D$5:$D$23*((K12+K13)/(Assumptions!$B$15+Assumptions!$B$17))+Staffing!$E$5:$E$23+ABS(Staffing!$D$5:$D$23*((K12+K13)/(Assumptions!$B$15+Assumptions!$B$17))-Staffing!$E$5:$E$23))/2)*Staffing!$I$5:$I$23*(1+Assumptions!$B$36*Staffing!$J$5:$J$23))/12 -> 0 | L26: =SUMPRODUCT((Staffing!$F$5:$F$23<=L4)*(Staffing!$C$5:$C$23="Day program")*((Staffing!$D$5:$D$23*((L12+L13)/(Assumptions!$B$15+Assumptions!$B$17))+Staffing!$E$5:$E$23+ABS(Staffing!$D$5:$D$23*((L12+L13)/(Assumptions!$B$15+Assumptions!$B$17))-Staffing!$E$5:$E$23))/2)*Staffing!$I$5:$I$23*(1+Assumptions!$B$36*Staffing!$J$5:$J$23))/12 -> 0 | M26: =SUMPRODUCT((Staffing!$F$5:$F$23<=M4)*(Staffing!$C$5:$C$23="Day program")*((Staffing!$D$5:$D$23*((M12+M13)/(Assumptions!$B$15+Assumptions!$B$17))+Staffing!$E$5:$E$23+ABS(Staffing!$D$5:$D$23*((M12+M13)/(Assumptions!$B$15+Assumptions!$B$17))-Staffing!$E$5:$E$23))/2)*Staffing!$I$5:$I$23*(1+Assumptions!$B$36*Staffing!$J$5:$J$23))/12 -> 6608.3333 | ... AO26: =SUMPRODUCT((Staffing!$F$5:$F$23<=AO4)*(Staffing!$C$5:$C$23="Day program")*((Staffing!$D$5:$D$23*((AO12+AO13)/(Assumptions!$B$15+Assumptions!$B$17))+Staffing!$E$5:$E$23+ABS(Staffing!$D$5:$D$23*((AO12+AO13)/(Assumptions!$B$15+Assumptions!$B$17))-Staffing!$E$5:$E$23))/2)*Staffing!$I$5:$I$23*(1+Assumptions!$B$36*Staffing!$J$5:$J$23))/12 -> 13216.667
A27: Outpatient census-driven roles | F27: =SUMPRODUCT((Staffing!$F$5:$F$23<=F4)*(Staffing!$C$5:$C$23="Outpatient")*((Staffing!$D$5:$D$23*(F14/Assumptions!$B$19)+Staffing!$E$5:$E$23+ABS(Staffing!$D$5:$D$23*(F14/Assumptions!$B$19)-Staffing!$E$5:$E$23))/2)*Staffing!$I$5:$I$23*(1+Assumptions!$B$36*Staffing!$J$5:$J$23))/12 -> 0 | G27: =SUMPRODUCT((Staffing!$F$5:$F$23<=G4)*(Staffing!$C$5:$C$23="Outpatient")*((Staffing!$D$5:$D$23*(G14/Assumptions!$B$19)+Staffing!$E$5:$E$23+ABS(Staffing!$D$5:$D$23*(G14/Assumptions!$B$19)-Staffing!$E$5:$E$23))/2)*Staffing!$I$5:$I$23*(1+Assumptions!$B$36*Staffing!$J$5:$J$23))/12 -> 0 | H27: =SUMPRODUCT((Staffing!$F$5:$F$23<=H4)*(Staffing!$C$5:$C$23="Outpatient")*((Staffing!$D$5:$D$23*(H14/Assumptions!$B$19)+Staffing!$E$5:$E$23+ABS(Staffing!$D$5:$D$23*(H14/Assumptions!$B$19)-Staffing!$E$5:$E$23))/2)*Staffing!$I$5:$I$23*(1+Assumptions!$B$36*Staffing!$J$5:$J$23))/12 -> 0 | I27: =SUMPRODUCT((Staffing!$F$5:$F$23<=I4)*(Staffing!$C$5:$C$23="Outpatient")*((Staffing!$D$5:$D$23*(I14/Assumptions!$B$19)+Staffing!$E$5:$E$23+ABS(Staffing!$D$5:$D$23*(I14/Assumptions!$B$19)-Staffing!$E$5:$E$23))/2)*Staffing!$I$5:$I$23*(1+Assumptions!$B$36*Staffing!$J$5:$J$23))/12 -> 0 | J27: =SUMPRODUCT((Staffing!$F$5:$F$23<=J4)*(Staffing!$C$5:$C$23="Outpatient")*((Staffing!$D$5:$D$23*(J14/Assumptions!$B$19)+Staffing!$E$5:$E$23+ABS(Staffing!$D$5:$D$23*(J14/Assumptions!$B$19)-Staffing!$E$5:$E$23))/2)*Staffing!$I$5:$I$23*(1+Assumptions!$B$36*Staffing!$J$5:$J$23))/12 -> 0 | K27: =SUMPRODUCT((Staffing!$F$5:$F$23<=K4)*(Staffing!$C$5:$C$23="Outpatient")*((Staffing!$D$5:$D$23*(K14/Assumptions!$B$19)+Staffing!$E$5:$E$23+ABS(Staffing!$D$5:$D$23*(K14/Assumptions!$B$19)-Staffing!$E$5:$E$23))/2)*Staffing!$I$5:$I$23*(1+Assumptions!$B$36*Staffing!$J$5:$J$23))/12 -> 0 | L27: =SUMPRODUCT((Staffing!$F$5:$F$23<=L4)*(Staffing!$C$5:$C$23="Outpatient")*((Staffing!$D$5:$D$23*(L14/Assumptions!$B$19)+Staffing!$E$5:$E$23+ABS(Staffing!$D$5:$D$23*(L14/Assumptions!$B$19)-Staffing!$E$5:$E$23))/2)*Staffing!$I$5:$I$23*(1+Assumptions!$B$36*Staffing!$J$5:$J$23))/12 -> 0 | M27: =SUMPRODUCT((Staffing!$F$5:$F$23<=M4)*(Staffing!$C$5:$C$23="Outpatient")*((Staffing!$D$5:$D$23*(M14/Assumptions!$B$19)+Staffing!$E$5:$E$23+ABS(Staffing!$D$5:$D$23*(M14/Assumptions!$B$19)-Staffing!$E$5:$E$23))/2)*Staffing!$I$5:$I$23*(1+Assumptions!$B$36*Staffing!$J$5:$J$23))/12 -> 0 | ... AO27: =SUMPRODUCT((Staffing!$F$5:$F$23<=AO4)*(Staffing!$C$5:$C$23="Outpatient")*((Staffing!$D$5:$D$23*(AO14/Assumptions!$B$19)+Staffing!$E$5:$E$23+ABS(Staffing!$D$5:$D$23*(AO14/Assumptions!$B$19)-Staffing!$E$5:$E$23))/2)*Staffing!$I$5:$I$23*(1+Assumptions!$B$36*Staffing!$J$5:$J$23))/12 -> 0
A28: Total payroll incl. burden, PRN/OT and inflation | F28: =SUM(F24:F27)*F7*(1+Assumptions!$B$37) -> 22366.667 | G28: =SUM(G24:G27)*G7*(1+Assumptions!$B$37) -> 22366.667 | H28: =SUM(H24:H27)*H7*(1+Assumptions!$B$37) -> 42496.667 | I28: =SUM(I24:I27)*I7*(1+Assumptions!$B$37) -> 54239.167 | J28: =SUM(J24:J27)*J7*(1+Assumptions!$B$37) -> 202820.93 | K28: =SUM(K24:K27)*K7*(1+Assumptions!$B$37) -> 202820.93 | L28: =SUM(L24:L27)*L7*(1+Assumptions!$B$37) -> 202820.93 | M28: =SUM(M24:M27)*M7*(1+Assumptions!$B$37) -> 210090.1 | ... AO28: =SUM(AO24:AO27)*AO7*(1+Assumptions!$B$37) -> 238950.96
A29: OPERATING EXPENSES
A30: Rent | F30: =IF(F6>=0,Assumptions!$B$39*F7,IF(F4>=Assumptions!$B$41,Assumptions!$B$39*Assumptions!$B$40,0)) -> 0 | G30: =IF(G6>=0,Assumptions!$B$39*G7,IF(G4>=Assumptions!$B$41,Assumptions!$B$39*Assumptions!$B$40,0)) -> 0 | H30: =IF(H6>=0,Assumptions!$B$39*H7,IF(H4>=Assumptions!$B$41,Assumptions!$B$39*Assumptions!$B$40,0)) -> 22500 | I30: =IF(I6>=0,Assumptions!$B$39*I7,IF(I4>=Assumptions!$B$41,Assumptions!$B$39*Assumptions!$B$40,0)) -> 22500 | J30: =IF(J6>=0,Assumptions!$B$39*J7,IF(J4>=Assumptions!$B$41,Assumptions!$B$39*Assumptions!$B$40,0)) -> 22500 | K30: =IF(K6>=0,Assumptions!$B$39*K7,IF(K4>=Assumptions!$B$41,Assumptions!$B$39*Assumptions!$B$40,0)) -> 45000 | L30: =IF(L6>=0,Assumptions!$B$39*L7,IF(L4>=Assumptions!$B$41,Assumptions!$B$39*Assumptions!$B$40,0)) -> 45000 | M30: =IF(M6>=0,Assumptions!$B$39*M7,IF(M4>=Assumptions!$B$41,Assumptions!$B$39*Assumptions!$B$40,0)) -> 45000 | ... AO30: =IF(AO6>=0,Assumptions!$B$39*AO7,IF(AO4>=Assumptions!$B$41,Assumptions!$B$39*Assumptions!$B$40,0)) -> 47740.5
A31: Utilities | F31: =IF(F6>=0,Assumptions!$B$42*F7,IF(F4>=Assumptions!$B$44,Assumptions!$B$43,0)) -> 0 | G31: =IF(G6>=0,Assumptions!$B$42*G7,IF(G4>=Assumptions!$B$44,Assumptions!$B$43,0)) -> 0 | H31: =IF(H6>=0,Assumptions!$B$42*H7,IF(H4>=Assumptions!$B$44,Assumptions!$B$43,0)) -> 0 | I31: =IF(I6>=0,Assumptions!$B$42*I7,IF(I4>=Assumptions!$B$44,Assumptions!$B$43,0)) -> 4000 | J31: =IF(J6>=0,Assumptions!$B$42*J7,IF(J4>=Assumptions!$B$44,Assumptions!$B$43,0)) -> 4000 | K31: =IF(K6>=0,Assumptions!$B$42*K7,IF(K4>=Assumptions!$B$44,Assumptions!$B$43,0)) -> 12000 | L31: =IF(L6>=0,Assumptions!$B$42*L7,IF(L4>=Assumptions!$B$44,Assumptions!$B$43,0)) -> 12000 | M31: =IF(M6>=0,Assumptions!$B$42*M7,IF(M4>=Assumptions!$B$44,Assumptions!$B$43,0)) -> 12000 | ... AO31: =IF(AO6>=0,Assumptions!$B$42*AO7,IF(AO4>=Assumptions!$B$44,Assumptions!$B$43,0)) -> 12730.8
A32: Food | F32: =F11*Assumptions!$B$45 -> 0 | G32: =G11*Assumptions!$B$45 -> 0 | H32: =H11*Assumptions!$B$45 -> 0 | I32: =I11*Assumptions!$B$45 -> 0 | J32: =J11*Assumptions!$B$45 -> 0 | K32: =K11*Assumptions!$B$45 -> 1824 | L32: =L11*Assumptions!$B$45 -> 3040 | M32: =M11*Assumptions!$B$45 -> 4256 | ... AO32: =AO11*Assumptions!$B$45 -> 9120
A33: Medical and program supplies | F33: =F11*Assumptions!$B$46+(F12*Assumptions!$B$9+F13*Assumptions!$B$10)*Assumptions!$B$47 -> 0 | G33: =G11*Assumptions!$B$46+(G12*Assumptions!$B$9+G13*Assumptions!$B$10)*Assumptions!$B$47 -> 0 | H33: =H11*Assumptions!$B$46+(H12*Assumptions!$B$9+H13*Assumptions!$B$10)*Assumptions!$B$47 -> 0 | I33: =I11*Assumptions!$B$46+(I12*Assumptions!$B$9+I13*Assumptions!$B$10)*Assumptions!$B$47 -> 0 | J33: =J11*Assumptions!$B$46+(J12*Assumptions!$B$9+J13*Assumptions!$B$10)*Assumptions!$B$47 -> 0 | K33: =K11*Assumptions!$B$46+(K12*Assumptions!$B$9+K13*Assumptions!$B$10)*Assumptions!$B$47 -> 1824 | L33: =L11*Assumptions!$B$46+(L12*Assumptions!$B$9+L13*Assumptions!$B$10)*Assumptions!$B$47 -> 3040 | M33: =M11*Assumptions!$B$46+(M12*Assumptions!$B$9+M13*Assumptions!$B$10)*Assumptions!$B$47 -> 4321.1 | ... AO33: =AO11*Assumptions!$B$46+(AO12*Assumptions!$B$9+AO13*Assumptions!$B$10)*Assumptions!$B$47 -> 10159.8
A34: Experiential and activity supplies | F34: =IF(F6>=0,Assumptions!$B$48,0) -> 0 | G34: =IF(G6>=0,Assumptions!$B$48,0) -> 0 | H34: =IF(H6>=0,Assumptions!$B$48,0) -> 0 | I34: =IF(I6>=0,Assumptions!$B$48,0) -> 0 | J34: =IF(J6>=0,Assumptions!$B$48,0) -> 0 | K34: =IF(K6>=0,Assumptions!$B$48,0) -> 3000 | L34: =IF(L6>=0,Assumptions!$B$48,0) -> 3000 | M34: =IF(M6>=0,Assumptions!$B$48,0) -> 3000 | ... AO34: =IF(AO6>=0,Assumptions!$B$48,0) -> 3000
A35: Contracted wellness services | F35: =IF(F6>=0,Assumptions!$B$49,0) -> 0 | G35: =IF(G6>=0,Assumptions!$B$49,0) -> 0 | H35: =IF(H6>=0,Assumptions!$B$49,0) -> 0 | I35: =IF(I6>=0,Assumptions!$B$49,0) -> 0 | J35: =IF(J6>=0,Assumptions!$B$49,0) -> 0 | K35: =IF(K6>=0,Assumptions!$B$49,0) -> 8000 | L35: =IF(L6>=0,Assumptions!$B$49,0) -> 8000 | M35: =IF(M6>=0,Assumptions!$B$49,0) -> 8000 | ... AO35: =IF(AO6>=0,Assumptions!$B$49,0) -> 8000
A36: Medical director stipend | F36: =IF(F4>=Assumptions!$B$51,Assumptions!$B$50,0) -> 0 | G36: =IF(G4>=Assumptions!$B$51,Assumptions!$B$50,0) -> 0 | H36: =IF(H4>=Assumptions!$B$51,Assumptions!$B$50,0) -> 5000 | I36: =IF(I4>=Assumptions!$B$51,Assumptions!$B$50,0) -> 5000 | J36: =IF(J4>=Assumptions!$B$51,Assumptions!$B$50,0) -> 5000 | K36: =IF(K4>=Assumptions!$B$51,Assumptions!$B$50,0) -> 5000 | L36: =IF(L4>=Assumptions!$B$51,Assumptions!$B$50,0) -> 5000 | M36: =IF(M4>=Assumptions!$B$51,Assumptions!$B$50,0) -> 5000 | ... AO36: =IF(AO4>=Assumptions!$B$51,Assumptions!$B$50,0) -> 5000
A37: Insurance | F37: =IF(F4>=Assumptions!$B$53,Assumptions!$B$52,0) -> 0 | G37: =IF(G4>=Assumptions!$B$53,Assumptions!$B$52,0) -> 0 | H37: =IF(H4>=Assumptions!$B$53,Assumptions!$B$52,0) -> 0 | I37: =IF(I4>=Assumptions!$B$53,Assumptions!$B$52,0) -> 12500 | J37: =IF(J4>=Assumptions!$B$53,Assumptions!$B$52,0) -> 12500 | K37: =IF(K4>=Assumptions!$B$53,Assumptions!$B$52,0) -> 12500 | L37: =IF(L4>=Assumptions!$B$53,Assumptions!$B$52,0) -> 12500 | M37: =IF(M4>=Assumptions!$B$53,Assumptions!$B$52,0) -> 12500 | ... AO37: =IF(AO4>=Assumptions!$B$53,Assumptions!$B$52,0) -> 12500
A38: Technology and EHR | F38: =IF(F4>=Assumptions!$B$55,Assumptions!$B$54,0) -> 0 | G38: =IF(G4>=Assumptions!$B$55,Assumptions!$B$54,0) -> 0 | H38: =IF(H4>=Assumptions!$B$55,Assumptions!$B$54,0) -> 10000 | I38: =IF(I4>=Assumptions!$B$55,Assumptions!$B$54,0) -> 10000 | J38: =IF(J4>=Assumptions!$B$55,Assumptions!$B$54,0) -> 10000 | K38: =IF(K4>=Assumptions!$B$55,Assumptions!$B$54,0) -> 10000 | L38: =IF(L4>=Assumptions!$B$55,Assumptions!$B$54,0) -> 10000 | M38: =IF(M4>=Assumptions!$B$55,Assumptions!$B$54,0) -> 10000 | ... AO38: =IF(AO4>=Assumptions!$B$55,Assumptions!$B$54,0) -> 10000
A39: Clearinghouse and billing software | F39: =IF(F6>=0,Assumptions!$B$56,0) -> 0 | G39: =IF(G6>=0,Assumptions!$B$56,0) -> 0 | H39: =IF(H6>=0,Assumptions!$B$56,0) -> 0 | I39: =IF(I6>=0,Assumptions!$B$56,0) -> 0 | J39: =IF(J6>=0,Assumptions!$B$56,0) -> 0 | K39: =IF(K6>=0,Assumptions!$B$56,0) -> 2500 | L39: =IF(L6>=0,Assumptions!$B$56,0) -> 2500 | M39: =IF(M6>=0,Assumptions!$B$56,0) -> 2500 | ... AO39: =IF(AO6>=0,Assumptions!$B$56,0) -> 2500
A40: Paid media (Google, Meta, directories) | F40: =IF(F6>=0,Assumptions!$B$57,IF(F4>=Assumptions!$B$59,Assumptions!$B$58,0)) -> 0 | G40: =IF(G6>=0,Assumptions!$B$57,IF(G4>=Assumptions!$B$59,Assumptions!$B$58,0)) -> 0 | H40: =IF(H6>=0,Assumptions!$B$57,IF(H4>=Assumptions!$B$59,Assumptions!$B$58,0)) -> 0 | I40: =IF(I6>=0,Assumptions!$B$57,IF(I4>=Assumptions!$B$59,Assumptions!$B$58,0)) -> 10000 | J40: =IF(J6>=0,Assumptions!$B$57,IF(J4>=Assumptions!$B$59,Assumptions!$B$58,0)) -> 10000 | K40: =IF(K6>=0,Assumptions!$B$57,IF(K4>=Assumptions!$B$59,Assumptions!$B$58,0)) -> 25000 | L40: =IF(L6>=0,Assumptions!$B$57,IF(L4>=Assumptions!$B$59,Assumptions!$B$58,0)) -> 25000 | M40: =IF(M6>=0,Assumptions!$B$57,IF(M4>=Assumptions!$B$59,Assumptions!$B$58,0)) -> 25000 | ... AO40: =IF(AO6>=0,Assumptions!$B$57,IF(AO4>=Assumptions!$B$59,Assumptions!$B$58,0)) -> 25000
A41: Marketing software | F41: =IF(F4>=Assumptions!$B$61,Assumptions!$B$60,0) -> 0 | G41: =IF(G4>=Assumptions!$B$61,Assumptions!$B$60,0) -> 3000 | H41: =IF(H4>=Assumptions!$B$61,Assumptions!$B$60,0) -> 3000 | I41: =IF(I4>=Assumptions!$B$61,Assumptions!$B$60,0) -> 3000 | J41: =IF(J4>=Assumptions!$B$61,Assumptions!$B$60,0) -> 3000 | K41: =IF(K4>=Assumptions!$B$61,Assumptions!$B$60,0) -> 3000 | L41: =IF(L4>=Assumptions!$B$61,Assumptions!$B$60,0) -> 3000 | M41: =IF(M4>=Assumptions!$B$61,Assumptions!$B$60,0) -> 3000 | ... AO41: =IF(AO4>=Assumptions!$B$61,Assumptions!$B$60,0) -> 3000
A42: Accreditation (survey, then annual fees) | F42: =IF(F4=Assumptions!$B$63,Assumptions!$B$62,0)+IF(F4>Assumptions!$B$63,Assumptions!$B$64/12,0) -> 0 | G42: =IF(G4=Assumptions!$B$63,Assumptions!$B$62,0)+IF(G4>Assumptions!$B$63,Assumptions!$B$64/12,0) -> 0 | H42: =IF(H4=Assumptions!$B$63,Assumptions!$B$62,0)+IF(H4>Assumptions!$B$63,Assumptions!$B$64/12,0) -> 0 | I42: =IF(I4=Assumptions!$B$63,Assumptions!$B$62,0)+IF(I4>Assumptions!$B$63,Assumptions!$B$64/12,0) -> 0 | J42: =IF(J4=Assumptions!$B$63,Assumptions!$B$62,0)+IF(J4>Assumptions!$B$63,Assumptions!$B$64/12,0) -> 0 | K42: =IF(K4=Assumptions!$B$63,Assumptions!$B$62,0)+IF(K4>Assumptions!$B$63,Assumptions!$B$64/12,0) -> 0 | L42: =IF(L4=Assumptions!$B$63,Assumptions!$B$62,0)+IF(L4>Assumptions!$B$63,Assumptions!$B$64/12,0) -> 0 | M42: =IF(M4=Assumptions!$B$63,Assumptions!$B$62,0)+IF(M4>Assumptions!$B$63,Assumptions!$B$64/12,0) -> 0 | ... AO42: =IF(AO4=Assumptions!$B$63,Assumptions!$B$62,0)+IF(AO4>Assumptions!$B$63,Assumptions!$B$64/12,0) -> 833.33333
A43: Professional fees | F43: =IF(F6<0,Assumptions!$B$65,Assumptions!$B$66) -> 15000 | G43: =IF(G6<0,Assumptions!$B$65,Assumptions!$B$66) -> 15000 | H43: =IF(H6<0,Assumptions!$B$65,Assumptions!$B$66) -> 15000 | I43: =IF(I6<0,Assumptions!$B$65,Assumptions!$B$66) -> 15000 | J43: =IF(J6<0,Assumptions!$B$65,Assumptions!$B$66) -> 15000 | K43: =IF(K6<0,Assumptions!$B$65,Assumptions!$B$66) -> 8000 | L43: =IF(L6<0,Assumptions!$B$65,Assumptions!$B$66) -> 8000 | M43: =IF(M6<0,Assumptions!$B$65,Assumptions!$B$66) -> 8000 | ... AO43: =IF(AO6<0,Assumptions!$B$65,Assumptions!$B$66) -> 8000
A44: Other operating | F44: =IF(F6>=0,Assumptions!$B$67,0) -> 0 | G44: =IF(G6>=0,Assumptions!$B$67,0) -> 0 | H44: =IF(H6>=0,Assumptions!$B$67,0) -> 0 | I44: =IF(I6>=0,Assumptions!$B$67,0) -> 0 | J44: =IF(J6>=0,Assumptions!$B$67,0) -> 0 | K44: =IF(K6>=0,Assumptions!$B$67,0) -> 12000 | L44: =IF(L6>=0,Assumptions!$B$67,0) -> 12000 | M44: =IF(M6>=0,Assumptions!$B$67,0) -> 12000 | ... AO44: =IF(AO6>=0,Assumptions!$B$67,0) -> 12000
A45: Total operating expenses | F45: =SUM(F30:F44) -> 15000 | G45: =SUM(G30:G44) -> 18000 | H45: =SUM(H30:H44) -> 55500 | I45: =SUM(I30:I44) -> 82000 | J45: =SUM(J30:J44) -> 82000 | K45: =SUM(K30:K44) -> 149648 | L45: =SUM(L30:L44) -> 152080 | M45: =SUM(M30:M44) -> 154577.1 | ... AO45: =SUM(AO30:AO44) -> 169584.43
A46: EBITDA | F46: =F22-F28-F45 -> -37366.667 | G46: =G22-G28-G45 -> -40366.667 | H46: =H22-H28-H45 -> -97996.667 | I46: =I22-I28-I45 -> -136239.17 | J46: =J22-J28-J45 -> -284820.93 | K46: =K22-K28-K45 -> -272760.13 | L46: =L22-L28-L45 -> -222052.93 | M46: =M22-M28-M45 -> -169197.1 | ... AO46: =AO22-AO28-AO45 -> 136505.17
A47: EBITDA margin | F47: =IF(F22=0,0,F46/F22) -> 0 | G47: =IF(G22=0,0,G46/G22) -> 0 | H47: =IF(H22=0,0,H46/H22) -> 0 | I47: =IF(I22=0,0,I46/I22) -> 0 | J47: =IF(J22=0,0,J46/J22) -> 0 | K47: =IF(K22=0,0,K46/K22) -> -3.4219576 | L47: =IF(L22=0,0,L46/L22) -> -1.6714812 | M47: =IF(M22=0,0,M46/M22) -> -0.8655907 | ... AO47: =IF(AO22=0,0,AO46/AO22) -> 0.25044957
A48: CASH FLOW
A49: Cash collected | F49: =F22*Assumptions!$B$31+E22*Assumptions!$B$32+D22*Assumptions!$B$33+C22*Assumptions!$B$34 -> 0 | G49: =G22*Assumptions!$B$31+F22*Assumptions!$B$32+E22*Assumptions!$B$33+D22*Assumptions!$B$34 -> 0 | H49: =H22*Assumptions!$B$31+G22*Assumptions!$B$32+F22*Assumptions!$B$33+E22*Assumptions!$B$34 -> 0 | I49: =I22*Assumptions!$B$31+H22*Assumptions!$B$32+G22*Assumptions!$B$33+F22*Assumptions!$B$34 -> 0 | J49: =J22*Assumptions!$B$31+I22*Assumptions!$B$32+H22*Assumptions!$B$33+G22*Assumptions!$B$34 -> 0 | K49: =K22*Assumptions!$B$31+J22*Assumptions!$B$32+I22*Assumptions!$B$33+H22*Assumptions!$B$34 -> 0 | L49: =L22*Assumptions!$B$31+K22*Assumptions!$B$32+J22*Assumptions!$B$33+I22*Assumptions!$B$34 -> 15941.76 | M49: =M22*Assumptions!$B$31+L22*Assumptions!$B$32+K22*Assumptions!$B$33+J22*Assumptions!$B$34 -> 70409.44 | ... AO49: =AO22*Assumptions!$B$31+AN22*Assumptions!$B$32+AM22*Assumptions!$B$33+AL22*Assumptions!$B$34 -> 545040.57
A50: One-time startup costs | F50: =IF(F4<=8,INDEX(Capital!$B$13:$I$13,F4),0) -> 145000 | G50: =IF(G4<=8,INDEX(Capital!$B$13:$I$13,G4),0) -> 175000 | H50: =IF(H4<=8,INDEX(Capital!$B$13:$I$13,H4),0) -> 245000 | I50: =IF(I4<=8,INDEX(Capital!$B$13:$I$13,I4),0) -> 325000 | J50: =IF(J4<=8,INDEX(Capital!$B$13:$I$13,J4),0) -> 370000 | K50: =IF(K4<=8,INDEX(Capital!$B$13:$I$13,K4),0) -> 15000 | L50: =IF(L4<=8,INDEX(Capital!$B$13:$I$13,L4),0) -> 0 | M50: =IF(M4<=8,INDEX(Capital!$B$13:$I$13,M4),0) -> 0 | ... AO50: =IF(AO4<=8,INDEX(Capital!$B$13:$I$13,AO4),0) -> 0
A51: Net cash flow | F51: =F49-F28-F45-F50 -> -182366.67 | G51: =G49-G28-G45-G50 -> -215366.67 | H51: =H49-H28-H45-H50 -> -342996.67 | I51: =I49-I28-I45-I50 -> -461239.17 | J51: =J49-J28-J45-J50 -> -654820.93 | K51: =K49-K28-K45-K50 -> -367468.93 | L51: =L49-L28-L45-L50 -> -338959.17 | M51: =M49-M28-M45-M50 -> -294257.76 | ... AO51: =AO49-AO28-AO45-AO50 -> 136505.17
A52: Cumulative cash flow | F52: =F51 -> -182366.67 | G52: =F52+G51 -> -397733.33 | H52: =G52+H51 -> -740730 | I52: =H52+I51 -> -1201969.2 | J52: =I52+J51 -> -1856790.1 | K52: =J52+K51 -> -2224259 | L52: =K52+L51 -> -2563218.2 | M52: =L52+M51 -> -2857476 | N52: =M52+N51 -> -3094427.6 | ... AO52: =AN52+AO51 -> -1009664
A53: Paid back flag (after trough, cumulative at or above zero) | F53: =IF(AND(F4>$B$57,F52>=0),1,0) -> 0 | G53: =IF(AND(G4>$B$57,G52>=0),1,0) -> 0 | H53: =IF(AND(H4>$B$57,H52>=0),1,0) -> 0 | I53: =IF(AND(I4>$B$57,I52>=0),1,0) -> 0 | J53: =IF(AND(J4>$B$57,J52>=0),1,0) -> 0 | K53: =IF(AND(K4>$B$57,K52>=0),1,0) -> 0 | L53: =IF(AND(L4>$B$57,L52>=0),1,0) -> 0 | M53: =IF(AND(M4>$B$57,M52>=0),1,0) -> 0 | ... AO53: =IF(AND(AO4>$B$57,AO52>=0),1,0) -> 0
A55: KEY RESULTS
A56: Peak capital need (lowest cumulative cash) | B56: =-MIN($F$52:$AO$52) -> 3551434.9
A57: Month of peak need | B57: =INDEX($F$4:$AO$4,MATCH(MIN($F$52:$AO$52),$F$52:$AO$52,0)) -> 14
A58: EBITDA positive from month (stays positive) | B58: =SUMPRODUCT(MAX(($F$46:$AO$46<0)*$F$4:$AO$4))+1 -> 12
A59: Cash flow positive from month (stays positive) | B59: =SUMPRODUCT(MAX(($F$51:$AO$51<0)*$F$4:$AO$4))+1 -> 15
A60: Cumulative cash payback month | B60: =IFERROR(INDEX($F$4:$AO$4,MATCH(1,$F$53:$AO$53,0)),"After M36") -> After M36
A61: Cumulative cash at Month 36 | B61: =AO52 -> -1009664

Sheet Base Monthly
A1: EverBloom: monthly model, Base case
A2: All values in $ unless noted. Columns C-E are blank padding so collection lags work in the first months.
C3: (pad) | D3: (pad) | E3: (pad)
A4: Month | F4: 1 | G4: 2 | H4: 3 | I4: 4 | J4: 5 | K4: 6 | L4: 7 | M4: 8 | N4: 9 | O4: 10 | P4: 11 | Q4: 12 | R4: 13 | S4: 14 | T4: 15 | U4: 16 | V4: 17 | W4: 18 | X4: 19 | Y4: 20 | Z4: 21 | AA4: 22 | AB4: 23 | AC4: 24 | AD4: 25 | AE4: 26 | AF4: 27 | AG4: 28 | AH4: 29 | AI4: 30 | AJ4: 31 | AK4: 32 | AL4: 33 | AM4: 34 | AN4: 35 | AO4: 36
A5: Year | F5: =ROUNDUP(F4/12,0) -> 1 | G5: =ROUNDUP(G4/12,0) -> 1 | H5: =ROUNDUP(H4/12,0) -> 1 | I5: =ROUNDUP(I4/12,0) -> 1 | J5: =ROUNDUP(J4/12,0) -> 1 | K5: =ROUNDUP(K4/12,0) -> 1 | L5: =ROUNDUP(L4/12,0) -> 1 | M5: =ROUNDUP(M4/12,0) -> 1 | ... AO5: =ROUNDUP(AO4/12,0) -> 3
A6: Months since opening | F6: =F4-Assumptions!$C$7 -> -5 | G6: =G4-Assumptions!$C$7 -> -4 | H6: =H4-Assumptions!$C$7 -> -3 | I6: =I4-Assumptions!$C$7 -> -2 | J6: =J4-Assumptions!$C$7 -> -1 | K6: =K4-Assumptions!$C$7 -> 0 | L6: =L4-Assumptions!$C$7 -> 1 | M6: =M4-Assumptions!$C$7 -> 2 | ... AO6: =AO4-Assumptions!$C$7 -> 30
A7: Cost escalator | F7: =(1+Assumptions!$C$28)^(F5-1) -> 1 | G7: =(1+Assumptions!$C$28)^(G5-1) -> 1 | H7: =(1+Assumptions!$C$28)^(H5-1) -> 1 | I7: =(1+Assumptions!$C$28)^(I5-1) -> 1 | J7: =(1+Assumptions!$C$28)^(J5-1) -> 1 | K7: =(1+Assumptions!$C$28)^(K5-1) -> 1 | L7: =(1+Assumptions!$C$28)^(L5-1) -> 1 | M7: =(1+Assumptions!$C$28)^(M5-1) -> 1 | ... AO7: =(1+Assumptions!$C$28)^(AO5-1) -> 1.0609
A8: Rate escalator | F8: =IF(F4>24,1+Assumptions!$C$27,1) -> 1 | G8: =IF(G4>24,1+Assumptions!$C$27,1) -> 1 | H8: =IF(H4>24,1+Assumptions!$C$27,1) -> 1 | I8: =IF(I4>24,1+Assumptions!$C$27,1) -> 1 | J8: =IF(J4>24,1+Assumptions!$C$27,1) -> 1 | K8: =IF(K4>24,1+Assumptions!$C$27,1) -> 1 | L8: =IF(L4>24,1+Assumptions!$C$27,1) -> 1 | M8: =IF(M4>24,1+Assumptions!$C$27,1) -> 1 | ... AO8: =IF(AO4>24,1+Assumptions!$C$27,1) -> 1.03
A9: VOLUMES
A10: Residential occupancy | F10: =IF(F6<0,0,IF(F6<11,INDEX(Assumptions!$C$69:$C$79,F6+1),IF(F4>24,Assumptions!$C$14,Assumptions!$C$13))) -> 0 | G10: =IF(G6<0,0,IF(G6<11,INDEX(Assumptions!$C$69:$C$79,G6+1),IF(G4>24,Assumptions!$C$14,Assumptions!$C$13))) -> 0 | H10: =IF(H6<0,0,IF(H6<11,INDEX(Assumptions!$C$69:$C$79,H6+1),IF(H4>24,Assumptions!$C$14,Assumptions!$C$13))) -> 0 | I10: =IF(I6<0,0,IF(I6<11,INDEX(Assumptions!$C$69:$C$79,I6+1),IF(I4>24,Assumptions!$C$14,Assumptions!$C$13))) -> 0 | J10: =IF(J6<0,0,IF(J6<11,INDEX(Assumptions!$C$69:$C$79,J6+1),IF(J4>24,Assumptions!$C$14,Assumptions!$C$13))) -> 0 | K10: =IF(K6<0,0,IF(K6<11,INDEX(Assumptions!$C$69:$C$79,K6+1),IF(K4>24,Assumptions!$C$14,Assumptions!$C$13))) -> 0.25 | L10: =IF(L6<0,0,IF(L6<11,INDEX(Assumptions!$C$69:$C$79,L6+1),IF(L4>24,Assumptions!$C$14,Assumptions!$C$13))) -> 0.4 | M10: =IF(M6<0,0,IF(M6<11,INDEX(Assumptions!$C$69:$C$79,M6+1),IF(M4>24,Assumptions!$C$14,Assumptions!$C$13))) -> 0.5 | ... AO10: =IF(AO6<0,0,IF(AO6<11,INDEX(Assumptions!$C$69:$C$79,AO6+1),IF(AO4>24,Assumptions!$C$14,Assumptions!$C$13))) -> 0.85
A11: Residential patient days | F11: =Assumptions!$C$6*F10*Assumptions!$C$8 -> 0 | G11: =Assumptions!$C$6*G10*Assumptions!$C$8 -> 0 | H11: =Assumptions!$C$6*H10*Assumptions!$C$8 -> 0 | I11: =Assumptions!$C$6*I10*Assumptions!$C$8 -> 0 | J11: =Assumptions!$C$6*J10*Assumptions!$C$8 -> 0 | K11: =Assumptions!$C$6*K10*Assumptions!$C$8 -> 152 | L11: =Assumptions!$C$6*L10*Assumptions!$C$8 -> 243.2 | M11: =Assumptions!$C$6*M10*Assumptions!$C$8 -> 304 | ... AO11: =Assumptions!$C$6*AO10*Assumptions!$C$8 -> 516.8
A12: PHP average daily census | F12: =IF(F6-Assumptions!$C$21<0,0,Assumptions!$C$15*MIN(1,(F6-Assumptions!$C$21+1)/Assumptions!$C$22)) -> 0 | G12: =IF(G6-Assumptions!$C$21<0,0,Assumptions!$C$15*MIN(1,(G6-Assumptions!$C$21+1)/Assumptions!$C$22)) -> 0 | H12: =IF(H6-Assumptions!$C$21<0,0,Assumptions!$C$15*MIN(1,(H6-Assumptions!$C$21+1)/Assumptions!$C$22)) -> 0 | I12: =IF(I6-Assumptions!$C$21<0,0,Assumptions!$C$15*MIN(1,(I6-Assumptions!$C$21+1)/Assumptions!$C$22)) -> 0 | J12: =IF(J6-Assumptions!$C$21<0,0,Assumptions!$C$15*MIN(1,(J6-Assumptions!$C$21+1)/Assumptions!$C$22)) -> 0 | K12: =IF(K6-Assumptions!$C$21<0,0,Assumptions!$C$15*MIN(1,(K6-Assumptions!$C$21+1)/Assumptions!$C$22)) -> 0 | L12: =IF(L6-Assumptions!$C$21<0,0,Assumptions!$C$15*MIN(1,(L6-Assumptions!$C$21+1)/Assumptions!$C$22)) -> 0 | M12: =IF(M6-Assumptions!$C$21<0,0,Assumptions!$C$15*MIN(1,(M6-Assumptions!$C$21+1)/Assumptions!$C$22)) -> 1.5 | ... AO12: =IF(AO6-Assumptions!$C$21<0,0,Assumptions!$C$15*MIN(1,(AO6-Assumptions!$C$21+1)/Assumptions!$C$22)) -> 12
A13: IOP average daily census | F13: =IF(F6-Assumptions!$C$23<0,0,Assumptions!$C$17*MIN(1,(F6-Assumptions!$C$23+1)/Assumptions!$C$24)) -> 0 | G13: =IF(G6-Assumptions!$C$23<0,0,Assumptions!$C$17*MIN(1,(G6-Assumptions!$C$23+1)/Assumptions!$C$24)) -> 0 | H13: =IF(H6-Assumptions!$C$23<0,0,Assumptions!$C$17*MIN(1,(H6-Assumptions!$C$23+1)/Assumptions!$C$24)) -> 0 | I13: =IF(I6-Assumptions!$C$23<0,0,Assumptions!$C$17*MIN(1,(I6-Assumptions!$C$23+1)/Assumptions!$C$24)) -> 0 | J13: =IF(J6-Assumptions!$C$23<0,0,Assumptions!$C$17*MIN(1,(J6-Assumptions!$C$23+1)/Assumptions!$C$24)) -> 0 | K13: =IF(K6-Assumptions!$C$23<0,0,Assumptions!$C$17*MIN(1,(K6-Assumptions!$C$23+1)/Assumptions!$C$24)) -> 0 | L13: =IF(L6-Assumptions!$C$23<0,0,Assumptions!$C$17*MIN(1,(L6-Assumptions!$C$23+1)/Assumptions!$C$24)) -> 0 | M13: =IF(M6-Assumptions!$C$23<0,0,Assumptions!$C$17*MIN(1,(M6-Assumptions!$C$23+1)/Assumptions!$C$24)) -> 0 | ... AO13: =IF(AO6-Assumptions!$C$23<0,0,Assumptions!$C$17*MIN(1,(AO6-Assumptions!$C$23+1)/Assumptions!$C$24)) -> 15
A14: Outpatient visits | F14: =IF(F6-Assumptions!$C$25<0,0,Assumptions!$C$19*MIN(1,(F6-Assumptions!$C$25+1)/Assumptions!$C$26)) -> 0 | G14: =IF(G6-Assumptions!$C$25<0,0,Assumptions!$C$19*MIN(1,(G6-Assumptions!$C$25+1)/Assumptions!$C$26)) -> 0 | H14: =IF(H6-Assumptions!$C$25<0,0,Assumptions!$C$19*MIN(1,(H6-Assumptions!$C$25+1)/Assumptions!$C$26)) -> 0 | I14: =IF(I6-Assumptions!$C$25<0,0,Assumptions!$C$19*MIN(1,(I6-Assumptions!$C$25+1)/Assumptions!$C$26)) -> 0 | J14: =IF(J6-Assumptions!$C$25<0,0,Assumptions!$C$19*MIN(1,(J6-Assumptions!$C$25+1)/Assumptions!$C$26)) -> 0 | K14: =IF(K6-Assumptions!$C$25<0,0,Assumptions!$C$19*MIN(1,(K6-Assumptions!$C$25+1)/Assumptions!$C$26)) -> 0 | L14: =IF(L6-Assumptions!$C$25<0,0,Assumptions!$C$19*MIN(1,(L6-Assumptions!$C$25+1)/Assumptions!$C$26)) -> 0 | M14: =IF(M6-Assumptions!$C$25<0,0,Assumptions!$C$19*MIN(1,(M6-Assumptions!$C$25+1)/Assumptions!$C$26)) -> 0 | ... AO14: =IF(AO6-Assumptions!$C$25<0,0,Assumptions!$C$19*MIN(1,(AO6-Assumptions!$C$25+1)/Assumptions!$C$26)) -> 200
A15: REVENUE (billed, net of contractual adjustments)
A16: Residential | F16: =F11*Assumptions!$C$12*F8 -> 0 | G16: =G11*Assumptions!$C$12*G8 -> 0 | H16: =H11*Assumptions!$C$12*H8 -> 0 | I16: =I11*Assumptions!$C$12*I8 -> 0 | J16: =J11*Assumptions!$C$12*J8 -> 0 | K16: =K11*Assumptions!$C$12*K8 -> 167200 | L16: =L11*Assumptions!$C$12*L8 -> 267520 | M16: =M11*Assumptions!$C$12*M8 -> 334400 | ... AO16: =AO11*Assumptions!$C$12*AO8 -> 585534.4
A17: PHP | F17: =F12*Assumptions!$C$9*Assumptions!$C$16*F8 -> 0 | G17: =G12*Assumptions!$C$9*Assumptions!$C$16*G8 -> 0 | H17: =H12*Assumptions!$C$9*Assumptions!$C$16*H8 -> 0 | I17: =I12*Assumptions!$C$9*Assumptions!$C$16*I8 -> 0 | J17: =J12*Assumptions!$C$9*Assumptions!$C$16*J8 -> 0 | K17: =K12*Assumptions!$C$9*Assumptions!$C$16*K8 -> 0 | L17: =L12*Assumptions!$C$9*Assumptions!$C$16*L8 -> 0 | M17: =M12*Assumptions!$C$9*Assumptions!$C$16*M8 -> 17902.5 | ... AO17: =AO12*Assumptions!$C$9*Assumptions!$C$16*AO8 -> 147516.6
A18: IOP | F18: =F13*Assumptions!$C$10*Assumptions!$C$18*F8 -> 0 | G18: =G13*Assumptions!$C$10*Assumptions!$C$18*G8 -> 0 | H18: =H13*Assumptions!$C$10*Assumptions!$C$18*H8 -> 0 | I18: =I13*Assumptions!$C$10*Assumptions!$C$18*I8 -> 0 | J18: =J13*Assumptions!$C$10*Assumptions!$C$18*J8 -> 0 | K18: =K13*Assumptions!$C$10*Assumptions!$C$18*K8 -> 0 | L18: =L13*Assumptions!$C$10*Assumptions!$C$18*L8 -> 0 | M18: =M13*Assumptions!$C$10*Assumptions!$C$18*M8 -> 0 | ... AO18: =AO13*Assumptions!$C$10*Assumptions!$C$18*AO8 -> 73503.375
A19: Outpatient | F19: =F14*Assumptions!$C$20*F8 -> 0 | G19: =G14*Assumptions!$C$20*G8 -> 0 | H19: =H14*Assumptions!$C$20*H8 -> 0 | I19: =I14*Assumptions!$C$20*I8 -> 0 | J19: =J14*Assumptions!$C$20*J8 -> 0 | K19: =K14*Assumptions!$C$20*K8 -> 0 | L19: =L14*Assumptions!$C$20*L8 -> 0 | M19: =M14*Assumptions!$C$20*M8 -> 0 | ... AO19: =AO14*Assumptions!$C$20*AO8 -> 30900
A20: Gross billed revenue | F20: =SUM(F16:F19) -> 0 | G20: =SUM(G16:G19) -> 0 | H20: =SUM(H16:H19) -> 0 | I20: =SUM(I16:I19) -> 0 | J20: =SUM(J16:J19) -> 0 | K20: =SUM(K16:K19) -> 167200 | L20: =SUM(L16:L19) -> 267520 | M20: =SUM(M16:M19) -> 352302.5 | ... AO20: =SUM(AO16:AO19) -> 837454.38
A21: Less denials and bad debt | F21: =-F20*Assumptions!$C$30 -> 0 | G21: =-G20*Assumptions!$C$30 -> 0 | H21: =-H20*Assumptions!$C$30 -> 0 | I21: =-I20*Assumptions!$C$30 -> 0 | J21: =-J20*Assumptions!$C$30 -> 0 | K21: =-K20*Assumptions!$C$30 -> -13376 | L21: =-L20*Assumptions!$C$30 -> -21401.6 | M21: =-M20*Assumptions!$C$30 -> -28184.2 | ... AO21: =-AO20*Assumptions!$C$30 -> -66996.35
A22: Net revenue | C22: 0 | D22: 0 | E22: 0 | F22: =F20+F21 -> 0 | G22: =G20+G21 -> 0 | H22: =H20+H21 -> 0 | I22: =I20+I21 -> 0 | J22: =J20+J21 -> 0 | K22: =K20+K21 -> 153824 | L22: =L20+L21 -> 246118.4 | M22: =M20+M21 -> 324118.3 | ... AO22: =AO20+AO21 -> 770458.03
A23: PAYROLL
A24: Fixed roles (leadership, RCM, admissions, marketing, nursing, support) | F24: =SUMPRODUCT((Staffing!$F$5:$F$23<=F4)*(Staffing!$C$5:$C$23="Fixed")*Staffing!$D$5:$D$23*Staffing!$I$5:$I$23*(1+Assumptions!$B$36*Staffing!$J$5:$J$23))/12 -> 20333.333 | G24: =SUMPRODUCT((Staffing!$F$5:$F$23<=G4)*(Staffing!$C$5:$C$23="Fixed")*Staffing!$D$5:$D$23*Staffing!$I$5:$I$23*(1+Assumptions!$B$36*Staffing!$J$5:$J$23))/12 -> 20333.333 | H24: =SUMPRODUCT((Staffing!$F$5:$F$23<=H4)*(Staffing!$C$5:$C$23="Fixed")*Staffing!$D$5:$D$23*Staffing!$I$5:$I$23*(1+Assumptions!$B$36*Staffing!$J$5:$J$23))/12 -> 38633.333 | I24: =SUMPRODUCT((Staffing!$F$5:$F$23<=I4)*(Staffing!$C$5:$C$23="Fixed")*Staffing!$D$5:$D$23*Staffing!$I$5:$I$23*(1+Assumptions!$B$36*Staffing!$J$5:$J$23))/12 -> 49308.333 | J24: =SUMPRODUCT((Staffing!$F$5:$F$23<=J4)*(Staffing!$C$5:$C$23="Fixed")*Staffing!$D$5:$D$23*Staffing!$I$5:$I$23*(1+Assumptions!$B$36*Staffing!$J$5:$J$23))/12 -> 177774.33 | K24: =SUMPRODUCT((Staffing!$F$5:$F$23<=K4)*(Staffing!$C$5:$C$23="Fixed")*Staffing!$D$5:$D$23*Staffing!$I$5:$I$23*(1+Assumptions!$B$36*Staffing!$J$5:$J$23))/12 -> 177774.33 | L24: =SUMPRODUCT((Staffing!$F$5:$F$23<=L4)*(Staffing!$C$5:$C$23="Fixed")*Staffing!$D$5:$D$23*Staffing!$I$5:$I$23*(1+Assumptions!$B$36*Staffing!$J$5:$J$23))/12 -> 177774.33 | M24: =SUMPRODUCT((Staffing!$F$5:$F$23<=M4)*(Staffing!$C$5:$C$23="Fixed")*Staffing!$D$5:$D$23*Staffing!$I$5:$I$23*(1+Assumptions!$B$36*Staffing!$J$5:$J$23))/12 -> 177774.33 | ... AO24: =SUMPRODUCT((Staffing!$F$5:$F$23<=AO4)*(Staffing!$C$5:$C$23="Fixed")*Staffing!$D$5:$D$23*Staffing!$I$5:$I$23*(1+Assumptions!$B$36*Staffing!$J$5:$J$23))/12 -> 177774.33
A25: Residential census-driven roles (techs, therapists) | F25: =SUMPRODUCT((Staffing!$F$5:$F$23<=F4)*(Staffing!$C$5:$C$23="Residential")*((Staffing!$D$5:$D$23*(F10/Assumptions!$C$13)+Staffing!$E$5:$E$23+ABS(Staffing!$D$5:$D$23*(F10/Assumptions!$C$13)-Staffing!$E$5:$E$23))/2)*Staffing!$I$5:$I$23*(1+Assumptions!$B$36*Staffing!$J$5:$J$23))/12 -> 0 | G25: =SUMPRODUCT((Staffing!$F$5:$F$23<=G4)*(Staffing!$C$5:$C$23="Residential")*((Staffing!$D$5:$D$23*(G10/Assumptions!$C$13)+Staffing!$E$5:$E$23+ABS(Staffing!$D$5:$D$23*(G10/Assumptions!$C$13)-Staffing!$E$5:$E$23))/2)*Staffing!$I$5:$I$23*(1+Assumptions!$B$36*Staffing!$J$5:$J$23))/12 -> 0 | H25: =SUMPRODUCT((Staffing!$F$5:$F$23<=H4)*(Staffing!$C$5:$C$23="Residential")*((Staffing!$D$5:$D$23*(H10/Assumptions!$C$13)+Staffing!$E$5:$E$23+ABS(Staffing!$D$5:$D$23*(H10/Assumptions!$C$13)-Staffing!$E$5:$E$23))/2)*Staffing!$I$5:$I$23*(1+Assumptions!$B$36*Staffing!$J$5:$J$23))/12 -> 0 | I25: =SUMPRODUCT((Staffing!$F$5:$F$23<=I4)*(Staffing!$C$5:$C$23="Residential")*((Staffing!$D$5:$D$23*(I10/Assumptions!$C$13)+Staffing!$E$5:$E$23+ABS(Staffing!$D$5:$D$23*(I10/Assumptions!$C$13)-Staffing!$E$5:$E$23))/2)*Staffing!$I$5:$I$23*(1+Assumptions!$B$36*Staffing!$J$5:$J$23))/12 -> 0 | J25: =SUMPRODUCT((Staffing!$F$5:$F$23<=J4)*(Staffing!$C$5:$C$23="Residential")*((Staffing!$D$5:$D$23*(J10/Assumptions!$C$13)+Staffing!$E$5:$E$23+ABS(Staffing!$D$5:$D$23*(J10/Assumptions!$C$13)-Staffing!$E$5:$E$23))/2)*Staffing!$I$5:$I$23*(1+Assumptions!$B$36*Staffing!$J$5:$J$23))/12 -> 6608.3333 | K25: =SUMPRODUCT((Staffing!$F$5:$F$23<=K4)*(Staffing!$C$5:$C$23="Residential")*((Staffing!$D$5:$D$23*(K10/Assumptions!$C$13)+Staffing!$E$5:$E$23+ABS(Staffing!$D$5:$D$23*(K10/Assumptions!$C$13)-Staffing!$E$5:$E$23))/2)*Staffing!$I$5:$I$23*(1+Assumptions!$B$36*Staffing!$J$5:$J$23))/12 -> 6608.3333 | L25: =SUMPRODUCT((Staffing!$F$5:$F$23<=L4)*(Staffing!$C$5:$C$23="Residential")*((Staffing!$D$5:$D$23*(L10/Assumptions!$C$13)+Staffing!$E$5:$E$23+ABS(Staffing!$D$5:$D$23*(L10/Assumptions!$C$13)-Staffing!$E$5:$E$23))/2)*Staffing!$I$5:$I$23*(1+Assumptions!$B$36*Staffing!$J$5:$J$23))/12 -> 6608.3333 | M25: =SUMPRODUCT((Staffing!$F$5:$F$23<=M4)*(Staffing!$C$5:$C$23="Residential")*((Staffing!$D$5:$D$23*(M10/Assumptions!$C$13)+Staffing!$E$5:$E$23+ABS(Staffing!$D$5:$D$23*(M10/Assumptions!$C$13)-Staffing!$E$5:$E$23))/2)*Staffing!$I$5:$I$23*(1+Assumptions!$B$36*Staffing!$J$5:$J$23))/12 -> 8058.9431 | ... AO25: =SUMPRODUCT((Staffing!$F$5:$F$23<=AO4)*(Staffing!$C$5:$C$23="Residential")*((Staffing!$D$5:$D$23*(AO10/Assumptions!$C$13)+Staffing!$E$5:$E$23+ABS(Staffing!$D$5:$D$23*(AO10/Assumptions!$C$13)-Staffing!$E$5:$E$23))/2)*Staffing!$I$5:$I$23*(1+Assumptions!$B$36*Staffing!$J$5:$J$23))/12 -> 13700.203
A26: Day program census-driven roles | F26: =SUMPRODUCT((Staffing!$F$5:$F$23<=F4)*(Staffing!$C$5:$C$23="Day program")*((Staffing!$D$5:$D$23*((F12+F13)/(Assumptions!$C$15+Assumptions!$C$17))+Staffing!$E$5:$E$23+ABS(Staffing!$D$5:$D$23*((F12+F13)/(Assumptions!$C$15+Assumptions!$C$17))-Staffing!$E$5:$E$23))/2)*Staffing!$I$5:$I$23*(1+Assumptions!$B$36*Staffing!$J$5:$J$23))/12 -> 0 | G26: =SUMPRODUCT((Staffing!$F$5:$F$23<=G4)*(Staffing!$C$5:$C$23="Day program")*((Staffing!$D$5:$D$23*((G12+G13)/(Assumptions!$C$15+Assumptions!$C$17))+Staffing!$E$5:$E$23+ABS(Staffing!$D$5:$D$23*((G12+G13)/(Assumptions!$C$15+Assumptions!$C$17))-Staffing!$E$5:$E$23))/2)*Staffing!$I$5:$I$23*(1+Assumptions!$B$36*Staffing!$J$5:$J$23))/12 -> 0 | H26: =SUMPRODUCT((Staffing!$F$5:$F$23<=H4)*(Staffing!$C$5:$C$23="Day program")*((Staffing!$D$5:$D$23*((H12+H13)/(Assumptions!$C$15+Assumptions!$C$17))+Staffing!$E$5:$E$23+ABS(Staffing!$D$5:$D$23*((H12+H13)/(Assumptions!$C$15+Assumptions!$C$17))-Staffing!$E$5:$E$23))/2)*Staffing!$I$5:$I$23*(1+Assumptions!$B$36*Staffing!$J$5:$J$23))/12 -> 0 | I26: =SUMPRODUCT((Staffing!$F$5:$F$23<=I4)*(Staffing!$C$5:$C$23="Day program")*((Staffing!$D$5:$D$23*((I12+I13)/(Assumptions!$C$15+Assumptions!$C$17))+Staffing!$E$5:$E$23+ABS(Staffing!$D$5:$D$23*((I12+I13)/(Assumptions!$C$15+Assumptions!$C$17))-Staffing!$E$5:$E$23))/2)*Staffing!$I$5:$I$23*(1+Assumptions!$B$36*Staffing!$J$5:$J$23))/12 -> 0 | J26: =SUMPRODUCT((Staffing!$F$5:$F$23<=J4)*(Staffing!$C$5:$C$23="Day program")*((Staffing!$D$5:$D$23*((J12+J13)/(Assumptions!$C$15+Assumptions!$C$17))+Staffing!$E$5:$E$23+ABS(Staffing!$D$5:$D$23*((J12+J13)/(Assumptions!$C$15+Assumptions!$C$17))-Staffing!$E$5:$E$23))/2)*Staffing!$I$5:$I$23*(1+Assumptions!$B$36*Staffing!$J$5:$J$23))/12 -> 0 | K26: =SUMPRODUCT((Staffing!$F$5:$F$23<=K4)*(Staffing!$C$5:$C$23="Day program")*((Staffing!$D$5:$D$23*((K12+K13)/(Assumptions!$C$15+Assumptions!$C$17))+Staffing!$E$5:$E$23+ABS(Staffing!$D$5:$D$23*((K12+K13)/(Assumptions!$C$15+Assumptions!$C$17))-Staffing!$E$5:$E$23))/2)*Staffing!$I$5:$I$23*(1+Assumptions!$B$36*Staffing!$J$5:$J$23))/12 -> 0 | L26: =SUMPRODUCT((Staffing!$F$5:$F$23<=L4)*(Staffing!$C$5:$C$23="Day program")*((Staffing!$D$5:$D$23*((L12+L13)/(Assumptions!$C$15+Assumptions!$C$17))+Staffing!$E$5:$E$23+ABS(Staffing!$D$5:$D$23*((L12+L13)/(Assumptions!$C$15+Assumptions!$C$17))-Staffing!$E$5:$E$23))/2)*Staffing!$I$5:$I$23*(1+Assumptions!$B$36*Staffing!$J$5:$J$23))/12 -> 0 | M26: =SUMPRODUCT((Staffing!$F$5:$F$23<=M4)*(Staffing!$C$5:$C$23="Day program")*((Staffing!$D$5:$D$23*((M12+M13)/(Assumptions!$C$15+Assumptions!$C$17))+Staffing!$E$5:$E$23+ABS(Staffing!$D$5:$D$23*((M12+M13)/(Assumptions!$C$15+Assumptions!$C$17))-Staffing!$E$5:$E$23))/2)*Staffing!$I$5:$I$23*(1+Assumptions!$B$36*Staffing!$J$5:$J$23))/12 -> 6608.3333 | ... AO26: =SUMPRODUCT((Staffing!$F$5:$F$23<=AO4)*(Staffing!$C$5:$C$23="Day program")*((Staffing!$D$5:$D$23*((AO12+AO13)/(Assumptions!$C$15+Assumptions!$C$17))+Staffing!$E$5:$E$23+ABS(Staffing!$D$5:$D$23*((AO12+AO13)/(Assumptions!$C$15+Assumptions!$C$17))-Staffing!$E$5:$E$23))/2)*Staffing!$I$5:$I$23*(1+Assumptions!$B$36*Staffing!$J$5:$J$23))/12 -> 13216.667
A27: Outpatient census-driven roles | F27: =SUMPRODUCT((Staffing!$F$5:$F$23<=F4)*(Staffing!$C$5:$C$23="Outpatient")*((Staffing!$D$5:$D$23*(F14/Assumptions!$C$19)+Staffing!$E$5:$E$23+ABS(Staffing!$D$5:$D$23*(F14/Assumptions!$C$19)-Staffing!$E$5:$E$23))/2)*Staffing!$I$5:$I$23*(1+Assumptions!$B$36*Staffing!$J$5:$J$23))/12 -> 0 | G27: =SUMPRODUCT((Staffing!$F$5:$F$23<=G4)*(Staffing!$C$5:$C$23="Outpatient")*((Staffing!$D$5:$D$23*(G14/Assumptions!$C$19)+Staffing!$E$5:$E$23+ABS(Staffing!$D$5:$D$23*(G14/Assumptions!$C$19)-Staffing!$E$5:$E$23))/2)*Staffing!$I$5:$I$23*(1+Assumptions!$B$36*Staffing!$J$5:$J$23))/12 -> 0 | H27: =SUMPRODUCT((Staffing!$F$5:$F$23<=H4)*(Staffing!$C$5:$C$23="Outpatient")*((Staffing!$D$5:$D$23*(H14/Assumptions!$C$19)+Staffing!$E$5:$E$23+ABS(Staffing!$D$5:$D$23*(H14/Assumptions!$C$19)-Staffing!$E$5:$E$23))/2)*Staffing!$I$5:$I$23*(1+Assumptions!$B$36*Staffing!$J$5:$J$23))/12 -> 0 | I27: =SUMPRODUCT((Staffing!$F$5:$F$23<=I4)*(Staffing!$C$5:$C$23="Outpatient")*((Staffing!$D$5:$D$23*(I14/Assumptions!$C$19)+Staffing!$E$5:$E$23+ABS(Staffing!$D$5:$D$23*(I14/Assumptions!$C$19)-Staffing!$E$5:$E$23))/2)*Staffing!$I$5:$I$23*(1+Assumptions!$B$36*Staffing!$J$5:$J$23))/12 -> 0 | J27: =SUMPRODUCT((Staffing!$F$5:$F$23<=J4)*(Staffing!$C$5:$C$23="Outpatient")*((Staffing!$D$5:$D$23*(J14/Assumptions!$C$19)+Staffing!$E$5:$E$23+ABS(Staffing!$D$5:$D$23*(J14/Assumptions!$C$19)-Staffing!$E$5:$E$23))/2)*Staffing!$I$5:$I$23*(1+Assumptions!$B$36*Staffing!$J$5:$J$23))/12 -> 0 | K27: =SUMPRODUCT((Staffing!$F$5:$F$23<=K4)*(Staffing!$C$5:$C$23="Outpatient")*((Staffing!$D$5:$D$23*(K14/Assumptions!$C$19)+Staffing!$E$5:$E$23+ABS(Staffing!$D$5:$D$23*(K14/Assumptions!$C$19)-Staffing!$E$5:$E$23))/2)*Staffing!$I$5:$I$23*(1+Assumptions!$B$36*Staffing!$J$5:$J$23))/12 -> 0 | L27: =SUMPRODUCT((Staffing!$F$5:$F$23<=L4)*(Staffing!$C$5:$C$23="Outpatient")*((Staffing!$D$5:$D$23*(L14/Assumptions!$C$19)+Staffing!$E$5:$E$23+ABS(Staffing!$D$5:$D$23*(L14/Assumptions!$C$19)-Staffing!$E$5:$E$23))/2)*Staffing!$I$5:$I$23*(1+Assumptions!$B$36*Staffing!$J$5:$J$23))/12 -> 0 | M27: =SUMPRODUCT((Staffing!$F$5:$F$23<=M4)*(Staffing!$C$5:$C$23="Outpatient")*((Staffing!$D$5:$D$23*(M14/Assumptions!$C$19)+Staffing!$E$5:$E$23+ABS(Staffing!$D$5:$D$23*(M14/Assumptions!$C$19)-Staffing!$E$5:$E$23))/2)*Staffing!$I$5:$I$23*(1+Assumptions!$B$36*Staffing!$J$5:$J$23))/12 -> 0 | ... AO27: =SUMPRODUCT((Staffing!$F$5:$F$23<=AO4)*(Staffing!$C$5:$C$23="Outpatient")*((Staffing!$D$5:$D$23*(AO14/Assumptions!$C$19)+Staffing!$E$5:$E$23+ABS(Staffing!$D$5:$D$23*(AO14/Assumptions!$C$19)-Staffing!$E$5:$E$23))/2)*Staffing!$I$5:$I$23*(1+Assumptions!$B$36*Staffing!$J$5:$J$23))/12 -> 0
A28: Total payroll incl. burden, PRN/OT and inflation | F28: =SUM(F24:F27)*F7*(1+Assumptions!$C$37) -> 22366.667 | G28: =SUM(G24:G27)*G7*(1+Assumptions!$C$37) -> 22366.667 | H28: =SUM(H24:H27)*H7*(1+Assumptions!$C$37) -> 42496.667 | I28: =SUM(I24:I27)*I7*(1+Assumptions!$C$37) -> 54239.167 | J28: =SUM(J24:J27)*J7*(1+Assumptions!$C$37) -> 202820.93 | K28: =SUM(K24:K27)*K7*(1+Assumptions!$C$37) -> 202820.93 | L28: =SUM(L24:L27)*L7*(1+Assumptions!$C$37) -> 202820.93 | M28: =SUM(M24:M27)*M7*(1+Assumptions!$C$37) -> 211685.77 | ... AO28: =SUM(AO24:AO27)*AO7*(1+Assumptions!$C$37) -> 238872.59
A29: OPERATING EXPENSES
A30: Rent | F30: =IF(F6>=0,Assumptions!$C$39*F7,IF(F4>=Assumptions!$C$41,Assumptions!$C$39*Assumptions!$C$40,0)) -> 0 | G30: =IF(G6>=0,Assumptions!$C$39*G7,IF(G4>=Assumptions!$C$41,Assumptions!$C$39*Assumptions!$C$40,0)) -> 0 | H30: =IF(H6>=0,Assumptions!$C$39*H7,IF(H4>=Assumptions!$C$41,Assumptions!$C$39*Assumptions!$C$40,0)) -> 22500 | I30: =IF(I6>=0,Assumptions!$C$39*I7,IF(I4>=Assumptions!$C$41,Assumptions!$C$39*Assumptions!$C$40,0)) -> 22500 | J30: =IF(J6>=0,Assumptions!$C$39*J7,IF(J4>=Assumptions!$C$41,Assumptions!$C$39*Assumptions!$C$40,0)) -> 22500 | K30: =IF(K6>=0,Assumptions!$C$39*K7,IF(K4>=Assumptions!$C$41,Assumptions!$C$39*Assumptions!$C$40,0)) -> 45000 | L30: =IF(L6>=0,Assumptions!$C$39*L7,IF(L4>=Assumptions!$C$41,Assumptions!$C$39*Assumptions!$C$40,0)) -> 45000 | M30: =IF(M6>=0,Assumptions!$C$39*M7,IF(M4>=Assumptions!$C$41,Assumptions!$C$39*Assumptions!$C$40,0)) -> 45000 | ... AO30: =IF(AO6>=0,Assumptions!$C$39*AO7,IF(AO4>=Assumptions!$C$41,Assumptions!$C$39*Assumptions!$C$40,0)) -> 47740.5
A31: Utilities | F31: =IF(F6>=0,Assumptions!$C$42*F7,IF(F4>=Assumptions!$C$44,Assumptions!$C$43,0)) -> 0 | G31: =IF(G6>=0,Assumptions!$C$42*G7,IF(G4>=Assumptions!$C$44,Assumptions!$C$43,0)) -> 0 | H31: =IF(H6>=0,Assumptions!$C$42*H7,IF(H4>=Assumptions!$C$44,Assumptions!$C$43,0)) -> 0 | I31: =IF(I6>=0,Assumptions!$C$42*I7,IF(I4>=Assumptions!$C$44,Assumptions!$C$43,0)) -> 4000 | J31: =IF(J6>=0,Assumptions!$C$42*J7,IF(J4>=Assumptions!$C$44,Assumptions!$C$43,0)) -> 4000 | K31: =IF(K6>=0,Assumptions!$C$42*K7,IF(K4>=Assumptions!$C$44,Assumptions!$C$43,0)) -> 12000 | L31: =IF(L6>=0,Assumptions!$C$42*L7,IF(L4>=Assumptions!$C$44,Assumptions!$C$43,0)) -> 12000 | M31: =IF(M6>=0,Assumptions!$C$42*M7,IF(M4>=Assumptions!$C$44,Assumptions!$C$43,0)) -> 12000 | ... AO31: =IF(AO6>=0,Assumptions!$C$42*AO7,IF(AO4>=Assumptions!$C$44,Assumptions!$C$43,0)) -> 12730.8
A32: Food | F32: =F11*Assumptions!$C$45 -> 0 | G32: =G11*Assumptions!$C$45 -> 0 | H32: =H11*Assumptions!$C$45 -> 0 | I32: =I11*Assumptions!$C$45 -> 0 | J32: =J11*Assumptions!$C$45 -> 0 | K32: =K11*Assumptions!$C$45 -> 3040 | L32: =L11*Assumptions!$C$45 -> 4864 | M32: =M11*Assumptions!$C$45 -> 6080 | ... AO32: =AO11*Assumptions!$C$45 -> 10336
A33: Medical and program supplies | F33: =F11*Assumptions!$C$46+(F12*Assumptions!$C$9+F13*Assumptions!$C$10)*Assumptions!$C$47 -> 0 | G33: =G11*Assumptions!$C$46+(G12*Assumptions!$C$9+G13*Assumptions!$C$10)*Assumptions!$C$47 -> 0 | H33: =H11*Assumptions!$C$46+(H12*Assumptions!$C$9+H13*Assumptions!$C$10)*Assumptions!$C$47 -> 0 | I33: =I11*Assumptions!$C$46+(I12*Assumptions!$C$9+I13*Assumptions!$C$10)*Assumptions!$C$47 -> 0 | J33: =J11*Assumptions!$C$46+(J12*Assumptions!$C$9+J13*Assumptions!$C$10)*Assumptions!$C$47 -> 0 | K33: =K11*Assumptions!$C$46+(K12*Assumptions!$C$9+K13*Assumptions!$C$10)*Assumptions!$C$47 -> 3040 | L33: =L11*Assumptions!$C$46+(L12*Assumptions!$C$9+L13*Assumptions!$C$10)*Assumptions!$C$47 -> 4864 | M33: =M11*Assumptions!$C$46+(M12*Assumptions!$C$9+M13*Assumptions!$C$10)*Assumptions!$C$47 -> 6177.65 | ... AO33: =AO11*Assumptions!$C$46+(AO12*Assumptions!$C$9+AO13*Assumptions!$C$10)*Assumptions!$C$47 -> 11895.7
A34: Experiential and activity supplies | F34: =IF(F6>=0,Assumptions!$C$48,0) -> 0 | G34: =IF(G6>=0,Assumptions!$C$48,0) -> 0 | H34: =IF(H6>=0,Assumptions!$C$48,0) -> 0 | I34: =IF(I6>=0,Assumptions!$C$48,0) -> 0 | J34: =IF(J6>=0,Assumptions!$C$48,0) -> 0 | K34: =IF(K6>=0,Assumptions!$C$48,0) -> 3000 | L34: =IF(L6>=0,Assumptions!$C$48,0) -> 3000 | M34: =IF(M6>=0,Assumptions!$C$48,0) -> 3000 | ... AO34: =IF(AO6>=0,Assumptions!$C$48,0) -> 3000
A35: Contracted wellness services | F35: =IF(F6>=0,Assumptions!$C$49,0) -> 0 | G35: =IF(G6>=0,Assumptions!$C$49,0) -> 0 | H35: =IF(H6>=0,Assumptions!$C$49,0) -> 0 | I35: =IF(I6>=0,Assumptions!$C$49,0) -> 0 | J35: =IF(J6>=0,Assumptions!$C$49,0) -> 0 | K35: =IF(K6>=0,Assumptions!$C$49,0) -> 8000 | L35: =IF(L6>=0,Assumptions!$C$49,0) -> 8000 | M35: =IF(M6>=0,Assumptions!$C$49,0) -> 8000 | ... AO35: =IF(AO6>=0,Assumptions!$C$49,0) -> 8000
A36: Medical director stipend | F36: =IF(F4>=Assumptions!$C$51,Assumptions!$C$50,0) -> 0 | G36: =IF(G4>=Assumptions!$C$51,Assumptions!$C$50,0) -> 0 | H36: =IF(H4>=Assumptions!$C$51,Assumptions!$C$50,0) -> 5000 | I36: =IF(I4>=Assumptions!$C$51,Assumptions!$C$50,0) -> 5000 | J36: =IF(J4>=Assumptions!$C$51,Assumptions!$C$50,0) -> 5000 | K36: =IF(K4>=Assumptions!$C$51,Assumptions!$C$50,0) -> 5000 | L36: =IF(L4>=Assumptions!$C$51,Assumptions!$C$50,0) -> 5000 | M36: =IF(M4>=Assumptions!$C$51,Assumptions!$C$50,0) -> 5000 | ... AO36: =IF(AO4>=Assumptions!$C$51,Assumptions!$C$50,0) -> 5000
A37: Insurance | F37: =IF(F4>=Assumptions!$C$53,Assumptions!$C$52,0) -> 0 | G37: =IF(G4>=Assumptions!$C$53,Assumptions!$C$52,0) -> 0 | H37: =IF(H4>=Assumptions!$C$53,Assumptions!$C$52,0) -> 0 | I37: =IF(I4>=Assumptions!$C$53,Assumptions!$C$52,0) -> 12500 | J37: =IF(J4>=Assumptions!$C$53,Assumptions!$C$52,0) -> 12500 | K37: =IF(K4>=Assumptions!$C$53,Assumptions!$C$52,0) -> 12500 | L37: =IF(L4>=Assumptions!$C$53,Assumptions!$C$52,0) -> 12500 | M37: =IF(M4>=Assumptions!$C$53,Assumptions!$C$52,0) -> 12500 | ... AO37: =IF(AO4>=Assumptions!$C$53,Assumptions!$C$52,0) -> 12500
A38: Technology and EHR | F38: =IF(F4>=Assumptions!$C$55,Assumptions!$C$54,0) -> 0 | G38: =IF(G4>=Assumptions!$C$55,Assumptions!$C$54,0) -> 0 | H38: =IF(H4>=Assumptions!$C$55,Assumptions!$C$54,0) -> 10000 | I38: =IF(I4>=Assumptions!$C$55,Assumptions!$C$54,0) -> 10000 | J38: =IF(J4>=Assumptions!$C$55,Assumptions!$C$54,0) -> 10000 | K38: =IF(K4>=Assumptions!$C$55,Assumptions!$C$54,0) -> 10000 | L38: =IF(L4>=Assumptions!$C$55,Assumptions!$C$54,0) -> 10000 | M38: =IF(M4>=Assumptions!$C$55,Assumptions!$C$54,0) -> 10000 | ... AO38: =IF(AO4>=Assumptions!$C$55,Assumptions!$C$54,0) -> 10000
A39: Clearinghouse and billing software | F39: =IF(F6>=0,Assumptions!$C$56,0) -> 0 | G39: =IF(G6>=0,Assumptions!$C$56,0) -> 0 | H39: =IF(H6>=0,Assumptions!$C$56,0) -> 0 | I39: =IF(I6>=0,Assumptions!$C$56,0) -> 0 | J39: =IF(J6>=0,Assumptions!$C$56,0) -> 0 | K39: =IF(K6>=0,Assumptions!$C$56,0) -> 2500 | L39: =IF(L6>=0,Assumptions!$C$56,0) -> 2500 | M39: =IF(M6>=0,Assumptions!$C$56,0) -> 2500 | ... AO39: =IF(AO6>=0,Assumptions!$C$56,0) -> 2500
A40: Paid media (Google, Meta, directories) | F40: =IF(F6>=0,Assumptions!$C$57,IF(F4>=Assumptions!$C$59,Assumptions!$C$58,0)) -> 0 | G40: =IF(G6>=0,Assumptions!$C$57,IF(G4>=Assumptions!$C$59,Assumptions!$C$58,0)) -> 0 | H40: =IF(H6>=0,Assumptions!$C$57,IF(H4>=Assumptions!$C$59,Assumptions!$C$58,0)) -> 0 | I40: =IF(I6>=0,Assumptions!$C$57,IF(I4>=Assumptions!$C$59,Assumptions!$C$58,0)) -> 10000 | J40: =IF(J6>=0,Assumptions!$C$57,IF(J4>=Assumptions!$C$59,Assumptions!$C$58,0)) -> 10000 | K40: =IF(K6>=0,Assumptions!$C$57,IF(K4>=Assumptions!$C$59,Assumptions!$C$58,0)) -> 25000 | L40: =IF(L6>=0,Assumptions!$C$57,IF(L4>=Assumptions!$C$59,Assumptions!$C$58,0)) -> 25000 | M40: =IF(M6>=0,Assumptions!$C$57,IF(M4>=Assumptions!$C$59,Assumptions!$C$58,0)) -> 25000 | ... AO40: =IF(AO6>=0,Assumptions!$C$57,IF(AO4>=Assumptions!$C$59,Assumptions!$C$58,0)) -> 25000
A41: Marketing software | F41: =IF(F4>=Assumptions!$C$61,Assumptions!$C$60,0) -> 0 | G41: =IF(G4>=Assumptions!$C$61,Assumptions!$C$60,0) -> 3000 | H41: =IF(H4>=Assumptions!$C$61,Assumptions!$C$60,0) -> 3000 | I41: =IF(I4>=Assumptions!$C$61,Assumptions!$C$60,0) -> 3000 | J41: =IF(J4>=Assumptions!$C$61,Assumptions!$C$60,0) -> 3000 | K41: =IF(K4>=Assumptions!$C$61,Assumptions!$C$60,0) -> 3000 | L41: =IF(L4>=Assumptions!$C$61,Assumptions!$C$60,0) -> 3000 | M41: =IF(M4>=Assumptions!$C$61,Assumptions!$C$60,0) -> 3000 | ... AO41: =IF(AO4>=Assumptions!$C$61,Assumptions!$C$60,0) -> 3000
A42: Accreditation (survey, then annual fees) | F42: =IF(F4=Assumptions!$C$63,Assumptions!$C$62,0)+IF(F4>Assumptions!$C$63,Assumptions!$C$64/12,0) -> 0 | G42: =IF(G4=Assumptions!$C$63,Assumptions!$C$62,0)+IF(G4>Assumptions!$C$63,Assumptions!$C$64/12,0) -> 0 | H42: =IF(H4=Assumptions!$C$63,Assumptions!$C$62,0)+IF(H4>Assumptions!$C$63,Assumptions!$C$64/12,0) -> 0 | I42: =IF(I4=Assumptions!$C$63,Assumptions!$C$62,0)+IF(I4>Assumptions!$C$63,Assumptions!$C$64/12,0) -> 0 | J42: =IF(J4=Assumptions!$C$63,Assumptions!$C$62,0)+IF(J4>Assumptions!$C$63,Assumptions!$C$64/12,0) -> 0 | K42: =IF(K4=Assumptions!$C$63,Assumptions!$C$62,0)+IF(K4>Assumptions!$C$63,Assumptions!$C$64/12,0) -> 0 | L42: =IF(L4=Assumptions!$C$63,Assumptions!$C$62,0)+IF(L4>Assumptions!$C$63,Assumptions!$C$64/12,0) -> 0 | M42: =IF(M4=Assumptions!$C$63,Assumptions!$C$62,0)+IF(M4>Assumptions!$C$63,Assumptions!$C$64/12,0) -> 0 | ... AO42: =IF(AO4=Assumptions!$C$63,Assumptions!$C$62,0)+IF(AO4>Assumptions!$C$63,Assumptions!$C$64/12,0) -> 833.33333
A43: Professional fees | F43: =IF(F6<0,Assumptions!$C$65,Assumptions!$C$66) -> 15000 | G43: =IF(G6<0,Assumptions!$C$65,Assumptions!$C$66) -> 15000 | H43: =IF(H6<0,Assumptions!$C$65,Assumptions!$C$66) -> 15000 | I43: =IF(I6<0,Assumptions!$C$65,Assumptions!$C$66) -> 15000 | J43: =IF(J6<0,Assumptions!$C$65,Assumptions!$C$66) -> 15000 | K43: =IF(K6<0,Assumptions!$C$65,Assumptions!$C$66) -> 8000 | L43: =IF(L6<0,Assumptions!$C$65,Assumptions!$C$66) -> 8000 | M43: =IF(M6<0,Assumptions!$C$65,Assumptions!$C$66) -> 8000 | ... AO43: =IF(AO6<0,Assumptions!$C$65,Assumptions!$C$66) -> 8000
A44: Other operating | F44: =IF(F6>=0,Assumptions!$C$67,0) -> 0 | G44: =IF(G6>=0,Assumptions!$C$67,0) -> 0 | H44: =IF(H6>=0,Assumptions!$C$67,0) -> 0 | I44: =IF(I6>=0,Assumptions!$C$67,0) -> 0 | J44: =IF(J6>=0,Assumptions!$C$67,0) -> 0 | K44: =IF(K6>=0,Assumptions!$C$67,0) -> 12000 | L44: =IF(L6>=0,Assumptions!$C$67,0) -> 12000 | M44: =IF(M6>=0,Assumptions!$C$67,0) -> 12000 | ... AO44: =IF(AO6>=0,Assumptions!$C$67,0) -> 12000
A45: Total operating expenses | F45: =SUM(F30:F44) -> 15000 | G45: =SUM(G30:G44) -> 18000 | H45: =SUM(H30:H44) -> 55500 | I45: =SUM(I30:I44) -> 82000 | J45: =SUM(J30:J44) -> 82000 | K45: =SUM(K30:K44) -> 152080 | L45: =SUM(L30:L44) -> 155728 | M45: =SUM(M30:M44) -> 158257.65 | ... AO45: =SUM(AO30:AO44) -> 172536.33
A46: EBITDA | F46: =F22-F28-F45 -> -37366.667 | G46: =G22-G28-G45 -> -40366.667 | H46: =H22-H28-H45 -> -97996.667 | I46: =I22-I28-I45 -> -136239.17 | J46: =J22-J28-J45 -> -284820.93 | K46: =K22-K28-K45 -> -201076.93 | L46: =L22-L28-L45 -> -112430.53 | M46: =M22-M28-M45 -> -45825.121 | ... AO46: =AO22-AO28-AO45 -> 359049.1
A47: EBITDA margin | F47: =IF(F22=0,0,F46/F22) -> 0 | G47: =IF(G22=0,0,G46/G22) -> 0 | H47: =IF(H22=0,0,H46/H22) -> 0 | I47: =IF(I22=0,0,I46/I22) -> 0 | J47: =IF(J22=0,0,J46/J22) -> 0 | K47: =IF(K22=0,0,K46/K22) -> -1.3071883 | L47: =IF(L22=0,0,L46/L22) -> -0.45681482 | M47: =IF(M22=0,0,M46/M22) -> -0.14138394 | ... AO47: =IF(AO22=0,0,AO46/AO22) -> 0.46602033
A48: CASH FLOW
A49: Cash collected | F49: =F22*Assumptions!$C$31+E22*Assumptions!$C$32+D22*Assumptions!$C$33+C22*Assumptions!$C$34 -> 0 | G49: =G22*Assumptions!$C$31+F22*Assumptions!$C$32+E22*Assumptions!$C$33+D22*Assumptions!$C$34 -> 0 | H49: =H22*Assumptions!$C$31+G22*Assumptions!$C$32+F22*Assumptions!$C$33+E22*Assumptions!$C$34 -> 0 | I49: =I22*Assumptions!$C$31+H22*Assumptions!$C$32+G22*Assumptions!$C$33+F22*Assumptions!$C$34 -> 0 | J49: =J22*Assumptions!$C$31+I22*Assumptions!$C$32+H22*Assumptions!$C$33+G22*Assumptions!$C$34 -> 0 | K49: =K22*Assumptions!$C$31+J22*Assumptions!$C$32+I22*Assumptions!$C$33+H22*Assumptions!$C$34 -> 0 | L49: =L22*Assumptions!$C$31+K22*Assumptions!$C$32+J22*Assumptions!$C$33+I22*Assumptions!$C$34 -> 30764.8 | M49: =M22*Assumptions!$C$31+L22*Assumptions!$C$32+K22*Assumptions!$C$33+J22*Assumptions!$C$34 -> 133826.88 | ... AO49: =AO22*Assumptions!$C$31+AN22*Assumptions!$C$32+AM22*Assumptions!$C$33+AL22*Assumptions!$C$34 -> 770458.03
A50: One-time startup costs | F50: =IF(F4<=8,INDEX(Capital!$B$13:$I$13,F4),0) -> 145000 | G50: =IF(G4<=8,INDEX(Capital!$B$13:$I$13,G4),0) -> 175000 | H50: =IF(H4<=8,INDEX(Capital!$B$13:$I$13,H4),0) -> 245000 | I50: =IF(I4<=8,INDEX(Capital!$B$13:$I$13,I4),0) -> 325000 | J50: =IF(J4<=8,INDEX(Capital!$B$13:$I$13,J4),0) -> 370000 | K50: =IF(K4<=8,INDEX(Capital!$B$13:$I$13,K4),0) -> 15000 | L50: =IF(L4<=8,INDEX(Capital!$B$13:$I$13,L4),0) -> 0 | M50: =IF(M4<=8,INDEX(Capital!$B$13:$I$13,M4),0) -> 0 | ... AO50: =IF(AO4<=8,INDEX(Capital!$B$13:$I$13,AO4),0) -> 0
A51: Net cash flow | F51: =F49-F28-F45-F50 -> -182366.67 | G51: =G49-G28-G45-G50 -> -215366.67 | H51: =H49-H28-H45-H50 -> -342996.67 | I51: =I49-I28-I45-I50 -> -461239.17 | J51: =J49-J28-J45-J50 -> -654820.93 | K51: =K49-K28-K45-K50 -> -369900.93 | L51: =L49-L28-L45-L50 -> -327784.13 | M51: =M49-M28-M45-M50 -> -236116.54 | ... AO51: =AO49-AO28-AO45-AO50 -> 359049.1
A52: Cumulative cash flow | F52: =F51 -> -182366.67 | G52: =F52+G51 -> -397733.33 | H52: =G52+H51 -> -740730 | I52: =H52+I51 -> -1201969.2 | J52: =I52+J51 -> -1856790.1 | K52: =J52+K51 -> -2226691 | L52: =K52+L51 -> -2554475.2 | M52: =L52+M51 -> -2790591.7 | N52: =M52+N51 -> -2926279.5 | ... AO52: =AN52+AO51 -> 4643780.1
A53: Paid back flag (after trough, cumulative at or above zero) | F53: =IF(AND(F4>$B$57,F52>=0),1,0) -> 0 | G53: =IF(AND(G4>$B$57,G52>=0),1,0) -> 0 | H53: =IF(AND(H4>$B$57,H52>=0),1,0) -> 0 | I53: =IF(AND(I4>$B$57,I52>=0),1,0) -> 0 | J53: =IF(AND(J4>$B$57,J52>=0),1,0) -> 0 | K53: =IF(AND(K4>$B$57,K52>=0),1,0) -> 0 | L53: =IF(AND(L4>$B$57,L52>=0),1,0) -> 0 | M53: =IF(AND(M4>$B$57,M52>=0),1,0) -> 0 | ... AO53: =IF(AND(AO4>$B$57,AO52>=0),1,0) -> 1
A55: KEY RESULTS
A56: Peak capital need (lowest cumulative cash) | B56: =-MIN($F$52:$AO$52) -> 2986131.8
A57: Month of peak need | B57: =INDEX($F$4:$AO$4,MATCH(MIN($F$52:$AO$52),$F$52:$AO$52,0)) -> 11
A58: EBITDA positive from month (stays positive) | B58: =SUMPRODUCT(MAX(($F$46:$AO$46<0)*$F$4:$AO$4))+1 -> 9
A59: Cash flow positive from month (stays positive) | B59: =SUMPRODUCT(MAX(($F$51:$AO$51<0)*$F$4:$AO$4))+1 -> 12
A60: Cumulative cash payback month | B60: =IFERROR(INDEX($F$4:$AO$4,MATCH(1,$F$53:$AO$53,0)),"After M36") -> 23
A61: Cumulative cash at Month 36 | B61: =AO52 -> 4643780.1

Sheet Upside Monthly
A1: EverBloom: monthly model, Upside case
A2: All values in $ unless noted. Columns C-E are blank padding so collection lags work in the first months.
C3: (pad) | D3: (pad) | E3: (pad)
A4: Month | F4: 1 | G4: 2 | H4: 3 | I4: 4 | J4: 5 | K4: 6 | L4: 7 | M4: 8 | N4: 9 | O4: 10 | P4: 11 | Q4: 12 | R4: 13 | S4: 14 | T4: 15 | U4: 16 | V4: 17 | W4: 18 | X4: 19 | Y4: 20 | Z4: 21 | AA4: 22 | AB4: 23 | AC4: 24 | AD4: 25 | AE4: 26 | AF4: 27 | AG4: 28 | AH4: 29 | AI4: 30 | AJ4: 31 | AK4: 32 | AL4: 33 | AM4: 34 | AN4: 35 | AO4: 36
A5: Year | F5: =ROUNDUP(F4/12,0) -> 1 | G5: =ROUNDUP(G4/12,0) -> 1 | H5: =ROUNDUP(H4/12,0) -> 1 | I5: =ROUNDUP(I4/12,0) -> 1 | J5: =ROUNDUP(J4/12,0) -> 1 | K5: =ROUNDUP(K4/12,0) -> 1 | L5: =ROUNDUP(L4/12,0) -> 1 | M5: =ROUNDUP(M4/12,0) -> 1 | ... AO5: =ROUNDUP(AO4/12,0) -> 3
A6: Months since opening | F6: =F4-Assumptions!$D$7 -> -5 | G6: =G4-Assumptions!$D$7 -> -4 | H6: =H4-Assumptions!$D$7 -> -3 | I6: =I4-Assumptions!$D$7 -> -2 | J6: =J4-Assumptions!$D$7 -> -1 | K6: =K4-Assumptions!$D$7 -> 0 | L6: =L4-Assumptions!$D$7 -> 1 | M6: =M4-Assumptions!$D$7 -> 2 | ... AO6: =AO4-Assumptions!$D$7 -> 30
A7: Cost escalator | F7: =(1+Assumptions!$D$28)^(F5-1) -> 1 | G7: =(1+Assumptions!$D$28)^(G5-1) -> 1 | H7: =(1+Assumptions!$D$28)^(H5-1) -> 1 | I7: =(1+Assumptions!$D$28)^(I5-1) -> 1 | J7: =(1+Assumptions!$D$28)^(J5-1) -> 1 | K7: =(1+Assumptions!$D$28)^(K5-1) -> 1 | L7: =(1+Assumptions!$D$28)^(L5-1) -> 1 | M7: =(1+Assumptions!$D$28)^(M5-1) -> 1 | ... AO7: =(1+Assumptions!$D$28)^(AO5-1) -> 1.0609
A8: Rate escalator | F8: =IF(F4>24,1+Assumptions!$D$27,1) -> 1 | G8: =IF(G4>24,1+Assumptions!$D$27,1) -> 1 | H8: =IF(H4>24,1+Assumptions!$D$27,1) -> 1 | I8: =IF(I4>24,1+Assumptions!$D$27,1) -> 1 | J8: =IF(J4>24,1+Assumptions!$D$27,1) -> 1 | K8: =IF(K4>24,1+Assumptions!$D$27,1) -> 1 | L8: =IF(L4>24,1+Assumptions!$D$27,1) -> 1 | M8: =IF(M4>24,1+Assumptions!$D$27,1) -> 1 | ... AO8: =IF(AO4>24,1+Assumptions!$D$27,1) -> 1.03
A9: VOLUMES
A10: Residential occupancy | F10: =IF(F6<0,0,IF(F6<11,INDEX(Assumptions!$D$69:$D$79,F6+1),IF(F4>24,Assumptions!$D$14,Assumptions!$D$13))) -> 0 | G10: =IF(G6<0,0,IF(G6<11,INDEX(Assumptions!$D$69:$D$79,G6+1),IF(G4>24,Assumptions!$D$14,Assumptions!$D$13))) -> 0 | H10: =IF(H6<0,0,IF(H6<11,INDEX(Assumptions!$D$69:$D$79,H6+1),IF(H4>24,Assumptions!$D$14,Assumptions!$D$13))) -> 0 | I10: =IF(I6<0,0,IF(I6<11,INDEX(Assumptions!$D$69:$D$79,I6+1),IF(I4>24,Assumptions!$D$14,Assumptions!$D$13))) -> 0 | J10: =IF(J6<0,0,IF(J6<11,INDEX(Assumptions!$D$69:$D$79,J6+1),IF(J4>24,Assumptions!$D$14,Assumptions!$D$13))) -> 0 | K10: =IF(K6<0,0,IF(K6<11,INDEX(Assumptions!$D$69:$D$79,K6+1),IF(K4>24,Assumptions!$D$14,Assumptions!$D$13))) -> 0.3 | L10: =IF(L6<0,0,IF(L6<11,INDEX(Assumptions!$D$69:$D$79,L6+1),IF(L4>24,Assumptions!$D$14,Assumptions!$D$13))) -> 0.5 | M10: =IF(M6<0,0,IF(M6<11,INDEX(Assumptions!$D$69:$D$79,M6+1),IF(M4>24,Assumptions!$D$14,Assumptions!$D$13))) -> 0.62 | ... AO10: =IF(AO6<0,0,IF(AO6<11,INDEX(Assumptions!$D$69:$D$79,AO6+1),IF(AO4>24,Assumptions!$D$14,Assumptions!$D$13))) -> 0.88
A11: Residential patient days | F11: =Assumptions!$D$6*F10*Assumptions!$D$8 -> 0 | G11: =Assumptions!$D$6*G10*Assumptions!$D$8 -> 0 | H11: =Assumptions!$D$6*H10*Assumptions!$D$8 -> 0 | I11: =Assumptions!$D$6*I10*Assumptions!$D$8 -> 0 | J11: =Assumptions!$D$6*J10*Assumptions!$D$8 -> 0 | K11: =Assumptions!$D$6*K10*Assumptions!$D$8 -> 182.4 | L11: =Assumptions!$D$6*L10*Assumptions!$D$8 -> 304 | M11: =Assumptions!$D$6*M10*Assumptions!$D$8 -> 376.96 | ... AO11: =Assumptions!$D$6*AO10*Assumptions!$D$8 -> 535.04
A12: PHP average daily census | F12: =IF(F6-Assumptions!$D$21<0,0,Assumptions!$D$15*MIN(1,(F6-Assumptions!$D$21+1)/Assumptions!$D$22)) -> 0 | G12: =IF(G6-Assumptions!$D$21<0,0,Assumptions!$D$15*MIN(1,(G6-Assumptions!$D$21+1)/Assumptions!$D$22)) -> 0 | H12: =IF(H6-Assumptions!$D$21<0,0,Assumptions!$D$15*MIN(1,(H6-Assumptions!$D$21+1)/Assumptions!$D$22)) -> 0 | I12: =IF(I6-Assumptions!$D$21<0,0,Assumptions!$D$15*MIN(1,(I6-Assumptions!$D$21+1)/Assumptions!$D$22)) -> 0 | J12: =IF(J6-Assumptions!$D$21<0,0,Assumptions!$D$15*MIN(1,(J6-Assumptions!$D$21+1)/Assumptions!$D$22)) -> 0 | K12: =IF(K6-Assumptions!$D$21<0,0,Assumptions!$D$15*MIN(1,(K6-Assumptions!$D$21+1)/Assumptions!$D$22)) -> 0 | L12: =IF(L6-Assumptions!$D$21<0,0,Assumptions!$D$15*MIN(1,(L6-Assumptions!$D$21+1)/Assumptions!$D$22)) -> 0 | M12: =IF(M6-Assumptions!$D$21<0,0,Assumptions!$D$15*MIN(1,(M6-Assumptions!$D$21+1)/Assumptions!$D$22)) -> 1.875 | ... AO12: =IF(AO6-Assumptions!$D$21<0,0,Assumptions!$D$15*MIN(1,(AO6-Assumptions!$D$21+1)/Assumptions!$D$22)) -> 15
A13: IOP average daily census | F13: =IF(F6-Assumptions!$D$23<0,0,Assumptions!$D$17*MIN(1,(F6-Assumptions!$D$23+1)/Assumptions!$D$24)) -> 0 | G13: =IF(G6-Assumptions!$D$23<0,0,Assumptions!$D$17*MIN(1,(G6-Assumptions!$D$23+1)/Assumptions!$D$24)) -> 0 | H13: =IF(H6-Assumptions!$D$23<0,0,Assumptions!$D$17*MIN(1,(H6-Assumptions!$D$23+1)/Assumptions!$D$24)) -> 0 | I13: =IF(I6-Assumptions!$D$23<0,0,Assumptions!$D$17*MIN(1,(I6-Assumptions!$D$23+1)/Assumptions!$D$24)) -> 0 | J13: =IF(J6-Assumptions!$D$23<0,0,Assumptions!$D$17*MIN(1,(J6-Assumptions!$D$23+1)/Assumptions!$D$24)) -> 0 | K13: =IF(K6-Assumptions!$D$23<0,0,Assumptions!$D$17*MIN(1,(K6-Assumptions!$D$23+1)/Assumptions!$D$24)) -> 0 | L13: =IF(L6-Assumptions!$D$23<0,0,Assumptions!$D$17*MIN(1,(L6-Assumptions!$D$23+1)/Assumptions!$D$24)) -> 0 | M13: =IF(M6-Assumptions!$D$23<0,0,Assumptions!$D$17*MIN(1,(M6-Assumptions!$D$23+1)/Assumptions!$D$24)) -> 0 | ... AO13: =IF(AO6-Assumptions!$D$23<0,0,Assumptions!$D$17*MIN(1,(AO6-Assumptions!$D$23+1)/Assumptions!$D$24)) -> 20
A14: Outpatient visits | F14: =IF(F6-Assumptions!$D$25<0,0,Assumptions!$D$19*MIN(1,(F6-Assumptions!$D$25+1)/Assumptions!$D$26)) -> 0 | G14: =IF(G6-Assumptions!$D$25<0,0,Assumptions!$D$19*MIN(1,(G6-Assumptions!$D$25+1)/Assumptions!$D$26)) -> 0 | H14: =IF(H6-Assumptions!$D$25<0,0,Assumptions!$D$19*MIN(1,(H6-Assumptions!$D$25+1)/Assumptions!$D$26)) -> 0 | I14: =IF(I6-Assumptions!$D$25<0,0,Assumptions!$D$19*MIN(1,(I6-Assumptions!$D$25+1)/Assumptions!$D$26)) -> 0 | J14: =IF(J6-Assumptions!$D$25<0,0,Assumptions!$D$19*MIN(1,(J6-Assumptions!$D$25+1)/Assumptions!$D$26)) -> 0 | K14: =IF(K6-Assumptions!$D$25<0,0,Assumptions!$D$19*MIN(1,(K6-Assumptions!$D$25+1)/Assumptions!$D$26)) -> 0 | L14: =IF(L6-Assumptions!$D$25<0,0,Assumptions!$D$19*MIN(1,(L6-Assumptions!$D$25+1)/Assumptions!$D$26)) -> 0 | M14: =IF(M6-Assumptions!$D$25<0,0,Assumptions!$D$19*MIN(1,(M6-Assumptions!$D$25+1)/Assumptions!$D$26)) -> 0 | ... AO14: =IF(AO6-Assumptions!$D$25<0,0,Assumptions!$D$19*MIN(1,(AO6-Assumptions!$D$25+1)/Assumptions!$D$26)) -> 280
A15: REVENUE (billed, net of contractual adjustments)
A16: Residential | F16: =F11*Assumptions!$D$12*F8 -> 0 | G16: =G11*Assumptions!$D$12*G8 -> 0 | H16: =H11*Assumptions!$D$12*H8 -> 0 | I16: =I11*Assumptions!$D$12*I8 -> 0 | J16: =J11*Assumptions!$D$12*J8 -> 0 | K16: =K11*Assumptions!$D$12*K8 -> 237120 | L16: =L11*Assumptions!$D$12*L8 -> 395200 | M16: =M11*Assumptions!$D$12*M8 -> 490048 | ... AO16: =AO11*Assumptions!$D$12*AO8 -> 716418.56
A17: PHP | F17: =F12*Assumptions!$D$9*Assumptions!$D$16*F8 -> 0 | G17: =G12*Assumptions!$D$9*Assumptions!$D$16*G8 -> 0 | H17: =H12*Assumptions!$D$9*Assumptions!$D$16*H8 -> 0 | I17: =I12*Assumptions!$D$9*Assumptions!$D$16*I8 -> 0 | J17: =J12*Assumptions!$D$9*Assumptions!$D$16*J8 -> 0 | K17: =K12*Assumptions!$D$9*Assumptions!$D$16*K8 -> 0 | L17: =L12*Assumptions!$D$9*Assumptions!$D$16*L8 -> 0 | M17: =M12*Assumptions!$D$9*Assumptions!$D$16*M8 -> 25429.688 | ... AO17: =AO12*Assumptions!$D$9*Assumptions!$D$16*AO8 -> 209540.62
A18: IOP | F18: =F13*Assumptions!$D$10*Assumptions!$D$18*F8 -> 0 | G18: =G13*Assumptions!$D$10*Assumptions!$D$18*G8 -> 0 | H18: =H13*Assumptions!$D$10*Assumptions!$D$18*H8 -> 0 | I18: =I13*Assumptions!$D$10*Assumptions!$D$18*I8 -> 0 | J18: =J13*Assumptions!$D$10*Assumptions!$D$18*J8 -> 0 | K18: =K13*Assumptions!$D$10*Assumptions!$D$18*K8 -> 0 | L18: =L13*Assumptions!$D$10*Assumptions!$D$18*L8 -> 0 | M18: =M13*Assumptions!$D$10*Assumptions!$D$18*M8 -> 0 | ... AO18: =AO13*Assumptions!$D$10*Assumptions!$D$18*AO8 -> 110477.8
A19: Outpatient | F19: =F14*Assumptions!$D$20*F8 -> 0 | G19: =G14*Assumptions!$D$20*G8 -> 0 | H19: =H14*Assumptions!$D$20*H8 -> 0 | I19: =I14*Assumptions!$D$20*I8 -> 0 | J19: =J14*Assumptions!$D$20*J8 -> 0 | K19: =K14*Assumptions!$D$20*K8 -> 0 | L19: =L14*Assumptions!$D$20*L8 -> 0 | M19: =M14*Assumptions!$D$20*M8 -> 0 | ... AO19: =AO14*Assumptions!$D$20*AO8 -> 43260
A20: Gross billed revenue | F20: =SUM(F16:F19) -> 0 | G20: =SUM(G16:G19) -> 0 | H20: =SUM(H16:H19) -> 0 | I20: =SUM(I16:I19) -> 0 | J20: =SUM(J16:J19) -> 0 | K20: =SUM(K16:K19) -> 237120 | L20: =SUM(L16:L19) -> 395200 | M20: =SUM(M16:M19) -> 515477.69 | ... AO20: =SUM(AO16:AO19) -> 1079697
A21: Less denials and bad debt | F21: =-F20*Assumptions!$D$30 -> 0 | G21: =-G20*Assumptions!$D$30 -> 0 | H21: =-H20*Assumptions!$D$30 -> 0 | I21: =-I20*Assumptions!$D$30 -> 0 | J21: =-J20*Assumptions!$D$30 -> 0 | K21: =-K20*Assumptions!$D$30 -> -18969.6 | L21: =-L20*Assumptions!$D$30 -> -31616 | M21: =-M20*Assumptions!$D$30 -> -41238.215 | ... AO21: =-AO20*Assumptions!$D$30 -> -86375.759
A22: Net revenue | C22: 0 | D22: 0 | E22: 0 | F22: =F20+F21 -> 0 | G22: =G20+G21 -> 0 | H22: =H20+H21 -> 0 | I22: =I20+I21 -> 0 | J22: =J20+J21 -> 0 | K22: =K20+K21 -> 218150.4 | L22: =L20+L21 -> 363584 | M22: =M20+M21 -> 474239.47 | ... AO22: =AO20+AO21 -> 993321.23
A23: PAYROLL
A24: Fixed roles (leadership, RCM, admissions, marketing, nursing, support) | F24: =SUMPRODUCT((Staffing!$F$5:$F$23<=F4)*(Staffing!$C$5:$C$23="Fixed")*Staffing!$D$5:$D$23*Staffing!$I$5:$I$23*(1+Assumptions!$B$36*Staffing!$J$5:$J$23))/12 -> 20333.333 | G24: =SUMPRODUCT((Staffing!$F$5:$F$23<=G4)*(Staffing!$C$5:$C$23="Fixed")*Staffing!$D$5:$D$23*Staffing!$I$5:$I$23*(1+Assumptions!$B$36*Staffing!$J$5:$J$23))/12 -> 20333.333 | H24: =SUMPRODUCT((Staffing!$F$5:$F$23<=H4)*(Staffing!$C$5:$C$23="Fixed")*Staffing!$D$5:$D$23*Staffing!$I$5:$I$23*(1+Assumptions!$B$36*Staffing!$J$5:$J$23))/12 -> 38633.333 | I24: =SUMPRODUCT((Staffing!$F$5:$F$23<=I4)*(Staffing!$C$5:$C$23="Fixed")*Staffing!$D$5:$D$23*Staffing!$I$5:$I$23*(1+Assumptions!$B$36*Staffing!$J$5:$J$23))/12 -> 49308.333 | J24: =SUMPRODUCT((Staffing!$F$5:$F$23<=J4)*(Staffing!$C$5:$C$23="Fixed")*Staffing!$D$5:$D$23*Staffing!$I$5:$I$23*(1+Assumptions!$B$36*Staffing!$J$5:$J$23))/12 -> 177774.33 | K24: =SUMPRODUCT((Staffing!$F$5:$F$23<=K4)*(Staffing!$C$5:$C$23="Fixed")*Staffing!$D$5:$D$23*Staffing!$I$5:$I$23*(1+Assumptions!$B$36*Staffing!$J$5:$J$23))/12 -> 177774.33 | L24: =SUMPRODUCT((Staffing!$F$5:$F$23<=L4)*(Staffing!$C$5:$C$23="Fixed")*Staffing!$D$5:$D$23*Staffing!$I$5:$I$23*(1+Assumptions!$B$36*Staffing!$J$5:$J$23))/12 -> 177774.33 | M24: =SUMPRODUCT((Staffing!$F$5:$F$23<=M4)*(Staffing!$C$5:$C$23="Fixed")*Staffing!$D$5:$D$23*Staffing!$I$5:$I$23*(1+Assumptions!$B$36*Staffing!$J$5:$J$23))/12 -> 177774.33 | ... AO24: =SUMPRODUCT((Staffing!$F$5:$F$23<=AO4)*(Staffing!$C$5:$C$23="Fixed")*Staffing!$D$5:$D$23*Staffing!$I$5:$I$23*(1+Assumptions!$B$36*Staffing!$J$5:$J$23))/12 -> 177774.33
A25: Residential census-driven roles (techs, therapists) | F25: =SUMPRODUCT((Staffing!$F$5:$F$23<=F4)*(Staffing!$C$5:$C$23="Residential")*((Staffing!$D$5:$D$23*(F10/Assumptions!$D$13)+Staffing!$E$5:$E$23+ABS(Staffing!$D$5:$D$23*(F10/Assumptions!$D$13)-Staffing!$E$5:$E$23))/2)*Staffing!$I$5:$I$23*(1+Assumptions!$B$36*Staffing!$J$5:$J$23))/12 -> 0 | G25: =SUMPRODUCT((Staffing!$F$5:$F$23<=G4)*(Staffing!$C$5:$C$23="Residential")*((Staffing!$D$5:$D$23*(G10/Assumptions!$D$13)+Staffing!$E$5:$E$23+ABS(Staffing!$D$5:$D$23*(G10/Assumptions!$D$13)-Staffing!$E$5:$E$23))/2)*Staffing!$I$5:$I$23*(1+Assumptions!$B$36*Staffing!$J$5:$J$23))/12 -> 0 | H25: =SUMPRODUCT((Staffing!$F$5:$F$23<=H4)*(Staffing!$C$5:$C$23="Residential")*((Staffing!$D$5:$D$23*(H10/Assumptions!$D$13)+Staffing!$E$5:$E$23+ABS(Staffing!$D$5:$D$23*(H10/Assumptions!$D$13)-Staffing!$E$5:$E$23))/2)*Staffing!$I$5:$I$23*(1+Assumptions!$B$36*Staffing!$J$5:$J$23))/12 -> 0 | I25: =SUMPRODUCT((Staffing!$F$5:$F$23<=I4)*(Staffing!$C$5:$C$23="Residential")*((Staffing!$D$5:$D$23*(I10/Assumptions!$D$13)+Staffing!$E$5:$E$23+ABS(Staffing!$D$5:$D$23*(I10/Assumptions!$D$13)-Staffing!$E$5:$E$23))/2)*Staffing!$I$5:$I$23*(1+Assumptions!$B$36*Staffing!$J$5:$J$23))/12 -> 0 | J25: =SUMPRODUCT((Staffing!$F$5:$F$23<=J4)*(Staffing!$C$5:$C$23="Residential")*((Staffing!$D$5:$D$23*(J10/Assumptions!$D$13)+Staffing!$E$5:$E$23+ABS(Staffing!$D$5:$D$23*(J10/Assumptions!$D$13)-Staffing!$E$5:$E$23))/2)*Staffing!$I$5:$I$23*(1+Assumptions!$B$36*Staffing!$J$5:$J$23))/12 -> 6608.3333 | K25: =SUMPRODUCT((Staffing!$F$5:$F$23<=K4)*(Staffing!$C$5:$C$23="Residential")*((Staffing!$D$5:$D$23*(K10/Assumptions!$D$13)+Staffing!$E$5:$E$23+ABS(Staffing!$D$5:$D$23*(K10/Assumptions!$D$13)-Staffing!$E$5:$E$23))/2)*Staffing!$I$5:$I$23*(1+Assumptions!$B$36*Staffing!$J$5:$J$23))/12 -> 6608.3333 | L25: =SUMPRODUCT((Staffing!$F$5:$F$23<=L4)*(Staffing!$C$5:$C$23="Residential")*((Staffing!$D$5:$D$23*(L10/Assumptions!$D$13)+Staffing!$E$5:$E$23+ABS(Staffing!$D$5:$D$23*(L10/Assumptions!$D$13)-Staffing!$E$5:$E$23))/2)*Staffing!$I$5:$I$23*(1+Assumptions!$B$36*Staffing!$J$5:$J$23))/12 -> 7774.5098 | M25: =SUMPRODUCT((Staffing!$F$5:$F$23<=M4)*(Staffing!$C$5:$C$23="Residential")*((Staffing!$D$5:$D$23*(M10/Assumptions!$D$13)+Staffing!$E$5:$E$23+ABS(Staffing!$D$5:$D$23*(M10/Assumptions!$D$13)-Staffing!$E$5:$E$23))/2)*Staffing!$I$5:$I$23*(1+Assumptions!$B$36*Staffing!$J$5:$J$23))/12 -> 9640.3922 | ... AO25: =SUMPRODUCT((Staffing!$F$5:$F$23<=AO4)*(Staffing!$C$5:$C$23="Residential")*((Staffing!$D$5:$D$23*(AO10/Assumptions!$D$13)+Staffing!$E$5:$E$23+ABS(Staffing!$D$5:$D$23*(AO10/Assumptions!$D$13)-Staffing!$E$5:$E$23))/2)*Staffing!$I$5:$I$23*(1+Assumptions!$B$36*Staffing!$J$5:$J$23))/12 -> 13683.137
A26: Day program census-driven roles | F26: =SUMPRODUCT((Staffing!$F$5:$F$23<=F4)*(Staffing!$C$5:$C$23="Day program")*((Staffing!$D$5:$D$23*((F12+F13)/(Assumptions!$D$15+Assumptions!$D$17))+Staffing!$E$5:$E$23+ABS(Staffing!$D$5:$D$23*((F12+F13)/(Assumptions!$D$15+Assumptions!$D$17))-Staffing!$E$5:$E$23))/2)*Staffing!$I$5:$I$23*(1+Assumptions!$B$36*Staffing!$J$5:$J$23))/12 -> 0 | G26: =SUMPRODUCT((Staffing!$F$5:$F$23<=G4)*(Staffing!$C$5:$C$23="Day program")*((Staffing!$D$5:$D$23*((G12+G13)/(Assumptions!$D$15+Assumptions!$D$17))+Staffing!$E$5:$E$23+ABS(Staffing!$D$5:$D$23*((G12+G13)/(Assumptions!$D$15+Assumptions!$D$17))-Staffing!$E$5:$E$23))/2)*Staffing!$I$5:$I$23*(1+Assumptions!$B$36*Staffing!$J$5:$J$23))/12 -> 0 | H26: =SUMPRODUCT((Staffing!$F$5:$F$23<=H4)*(Staffing!$C$5:$C$23="Day program")*((Staffing!$D$5:$D$23*((H12+H13)/(Assumptions!$D$15+Assumptions!$D$17))+Staffing!$E$5:$E$23+ABS(Staffing!$D$5:$D$23*((H12+H13)/(Assumptions!$D$15+Assumptions!$D$17))-Staffing!$E$5:$E$23))/2)*Staffing!$I$5:$I$23*(1+Assumptions!$B$36*Staffing!$J$5:$J$23))/12 -> 0 | I26: =SUMPRODUCT((Staffing!$F$5:$F$23<=I4)*(Staffing!$C$5:$C$23="Day program")*((Staffing!$D$5:$D$23*((I12+I13)/(Assumptions!$D$15+Assumptions!$D$17))+Staffing!$E$5:$E$23+ABS(Staffing!$D$5:$D$23*((I12+I13)/(Assumptions!$D$15+Assumptions!$D$17))-Staffing!$E$5:$E$23))/2)*Staffing!$I$5:$I$23*(1+Assumptions!$B$36*Staffing!$J$5:$J$23))/12 -> 0 | J26: =SUMPRODUCT((Staffing!$F$5:$F$23<=J4)*(Staffing!$C$5:$C$23="Day program")*((Staffing!$D$5:$D$23*((J12+J13)/(Assumptions!$D$15+Assumptions!$D$17))+Staffing!$E$5:$E$23+ABS(Staffing!$D$5:$D$23*((J12+J13)/(Assumptions!$D$15+Assumptions!$D$17))-Staffing!$E$5:$E$23))/2)*Staffing!$I$5:$I$23*(1+Assumptions!$B$36*Staffing!$J$5:$J$23))/12 -> 0 | K26: =SUMPRODUCT((Staffing!$F$5:$F$23<=K4)*(Staffing!$C$5:$C$23="Day program")*((Staffing!$D$5:$D$23*((K12+K13)/(Assumptions!$D$15+Assumptions!$D$17))+Staffing!$E$5:$E$23+ABS(Staffing!$D$5:$D$23*((K12+K13)/(Assumptions!$D$15+Assumptions!$D$17))-Staffing!$E$5:$E$23))/2)*Staffing!$I$5:$I$23*(1+Assumptions!$B$36*Staffing!$J$5:$J$23))/12 -> 0 | L26: =SUMPRODUCT((Staffing!$F$5:$F$23<=L4)*(Staffing!$C$5:$C$23="Day program")*((Staffing!$D$5:$D$23*((L12+L13)/(Assumptions!$D$15+Assumptions!$D$17))+Staffing!$E$5:$E$23+ABS(Staffing!$D$5:$D$23*((L12+L13)/(Assumptions!$D$15+Assumptions!$D$17))-Staffing!$E$5:$E$23))/2)*Staffing!$I$5:$I$23*(1+Assumptions!$B$36*Staffing!$J$5:$J$23))/12 -> 0 | M26: =SUMPRODUCT((Staffing!$F$5:$F$23<=M4)*(Staffing!$C$5:$C$23="Day program")*((Staffing!$D$5:$D$23*((M12+M13)/(Assumptions!$D$15+Assumptions!$D$17))+Staffing!$E$5:$E$23+ABS(Staffing!$D$5:$D$23*((M12+M13)/(Assumptions!$D$15+Assumptions!$D$17))-Staffing!$E$5:$E$23))/2)*Staffing!$I$5:$I$23*(1+Assumptions!$B$36*Staffing!$J$5:$J$23))/12 -> 6608.3333 | ... AO26: =SUMPRODUCT((Staffing!$F$5:$F$23<=AO4)*(Staffing!$C$5:$C$23="Day program")*((Staffing!$D$5:$D$23*((AO12+AO13)/(Assumptions!$D$15+Assumptions!$D$17))+Staffing!$E$5:$E$23+ABS(Staffing!$D$5:$D$23*((AO12+AO13)/(Assumptions!$D$15+Assumptions!$D$17))-Staffing!$E$5:$E$23))/2)*Staffing!$I$5:$I$23*(1+Assumptions!$B$36*Staffing!$J$5:$J$23))/12 -> 13216.667
A27: Outpatient census-driven roles | F27: =SUMPRODUCT((Staffing!$F$5:$F$23<=F4)*(Staffing!$C$5:$C$23="Outpatient")*((Staffing!$D$5:$D$23*(F14/Assumptions!$D$19)+Staffing!$E$5:$E$23+ABS(Staffing!$D$5:$D$23*(F14/Assumptions!$D$19)-Staffing!$E$5:$E$23))/2)*Staffing!$I$5:$I$23*(1+Assumptions!$B$36*Staffing!$J$5:$J$23))/12 -> 0 | G27: =SUMPRODUCT((Staffing!$F$5:$F$23<=G4)*(Staffing!$C$5:$C$23="Outpatient")*((Staffing!$D$5:$D$23*(G14/Assumptions!$D$19)+Staffing!$E$5:$E$23+ABS(Staffing!$D$5:$D$23*(G14/Assumptions!$D$19)-Staffing!$E$5:$E$23))/2)*Staffing!$I$5:$I$23*(1+Assumptions!$B$36*Staffing!$J$5:$J$23))/12 -> 0 | H27: =SUMPRODUCT((Staffing!$F$5:$F$23<=H4)*(Staffing!$C$5:$C$23="Outpatient")*((Staffing!$D$5:$D$23*(H14/Assumptions!$D$19)+Staffing!$E$5:$E$23+ABS(Staffing!$D$5:$D$23*(H14/Assumptions!$D$19)-Staffing!$E$5:$E$23))/2)*Staffing!$I$5:$I$23*(1+Assumptions!$B$36*Staffing!$J$5:$J$23))/12 -> 0 | I27: =SUMPRODUCT((Staffing!$F$5:$F$23<=I4)*(Staffing!$C$5:$C$23="Outpatient")*((Staffing!$D$5:$D$23*(I14/Assumptions!$D$19)+Staffing!$E$5:$E$23+ABS(Staffing!$D$5:$D$23*(I14/Assumptions!$D$19)-Staffing!$E$5:$E$23))/2)*Staffing!$I$5:$I$23*(1+Assumptions!$B$36*Staffing!$J$5:$J$23))/12 -> 0 | J27: =SUMPRODUCT((Staffing!$F$5:$F$23<=J4)*(Staffing!$C$5:$C$23="Outpatient")*((Staffing!$D$5:$D$23*(J14/Assumptions!$D$19)+Staffing!$E$5:$E$23+ABS(Staffing!$D$5:$D$23*(J14/Assumptions!$D$19)-Staffing!$E$5:$E$23))/2)*Staffing!$I$5:$I$23*(1+Assumptions!$B$36*Staffing!$J$5:$J$23))/12 -> 0 | K27: =SUMPRODUCT((Staffing!$F$5:$F$23<=K4)*(Staffing!$C$5:$C$23="Outpatient")*((Staffing!$D$5:$D$23*(K14/Assumptions!$D$19)+Staffing!$E$5:$E$23+ABS(Staffing!$D$5:$D$23*(K14/Assumptions!$D$19)-Staffing!$E$5:$E$23))/2)*Staffing!$I$5:$I$23*(1+Assumptions!$B$36*Staffing!$J$5:$J$23))/12 -> 0 | L27: =SUMPRODUCT((Staffing!$F$5:$F$23<=L4)*(Staffing!$C$5:$C$23="Outpatient")*((Staffing!$D$5:$D$23*(L14/Assumptions!$D$19)+Staffing!$E$5:$E$23+ABS(Staffing!$D$5:$D$23*(L14/Assumptions!$D$19)-Staffing!$E$5:$E$23))/2)*Staffing!$I$5:$I$23*(1+Assumptions!$B$36*Staffing!$J$5:$J$23))/12 -> 0 | M27: =SUMPRODUCT((Staffing!$F$5:$F$23<=M4)*(Staffing!$C$5:$C$23="Outpatient")*((Staffing!$D$5:$D$23*(M14/Assumptions!$D$19)+Staffing!$E$5:$E$23+ABS(Staffing!$D$5:$D$23*(M14/Assumptions!$D$19)-Staffing!$E$5:$E$23))/2)*Staffing!$I$5:$I$23*(1+Assumptions!$B$36*Staffing!$J$5:$J$23))/12 -> 0 | ... AO27: =SUMPRODUCT((Staffing!$F$5:$F$23<=AO4)*(Staffing!$C$5:$C$23="Outpatient")*((Staffing!$D$5:$D$23*(AO14/Assumptions!$D$19)+Staffing!$E$5:$E$23+ABS(Staffing!$D$5:$D$23*(AO14/Assumptions!$D$19)-Staffing!$E$5:$E$23))/2)*Staffing!$I$5:$I$23*(1+Assumptions!$B$36*Staffing!$J$5:$J$23))/12 -> 0
A28: Total payroll incl. burden, PRN/OT and inflation | F28: =SUM(F24:F27)*F7*(1+Assumptions!$D$37) -> 22366.667 | G28: =SUM(G24:G27)*G7*(1+Assumptions!$D$37) -> 22366.667 | H28: =SUM(H24:H27)*H7*(1+Assumptions!$D$37) -> 42496.667 | I28: =SUM(I24:I27)*I7*(1+Assumptions!$D$37) -> 54239.167 | J28: =SUM(J24:J27)*J7*(1+Assumptions!$D$37) -> 202820.93 | K28: =SUM(K24:K27)*K7*(1+Assumptions!$D$37) -> 202820.93 | L28: =SUM(L24:L27)*L7*(1+Assumptions!$D$37) -> 204103.73 | M28: =SUM(M24:M27)*M7*(1+Assumptions!$D$37) -> 213425.36 | ... AO28: =SUM(AO24:AO27)*AO7*(1+Assumptions!$D$37) -> 238852.67
A29: OPERATING EXPENSES
A30: Rent | F30: =IF(F6>=0,Assumptions!$D$39*F7,IF(F4>=Assumptions!$D$41,Assumptions!$D$39*Assumptions!$D$40,0)) -> 0 | G30: =IF(G6>=0,Assumptions!$D$39*G7,IF(G4>=Assumptions!$D$41,Assumptions!$D$39*Assumptions!$D$40,0)) -> 0 | H30: =IF(H6>=0,Assumptions!$D$39*H7,IF(H4>=Assumptions!$D$41,Assumptions!$D$39*Assumptions!$D$40,0)) -> 22500 | I30: =IF(I6>=0,Assumptions!$D$39*I7,IF(I4>=Assumptions!$D$41,Assumptions!$D$39*Assumptions!$D$40,0)) -> 22500 | J30: =IF(J6>=0,Assumptions!$D$39*J7,IF(J4>=Assumptions!$D$41,Assumptions!$D$39*Assumptions!$D$40,0)) -> 22500 | K30: =IF(K6>=0,Assumptions!$D$39*K7,IF(K4>=Assumptions!$D$41,Assumptions!$D$39*Assumptions!$D$40,0)) -> 45000 | L30: =IF(L6>=0,Assumptions!$D$39*L7,IF(L4>=Assumptions!$D$41,Assumptions!$D$39*Assumptions!$D$40,0)) -> 45000 | M30: =IF(M6>=0,Assumptions!$D$39*M7,IF(M4>=Assumptions!$D$41,Assumptions!$D$39*Assumptions!$D$40,0)) -> 45000 | ... AO30: =IF(AO6>=0,Assumptions!$D$39*AO7,IF(AO4>=Assumptions!$D$41,Assumptions!$D$39*Assumptions!$D$40,0)) -> 47740.5
A31: Utilities | F31: =IF(F6>=0,Assumptions!$D$42*F7,IF(F4>=Assumptions!$D$44,Assumptions!$D$43,0)) -> 0 | G31: =IF(G6>=0,Assumptions!$D$42*G7,IF(G4>=Assumptions!$D$44,Assumptions!$D$43,0)) -> 0 | H31: =IF(H6>=0,Assumptions!$D$42*H7,IF(H4>=Assumptions!$D$44,Assumptions!$D$43,0)) -> 0 | I31: =IF(I6>=0,Assumptions!$D$42*I7,IF(I4>=Assumptions!$D$44,Assumptions!$D$43,0)) -> 4000 | J31: =IF(J6>=0,Assumptions!$D$42*J7,IF(J4>=Assumptions!$D$44,Assumptions!$D$43,0)) -> 4000 | K31: =IF(K6>=0,Assumptions!$D$42*K7,IF(K4>=Assumptions!$D$44,Assumptions!$D$43,0)) -> 12000 | L31: =IF(L6>=0,Assumptions!$D$42*L7,IF(L4>=Assumptions!$D$44,Assumptions!$D$43,0)) -> 12000 | M31: =IF(M6>=0,Assumptions!$D$42*M7,IF(M4>=Assumptions!$D$44,Assumptions!$D$43,0)) -> 12000 | ... AO31: =IF(AO6>=0,Assumptions!$D$42*AO7,IF(AO4>=Assumptions!$D$44,Assumptions!$D$43,0)) -> 12730.8
A32: Food | F32: =F11*Assumptions!$D$45 -> 0 | G32: =G11*Assumptions!$D$45 -> 0 | H32: =H11*Assumptions!$D$45 -> 0 | I32: =I11*Assumptions!$D$45 -> 0 | J32: =J11*Assumptions!$D$45 -> 0 | K32: =K11*Assumptions!$D$45 -> 3648 | L32: =L11*Assumptions!$D$45 -> 6080 | M32: =M11*Assumptions!$D$45 -> 7539.2 | ... AO32: =AO11*Assumptions!$D$45 -> 10700.8
A33: Medical and program supplies | F33: =F11*Assumptions!$D$46+(F12*Assumptions!$D$9+F13*Assumptions!$D$10)*Assumptions!$D$47 -> 0 | G33: =G11*Assumptions!$D$46+(G12*Assumptions!$D$9+G13*Assumptions!$D$10)*Assumptions!$D$47 -> 0 | H33: =H11*Assumptions!$D$46+(H12*Assumptions!$D$9+H13*Assumptions!$D$10)*Assumptions!$D$47 -> 0 | I33: =I11*Assumptions!$D$46+(I12*Assumptions!$D$9+I13*Assumptions!$D$10)*Assumptions!$D$47 -> 0 | J33: =J11*Assumptions!$D$46+(J12*Assumptions!$D$9+J13*Assumptions!$D$10)*Assumptions!$D$47 -> 0 | K33: =K11*Assumptions!$D$46+(K12*Assumptions!$D$9+K13*Assumptions!$D$10)*Assumptions!$D$47 -> 3648 | L33: =L11*Assumptions!$D$46+(L12*Assumptions!$D$9+L13*Assumptions!$D$10)*Assumptions!$D$47 -> 6080 | M33: =M11*Assumptions!$D$46+(M12*Assumptions!$D$9+M13*Assumptions!$D$10)*Assumptions!$D$47 -> 7661.2625 | ... AO33: =AO11*Assumptions!$D$46+(AO12*Assumptions!$D$9+AO13*Assumptions!$D$10)*Assumptions!$D$47 -> 12715.3
A34: Experiential and activity supplies | F34: =IF(F6>=0,Assumptions!$D$48,0) -> 0 | G34: =IF(G6>=0,Assumptions!$D$48,0) -> 0 | H34: =IF(H6>=0,Assumptions!$D$48,0) -> 0 | I34: =IF(I6>=0,Assumptions!$D$48,0) -> 0 | J34: =IF(J6>=0,Assumptions!$D$48,0) -> 0 | K34: =IF(K6>=0,Assumptions!$D$48,0) -> 3000 | L34: =IF(L6>=0,Assumptions!$D$48,0) -> 3000 | M34: =IF(M6>=0,Assumptions!$D$48,0) -> 3000 | ... AO34: =IF(AO6>=0,Assumptions!$D$48,0) -> 3000
A35: Contracted wellness services | F35: =IF(F6>=0,Assumptions!$D$49,0) -> 0 | G35: =IF(G6>=0,Assumptions!$D$49,0) -> 0 | H35: =IF(H6>=0,Assumptions!$D$49,0) -> 0 | I35: =IF(I6>=0,Assumptions!$D$49,0) -> 0 | J35: =IF(J6>=0,Assumptions!$D$49,0) -> 0 | K35: =IF(K6>=0,Assumptions!$D$49,0) -> 8000 | L35: =IF(L6>=0,Assumptions!$D$49,0) -> 8000 | M35: =IF(M6>=0,Assumptions!$D$49,0) -> 8000 | ... AO35: =IF(AO6>=0,Assumptions!$D$49,0) -> 8000
A36: Medical director stipend | F36: =IF(F4>=Assumptions!$D$51,Assumptions!$D$50,0) -> 0 | G36: =IF(G4>=Assumptions!$D$51,Assumptions!$D$50,0) -> 0 | H36: =IF(H4>=Assumptions!$D$51,Assumptions!$D$50,0) -> 5000 | I36: =IF(I4>=Assumptions!$D$51,Assumptions!$D$50,0) -> 5000 | J36: =IF(J4>=Assumptions!$D$51,Assumptions!$D$50,0) -> 5000 | K36: =IF(K4>=Assumptions!$D$51,Assumptions!$D$50,0) -> 5000 | L36: =IF(L4>=Assumptions!$D$51,Assumptions!$D$50,0) -> 5000 | M36: =IF(M4>=Assumptions!$D$51,Assumptions!$D$50,0) -> 5000 | ... AO36: =IF(AO4>=Assumptions!$D$51,Assumptions!$D$50,0) -> 5000
A37: Insurance | F37: =IF(F4>=Assumptions!$D$53,Assumptions!$D$52,0) -> 0 | G37: =IF(G4>=Assumptions!$D$53,Assumptions!$D$52,0) -> 0 | H37: =IF(H4>=Assumptions!$D$53,Assumptions!$D$52,0) -> 0 | I37: =IF(I4>=Assumptions!$D$53,Assumptions!$D$52,0) -> 12500 | J37: =IF(J4>=Assumptions!$D$53,Assumptions!$D$52,0) -> 12500 | K37: =IF(K4>=Assumptions!$D$53,Assumptions!$D$52,0) -> 12500 | L37: =IF(L4>=Assumptions!$D$53,Assumptions!$D$52,0) -> 12500 | M37: =IF(M4>=Assumptions!$D$53,Assumptions!$D$52,0) -> 12500 | ... AO37: =IF(AO4>=Assumptions!$D$53,Assumptions!$D$52,0) -> 12500
A38: Technology and EHR | F38: =IF(F4>=Assumptions!$D$55,Assumptions!$D$54,0) -> 0 | G38: =IF(G4>=Assumptions!$D$55,Assumptions!$D$54,0) -> 0 | H38: =IF(H4>=Assumptions!$D$55,Assumptions!$D$54,0) -> 10000 | I38: =IF(I4>=Assumptions!$D$55,Assumptions!$D$54,0) -> 10000 | J38: =IF(J4>=Assumptions!$D$55,Assumptions!$D$54,0) -> 10000 | K38: =IF(K4>=Assumptions!$D$55,Assumptions!$D$54,0) -> 10000 | L38: =IF(L4>=Assumptions!$D$55,Assumptions!$D$54,0) -> 10000 | M38: =IF(M4>=Assumptions!$D$55,Assumptions!$D$54,0) -> 10000 | ... AO38: =IF(AO4>=Assumptions!$D$55,Assumptions!$D$54,0) -> 10000
A39: Clearinghouse and billing software | F39: =IF(F6>=0,Assumptions!$D$56,0) -> 0 | G39: =IF(G6>=0,Assumptions!$D$56,0) -> 0 | H39: =IF(H6>=0,Assumptions!$D$56,0) -> 0 | I39: =IF(I6>=0,Assumptions!$D$56,0) -> 0 | J39: =IF(J6>=0,Assumptions!$D$56,0) -> 0 | K39: =IF(K6>=0,Assumptions!$D$56,0) -> 2500 | L39: =IF(L6>=0,Assumptions!$D$56,0) -> 2500 | M39: =IF(M6>=0,Assumptions!$D$56,0) -> 2500 | ... AO39: =IF(AO6>=0,Assumptions!$D$56,0) -> 2500
A40: Paid media (Google, Meta, directories) | F40: =IF(F6>=0,Assumptions!$D$57,IF(F4>=Assumptions!$D$59,Assumptions!$D$58,0)) -> 0 | G40: =IF(G6>=0,Assumptions!$D$57,IF(G4>=Assumptions!$D$59,Assumptions!$D$58,0)) -> 0 | H40: =IF(H6>=0,Assumptions!$D$57,IF(H4>=Assumptions!$D$59,Assumptions!$D$58,0)) -> 0 | I40: =IF(I6>=0,Assumptions!$D$57,IF(I4>=Assumptions!$D$59,Assumptions!$D$58,0)) -> 10000 | J40: =IF(J6>=0,Assumptions!$D$57,IF(J4>=Assumptions!$D$59,Assumptions!$D$58,0)) -> 10000 | K40: =IF(K6>=0,Assumptions!$D$57,IF(K4>=Assumptions!$D$59,Assumptions!$D$58,0)) -> 25000 | L40: =IF(L6>=0,Assumptions!$D$57,IF(L4>=Assumptions!$D$59,Assumptions!$D$58,0)) -> 25000 | M40: =IF(M6>=0,Assumptions!$D$57,IF(M4>=Assumptions!$D$59,Assumptions!$D$58,0)) -> 25000 | ... AO40: =IF(AO6>=0,Assumptions!$D$57,IF(AO4>=Assumptions!$D$59,Assumptions!$D$58,0)) -> 25000
A41: Marketing software | F41: =IF(F4>=Assumptions!$D$61,Assumptions!$D$60,0) -> 0 | G41: =IF(G4>=Assumptions!$D$61,Assumptions!$D$60,0) -> 3000 | H41: =IF(H4>=Assumptions!$D$61,Assumptions!$D$60,0) -> 3000 | I41: =IF(I4>=Assumptions!$D$61,Assumptions!$D$60,0) -> 3000 | J41: =IF(J4>=Assumptions!$D$61,Assumptions!$D$60,0) -> 3000 | K41: =IF(K4>=Assumptions!$D$61,Assumptions!$D$60,0) -> 3000 | L41: =IF(L4>=Assumptions!$D$61,Assumptions!$D$60,0) -> 3000 | M41: =IF(M4>=Assumptions!$D$61,Assumptions!$D$60,0) -> 3000 | ... AO41: =IF(AO4>=Assumptions!$D$61,Assumptions!$D$60,0) -> 3000
A42: Accreditation (survey, then annual fees) | F42: =IF(F4=Assumptions!$D$63,Assumptions!$D$62,0)+IF(F4>Assumptions!$D$63,Assumptions!$D$64/12,0) -> 0 | G42: =IF(G4=Assumptions!$D$63,Assumptions!$D$62,0)+IF(G4>Assumptions!$D$63,Assumptions!$D$64/12,0) -> 0 | H42: =IF(H4=Assumptions!$D$63,Assumptions!$D$62,0)+IF(H4>Assumptions!$D$63,Assumptions!$D$64/12,0) -> 0 | I42: =IF(I4=Assumptions!$D$63,Assumptions!$D$62,0)+IF(I4>Assumptions!$D$63,Assumptions!$D$64/12,0) -> 0 | J42: =IF(J4=Assumptions!$D$63,Assumptions!$D$62,0)+IF(J4>Assumptions!$D$63,Assumptions!$D$64/12,0) -> 0 | K42: =IF(K4=Assumptions!$D$63,Assumptions!$D$62,0)+IF(K4>Assumptions!$D$63,Assumptions!$D$64/12,0) -> 0 | L42: =IF(L4=Assumptions!$D$63,Assumptions!$D$62,0)+IF(L4>Assumptions!$D$63,Assumptions!$D$64/12,0) -> 0 | M42: =IF(M4=Assumptions!$D$63,Assumptions!$D$62,0)+IF(M4>Assumptions!$D$63,Assumptions!$D$64/12,0) -> 0 | ... AO42: =IF(AO4=Assumptions!$D$63,Assumptions!$D$62,0)+IF(AO4>Assumptions!$D$63,Assumptions!$D$64/12,0) -> 833.33333
A43: Professional fees | F43: =IF(F6<0,Assumptions!$D$65,Assumptions!$D$66) -> 15000 | G43: =IF(G6<0,Assumptions!$D$65,Assumptions!$D$66) -> 15000 | H43: =IF(H6<0,Assumptions!$D$65,Assumptions!$D$66) -> 15000 | I43: =IF(I6<0,Assumptions!$D$65,Assumptions!$D$66) -> 15000 | J43: =IF(J6<0,Assumptions!$D$65,Assumptions!$D$66) -> 15000 | K43: =IF(K6<0,Assumptions!$D$65,Assumptions!$D$66) -> 8000 | L43: =IF(L6<0,Assumptions!$D$65,Assumptions!$D$66) -> 8000 | M43: =IF(M6<0,Assumptions!$D$65,Assumptions!$D$66) -> 8000 | ... AO43: =IF(AO6<0,Assumptions!$D$65,Assumptions!$D$66) -> 8000
A44: Other operating | F44: =IF(F6>=0,Assumptions!$D$67,0) -> 0 | G44: =IF(G6>=0,Assumptions!$D$67,0) -> 0 | H44: =IF(H6>=0,Assumptions!$D$67,0) -> 0 | I44: =IF(I6>=0,Assumptions!$D$67,0) -> 0 | J44: =IF(J6>=0,Assumptions!$D$67,0) -> 0 | K44: =IF(K6>=0,Assumptions!$D$67,0) -> 12000 | L44: =IF(L6>=0,Assumptions!$D$67,0) -> 12000 | M44: =IF(M6>=0,Assumptions!$D$67,0) -> 12000 | ... AO44: =IF(AO6>=0,Assumptions!$D$67,0) -> 12000
A45: Total operating expenses | F45: =SUM(F30:F44) -> 15000 | G45: =SUM(G30:G44) -> 18000 | H45: =SUM(H30:H44) -> 55500 | I45: =SUM(I30:I44) -> 82000 | J45: =SUM(J30:J44) -> 82000 | K45: =SUM(K30:K44) -> 153296 | L45: =SUM(L30:L44) -> 158160 | M45: =SUM(M30:M44) -> 161200.46 | ... AO45: =SUM(AO30:AO44) -> 173720.73
A46: EBITDA | F46: =F22-F28-F45 -> -37366.667 | G46: =G22-G28-G45 -> -40366.667 | H46: =H22-H28-H45 -> -97996.667 | I46: =I22-I28-I45 -> -136239.17 | J46: =J22-J28-J45 -> -284820.93 | K46: =K22-K28-K45 -> -137966.53 | L46: =L22-L28-L45 -> 1320.2725 | M46: =M22-M28-M45 -> 99613.645 | ... AO46: =AO22-AO28-AO45 -> 580747.82
A47: EBITDA margin | F47: =IF(F22=0,0,F46/F22) -> 0 | G47: =IF(G22=0,0,G46/G22) -> 0 | H47: =IF(H22=0,0,H46/H22) -> 0 | I47: =IF(I22=0,0,I46/I22) -> 0 | J47: =IF(J22=0,0,J46/J22) -> 0 | K47: =IF(K22=0,0,K46/K22) -> -0.63243768 | L47: =IF(L22=0,0,L46/L22) -> 0.0036312724 | M47: =IF(M22=0,0,M46/M22) -> 0.21004925 | ... AO47: =IF(AO22=0,0,AO46/AO22) -> 0.58465258
A48: CASH FLOW
A49: Cash collected | F49: =F22*Assumptions!$D$31+E22*Assumptions!$D$32+D22*Assumptions!$D$33+C22*Assumptions!$D$34 -> 0 | G49: =G22*Assumptions!$D$31+F22*Assumptions!$D$32+E22*Assumptions!$D$33+D22*Assumptions!$D$34 -> 0 | H49: =H22*Assumptions!$D$31+G22*Assumptions!$D$32+F22*Assumptions!$D$33+E22*Assumptions!$D$34 -> 0 | I49: =I22*Assumptions!$D$31+H22*Assumptions!$D$32+G22*Assumptions!$D$33+F22*Assumptions!$D$34 -> 0 | J49: =J22*Assumptions!$D$31+I22*Assumptions!$D$32+H22*Assumptions!$D$33+G22*Assumptions!$D$34 -> 0 | K49: =K22*Assumptions!$D$31+J22*Assumptions!$D$32+I22*Assumptions!$D$33+H22*Assumptions!$D$34 -> 0 | L49: =L22*Assumptions!$D$31+K22*Assumptions!$D$32+J22*Assumptions!$D$33+I22*Assumptions!$D$34 -> 43630.08 | M49: =M22*Assumptions!$D$31+L22*Assumptions!$D$32+K22*Assumptions!$D$33+J22*Assumptions!$D$34 -> 192699.52 | ... AO49: =AO22*Assumptions!$D$31+AN22*Assumptions!$D$32+AM22*Assumptions!$D$33+AL22*Assumptions!$D$34 -> 993321.23
A50: One-time startup costs | F50: =IF(F4<=8,INDEX(Capital!$B$13:$I$13,F4),0) -> 145000 | G50: =IF(G4<=8,INDEX(Capital!$B$13:$I$13,G4),0) -> 175000 | H50: =IF(H4<=8,INDEX(Capital!$B$13:$I$13,H4),0) -> 245000 | I50: =IF(I4<=8,INDEX(Capital!$B$13:$I$13,I4),0) -> 325000 | J50: =IF(J4<=8,INDEX(Capital!$B$13:$I$13,J4),0) -> 370000 | K50: =IF(K4<=8,INDEX(Capital!$B$13:$I$13,K4),0) -> 15000 | L50: =IF(L4<=8,INDEX(Capital!$B$13:$I$13,L4),0) -> 0 | M50: =IF(M4<=8,INDEX(Capital!$B$13:$I$13,M4),0) -> 0 | ... AO50: =IF(AO4<=8,INDEX(Capital!$B$13:$I$13,AO4),0) -> 0
A51: Net cash flow | F51: =F49-F28-F45-F50 -> -182366.67 | G51: =G49-G28-G45-G50 -> -215366.67 | H51: =H49-H28-H45-H50 -> -342996.67 | I51: =I49-I28-I45-I50 -> -461239.17 | J51: =J49-J28-J45-J50 -> -654820.93 | K51: =K49-K28-K45-K50 -> -371116.93 | L51: =L49-L28-L45-L50 -> -318633.65 | M51: =M49-M28-M45-M50 -> -181926.31 | ... AO51: =AO49-AO28-AO45-AO50 -> 580747.82
A52: Cumulative cash flow | F52: =F51 -> -182366.67 | G52: =F52+G51 -> -397733.33 | H52: =G52+H51 -> -740730 | I52: =H52+I51 -> -1201969.2 | J52: =I52+J51 -> -1856790.1 | K52: =J52+K51 -> -2227907 | L52: =K52+L51 -> -2546540.7 | M52: =L52+M51 -> -2728467 | N52: =M52+N51 -> -2758115.9 | ... AO52: =AN52+AO51 -> 10465906
A53: Paid back flag (after trough, cumulative at or above zero) | F53: =IF(AND(F4>$B$57,F52>=0),1,0) -> 0 | G53: =IF(AND(G4>$B$57,G52>=0),1,0) -> 0 | H53: =IF(AND(H4>$B$57,H52>=0),1,0) -> 0 | I53: =IF(AND(I4>$B$57,I52>=0),1,0) -> 0 | J53: =IF(AND(J4>$B$57,J52>=0),1,0) -> 0 | K53: =IF(AND(K4>$B$57,K52>=0),1,0) -> 0 | L53: =IF(AND(L4>$B$57,L52>=0),1,0) -> 0 | M53: =IF(AND(M4>$B$57,M52>=0),1,0) -> 0 | ... AO53: =IF(AND(AO4>$B$57,AO52>=0),1,0) -> 1
A55: KEY RESULTS
A56: Peak capital need (lowest cumulative cash) | B56: =-MIN($F$52:$AO$52) -> 2758115.9
A57: Month of peak need | B57: =INDEX($F$4:$AO$4,MATCH(MIN($F$52:$AO$52),$F$52:$AO$52,0)) -> 9
A58: EBITDA positive from month (stays positive) | B58: =SUMPRODUCT(MAX(($F$46:$AO$46<0)*$F$4:$AO$4))+1 -> 7
A59: Cash flow positive from month (stays positive) | B59: =SUMPRODUCT(MAX(($F$51:$AO$51<0)*$F$4:$AO$4))+1 -> 10
A60: Cumulative cash payback month | B60: =IFERROR(INDEX($F$4:$AO$4,MATCH(1,$F$53:$AO$53,0)),"After M36") -> 18
A61: Cumulative cash at Month 36 | B61: =AO52 -> 10465906

Sheet Sensitivity
A1: Stabilized economics (base case, Year 2 cost levels)
A3: Fixed payroll per month (fixed roles) | B3: =SUMPRODUCT((Staffing!$C$5:$C$23="Fixed")*Staffing!$D$5:$D$23*Staffing!$I$5:$I$23*(1+Assumptions!$B$36*Staffing!$J$5:$J$23))/12*(1+Assumptions!$C$37) -> 195551.77
A4: Fixed operating costs per month | B4: =Assumptions!$C$39+Assumptions!$C$42+Assumptions!$C$48+Assumptions!$C$49+Assumptions!$C$50+Assumptions!$C$52+Assumptions!$C$54+Assumptions!$C$56+Assumptions!$C$57+Assumptions!$C$60+Assumptions!$C$64/12+Assumptions!$C$66+Assumptions!$C$67 -> 146833.33
A5: Total fixed costs per month | B5: =B3+B4 -> 342385.1
A6: Contribution per residential patient day | B6: =Assumptions!$C$12*(1-Assumptions!$C$30)-(SUMPRODUCT((Staffing!$C$5:$C$23="Residential")*Staffing!$D$5:$D$23*Staffing!$I$5:$I$23*(1+Assumptions!$B$36*Staffing!$J$5:$J$23))/12*(1+Assumptions!$C$37))/(Assumptions!$C$6*Assumptions!$C$13*Assumptions!$C$8)-Assumptions!$C$45-Assumptions!$C$46 -> 942.83935
A7: Step-down contribution per month (PHP+IOP+OP at target) | B7: =Assumptions!$C$15*Assumptions!$C$9*(Assumptions!$C$16*(1-Assumptions!$C$30)-Assumptions!$C$47)+Assumptions!$C$17*Assumptions!$C$10*(Assumptions!$C$18*(1-Assumptions!$C$30)-Assumptions!$C$47)+Assumptions!$C$19*Assumptions!$C$20*(1-Assumptions!$C$30)-SUMPRODUCT((Staffing!$C$5:$C$23="Day program")*Staffing!$D$5:$D$23*Staffing!$I$5:$I$23*(1+Assumptions!$B$36*Staffing!$J$5:$J$23))/12*(1+Assumptions!$C$37)-SUMPRODUCT((Staffing!$C$5:$C$23="Outpatient")*Staffing!$D$5:$D$23*Staffing!$I$5:$I$23*(1+Assumptions!$B$36*Staffing!$J$5:$J$23))/12*(1+Assumptions!$C$37) -> 208917.87
A8: Break-even occupancy, residential only | B8: =B5/B6/Assumptions!$C$8/Assumptions!$C$6 -> 0.59727396
A9: Break-even occupancy, with step-down programs | B9: =(B5-B7)/B6/Assumptions!$C$8/Assumptions!$C$6 -> 0.23282702
A12: Stabilized annual EBITDA by residential occupancy (rows) and daily rate (columns)
A13: Occupancy \ Rate | B13: 950 | C13: 1100 | D13: 1250
A14: 0.65 | B14: =(Assumptions!$C$6*$A14*Assumptions!$C$8*(B$13*(1-Assumptions!$C$30)-(SUMPRODUCT((Staffing!$C$5:$C$23="Residential")*Staffing!$D$5:$D$23*Staffing!$I$5:$I$23*(1+Assumptions!$B$36*Staffing!$J$5:$J$23))/12*(1+Assumptions!$C$37))/(Assumptions!$C$6*Assumptions!$C$13*Assumptions!$C$8)-Assumptions!$C$45-Assumptions!$C$46)+$B$7-$B$5)*12 -> 2215263.3 | C14: =(Assumptions!$C$6*$A14*Assumptions!$C$8*(C$13*(1-Assumptions!$C$30)-(SUMPRODUCT((Staffing!$C$5:$C$23="Residential")*Staffing!$D$5:$D$23*Staffing!$I$5:$I$23*(1+Assumptions!$B$36*Staffing!$J$5:$J$23))/12*(1+Assumptions!$C$37))/(Assumptions!$C$6*Assumptions!$C$13*Assumptions!$C$8)-Assumptions!$C$45-Assumptions!$C$46)+$B$7-$B$5)*12 -> 2869714.5 | D14: =(Assumptions!$C$6*$A14*Assumptions!$C$8*(D$13*(1-Assumptions!$C$30)-(SUMPRODUCT((Staffing!$C$5:$C$23="Residential")*Staffing!$D$5:$D$23*Staffing!$I$5:$I$23*(1+Assumptions!$B$36*Staffing!$J$5:$J$23))/12*(1+Assumptions!$C$37))/(Assumptions!$C$6*Assumptions!$C$13*Assumptions!$C$8)-Assumptions!$C$45-Assumptions!$C$46)+$B$7-$B$5)*12 -> 3524165.7
A15: 0.75 | B15: =(Assumptions!$C$6*$A15*Assumptions!$C$8*(B$13*(1-Assumptions!$C$30)-(SUMPRODUCT((Staffing!$C$5:$C$23="Residential")*Staffing!$D$5:$D$23*Staffing!$I$5:$I$23*(1+Assumptions!$B$36*Staffing!$J$5:$J$23))/12*(1+Assumptions!$C$37))/(Assumptions!$C$6*Assumptions!$C$13*Assumptions!$C$8)-Assumptions!$C$45-Assumptions!$C$46)+$B$7-$B$5)*12 -> 2802474.1 | C15: =(Assumptions!$C$6*$A15*Assumptions!$C$8*(C$13*(1-Assumptions!$C$30)-(SUMPRODUCT((Staffing!$C$5:$C$23="Residential")*Staffing!$D$5:$D$23*Staffing!$I$5:$I$23*(1+Assumptions!$B$36*Staffing!$J$5:$J$23))/12*(1+Assumptions!$C$37))/(Assumptions!$C$6*Assumptions!$C$13*Assumptions!$C$8)-Assumptions!$C$45-Assumptions!$C$46)+$B$7-$B$5)*12 -> 3557610.1 | D15: =(Assumptions!$C$6*$A15*Assumptions!$C$8*(D$13*(1-Assumptions!$C$30)-(SUMPRODUCT((Staffing!$C$5:$C$23="Residential")*Staffing!$D$5:$D$23*Staffing!$I$5:$I$23*(1+Assumptions!$B$36*Staffing!$J$5:$J$23))/12*(1+Assumptions!$C$37))/(Assumptions!$C$6*Assumptions!$C$13*Assumptions!$C$8)-Assumptions!$C$45-Assumptions!$C$46)+$B$7-$B$5)*12 -> 4312746.1
A16: 0.85 | B16: =(Assumptions!$C$6*$A16*Assumptions!$C$8*(B$13*(1-Assumptions!$C$30)-(SUMPRODUCT((Staffing!$C$5:$C$23="Residential")*Staffing!$D$5:$D$23*Staffing!$I$5:$I$23*(1+Assumptions!$B$36*Staffing!$J$5:$J$23))/12*(1+Assumptions!$C$37))/(Assumptions!$C$6*Assumptions!$C$13*Assumptions!$C$8)-Assumptions!$C$45-Assumptions!$C$46)+$B$7-$B$5)*12 -> 3389684.9 | C16: =(Assumptions!$C$6*$A16*Assumptions!$C$8*(C$13*(1-Assumptions!$C$30)-(SUMPRODUCT((Staffing!$C$5:$C$23="Residential")*Staffing!$D$5:$D$23*Staffing!$I$5:$I$23*(1+Assumptions!$B$36*Staffing!$J$5:$J$23))/12*(1+Assumptions!$C$37))/(Assumptions!$C$6*Assumptions!$C$13*Assumptions!$C$8)-Assumptions!$C$45-Assumptions!$C$46)+$B$7-$B$5)*12 -> 4245505.7 | D16: =(Assumptions!$C$6*$A16*Assumptions!$C$8*(D$13*(1-Assumptions!$C$30)-(SUMPRODUCT((Staffing!$C$5:$C$23="Residential")*Staffing!$D$5:$D$23*Staffing!$I$5:$I$23*(1+Assumptions!$B$36*Staffing!$J$5:$J$23))/12*(1+Assumptions!$C$37))/(Assumptions!$C$6*Assumptions!$C$13*Assumptions!$C$8)-Assumptions!$C$45-Assumptions!$C$46)+$B$7-$B$5)*12 -> 5101326.5
A18: Rates in row 13 and occupancies in column A are inputs. Census-driven staff scale linearly here (minimum-FTE floors ignored), so low-occupancy cells are slightly optimistic.
